[
{
"GEMEINDE": "Aeugst a.A.",
"BEZIRK": "Affoltern",
"STIMMBETEILIGUNG": "   82.08",
"AZ_GÜLTIGE_STIMMZETTEL": 133,
"AZ_JA_STIMMEN": 17
}
,
{
"GEMEINDE": "Affoltern a.A.",
"BEZIRK": "Affoltern",
"STIMMBETEILIGUNG": "   76.97",
"AZ_GÜLTIGE_STIMMZETTEL": 565,
"AZ_JA_STIMMEN": 143
}
,
{
"GEMEINDE": "Bonstetten",
"BEZIRK": "Affoltern",
"STIMMBETEILIGUNG": "   89.04",
"AZ_GÜLTIGE_STIMMZETTEL": 190,
"AZ_JA_STIMMEN": 51
}
,
{
"GEMEINDE": "Hausen a.A.",
"BEZIRK": "Affoltern",
"STIMMBETEILIGUNG": "   66.74",
"AZ_GÜLTIGE_STIMMZETTEL": 273,
"AZ_JA_STIMMEN": 44
}
,
{
"GEMEINDE": "Hedingen",
"BEZIRK": "Affoltern",
"STIMMBETEILIGUNG": "   83.75",
"AZ_GÜLTIGE_STIMMZETTEL": 212,
"AZ_JA_STIMMEN": 61
}
,
{
"GEMEINDE": "Kappel a.A.",
"BEZIRK": "Affoltern",
"STIMMBETEILIGUNG": "   82.39",
"AZ_GÜLTIGE_STIMMZETTEL": 116,
"AZ_JA_STIMMEN": 21
}
,
{
"GEMEINDE": "Knonau",
"BEZIRK": "Affoltern",
"STIMMBETEILIGUNG": "   68.51",
"AZ_GÜLTIGE_STIMMZETTEL": 107,
"AZ_JA_STIMMEN": 29
}
,
{
"GEMEINDE": "Maschwanden",
"BEZIRK": "Affoltern",
"STIMMBETEILIGUNG": "   79.10",
"AZ_GÜLTIGE_STIMMZETTEL": 95,
"AZ_JA_STIMMEN": 14
}
,
{
"GEMEINDE": "Mettmenstetten",
"BEZIRK": "Affoltern",
"STIMMBETEILIGUNG": "   77.14",
"AZ_GÜLTIGE_STIMMZETTEL": 301,
"AZ_JA_STIMMEN": 79
}
,
{
"GEMEINDE": "Obfelden",
"BEZIRK": "Affoltern",
"STIMMBETEILIGUNG": "   72.90",
"AZ_GÜLTIGE_STIMMZETTEL": 252,
"AZ_JA_STIMMEN": 66
}
,
{
"GEMEINDE": "Ottenbach",
"BEZIRK": "Affoltern",
"STIMMBETEILIGUNG": "   80.29",
"AZ_GÜLTIGE_STIMMZETTEL": 204,
"AZ_JA_STIMMEN": 51
}
,
{
"GEMEINDE": "Rifferswil",
"BEZIRK": "Affoltern",
"STIMMBETEILIGUNG": "   86.01",
"AZ_GÜLTIGE_STIMMZETTEL": 116,
"AZ_JA_STIMMEN": 29
}
,
{
"GEMEINDE": "Stallikon",
"BEZIRK": "Affoltern",
"STIMMBETEILIGUNG": "   75.39",
"AZ_GÜLTIGE_STIMMZETTEL": 132,
"AZ_JA_STIMMEN": 22
}
,
{
"GEMEINDE": "Wettswil a.A.",
"BEZIRK": "Affoltern",
"STIMMBETEILIGUNG": "   84.21",
"AZ_GÜLTIGE_STIMMZETTEL": 73,
"AZ_JA_STIMMEN": 18
}
,
{
"GEMEINDE": "Adlikon",
"BEZIRK": "Andelfingen",
"STIMMBETEILIGUNG": "   92.06",
"AZ_GÜLTIGE_STIMMZETTEL": 116,
"AZ_JA_STIMMEN": 26
}
,
{
"GEMEINDE": "Andelfingen",
"BEZIRK": "Andelfingen",
"STIMMBETEILIGUNG": "   82.69",
"AZ_GÜLTIGE_STIMMZETTEL": 198,
"AZ_JA_STIMMEN": 44
}
,
{
"GEMEINDE": "Benken",
"BEZIRK": "Andelfingen",
"STIMMBETEILIGUNG": "   92.41",
"AZ_GÜLTIGE_STIMMZETTEL": 115,
"AZ_JA_STIMMEN": 47
}
,
{
"GEMEINDE": "Berg a.I.",
"BEZIRK": "Andelfingen",
"STIMMBETEILIGUNG": "   98.44",
"AZ_GÜLTIGE_STIMMZETTEL": 117,
"AZ_JA_STIMMEN": 28
}
,
{
"GEMEINDE": "Buch a.I.",
"BEZIRK": "Andelfingen",
"STIMMBETEILIGUNG": "   87.41",
"AZ_GÜLTIGE_STIMMZETTEL": 111,
"AZ_JA_STIMMEN": 34
}
,
{
"GEMEINDE": "Dachsen",
"BEZIRK": "Andelfingen",
"STIMMBETEILIGUNG": "   85.55",
"AZ_GÜLTIGE_STIMMZETTEL": 129,
"AZ_JA_STIMMEN": 48
}
,
{
"GEMEINDE": "Dorf",
"BEZIRK": "Andelfingen",
"STIMMBETEILIGUNG": "   89.01",
"AZ_GÜLTIGE_STIMMZETTEL": 66,
"AZ_JA_STIMMEN": 19
}
,
{
"GEMEINDE": "Feuerthalen",
"BEZIRK": "Andelfingen",
"STIMMBETEILIGUNG": "   87.73",
"AZ_GÜLTIGE_STIMMZETTEL": 490,
"AZ_JA_STIMMEN": 118
}
,
{
"GEMEINDE": "Flaach",
"BEZIRK": "Andelfingen",
"STIMMBETEILIGUNG": "   93.14",
"AZ_GÜLTIGE_STIMMZETTEL": 180,
"AZ_JA_STIMMEN": 45
}
,
{
"GEMEINDE": "Flurlingen",
"BEZIRK": "Andelfingen",
"STIMMBETEILIGUNG": "   84.50",
"AZ_GÜLTIGE_STIMMZETTEL": 212,
"AZ_JA_STIMMEN": 60
}
,
{
"GEMEINDE": "Henggart",
"BEZIRK": "Andelfingen",
"STIMMBETEILIGUNG": "   73.20",
"AZ_GÜLTIGE_STIMMZETTEL": 111,
"AZ_JA_STIMMEN": 25
}
,
{
"GEMEINDE": "Humlikon",
"BEZIRK": "Andelfingen",
"STIMMBETEILIGUNG": "   91.89",
"AZ_GÜLTIGE_STIMMZETTEL": 61,
"AZ_JA_STIMMEN": 19
}
,
{
"GEMEINDE": "Kleinandelfingen",
"BEZIRK": "Andelfingen",
"STIMMBETEILIGUNG": "   86.38",
"AZ_GÜLTIGE_STIMMZETTEL": 242,
"AZ_JA_STIMMEN": 63
}
,
{
"GEMEINDE": "Laufen-Uhwiesen",
"BEZIRK": "Andelfingen",
"STIMMBETEILIGUNG": "   82.70",
"AZ_GÜLTIGE_STIMMZETTEL": 179,
"AZ_JA_STIMMEN": 63
}
,
{
"GEMEINDE": "Marthalen",
"BEZIRK": "Andelfingen",
"STIMMBETEILIGUNG": "   74.42",
"AZ_GÜLTIGE_STIMMZETTEL": 237,
"AZ_JA_STIMMEN": 65
}
,
{
"GEMEINDE": "Oberstammheim",
"BEZIRK": "Andelfingen",
"STIMMBETEILIGUNG": "   75.00",
"AZ_GÜLTIGE_STIMMZETTEL": 151,
"AZ_JA_STIMMEN": 28
}
,
{
"GEMEINDE": "Ossingen",
"BEZIRK": "Andelfingen",
"STIMMBETEILIGUNG": "   85.02",
"AZ_GÜLTIGE_STIMMZETTEL": 208,
"AZ_JA_STIMMEN": 60
}
,
{
"GEMEINDE": "Rheinau",
"BEZIRK": "Andelfingen",
"STIMMBETEILIGUNG": "   78.01",
"AZ_GÜLTIGE_STIMMZETTEL": 177,
"AZ_JA_STIMMEN": 50
}
,
{
"GEMEINDE": "Thalheim a.d.Th.",
"BEZIRK": "Andelfingen",
"STIMMBETEILIGUNG": "   95.65",
"AZ_GÜLTIGE_STIMMZETTEL": 117,
"AZ_JA_STIMMEN": 18
}
,
{
"GEMEINDE": "Trüllikon",
"BEZIRK": "Andelfingen",
"STIMMBETEILIGUNG": "   83.72",
"AZ_GÜLTIGE_STIMMZETTEL": 205,
"AZ_JA_STIMMEN": 73
}
,
{
"GEMEINDE": "Truttikon",
"BEZIRK": "Andelfingen",
"STIMMBETEILIGUNG": "   89.47",
"AZ_GÜLTIGE_STIMMZETTEL": 84,
"AZ_JA_STIMMEN": 24
}
,
{
"GEMEINDE": "Unterstammheim",
"BEZIRK": "Andelfingen",
"STIMMBETEILIGUNG": "   82.84",
"AZ_GÜLTIGE_STIMMZETTEL": 136,
"AZ_JA_STIMMEN": 20
}
,
{
"GEMEINDE": "Volken",
"BEZIRK": "Andelfingen",
"STIMMBETEILIGUNG": "   90.54",
"AZ_GÜLTIGE_STIMMZETTEL": 58,
"AZ_JA_STIMMEN": 18
}
,
{
"GEMEINDE": "Waltalingen",
"BEZIRK": "Andelfingen",
"STIMMBETEILIGUNG": "   92.64",
"AZ_GÜLTIGE_STIMMZETTEL": 146,
"AZ_JA_STIMMEN": 27
}
,
{
"GEMEINDE": "Bachenbülach",
"BEZIRK": "Bülach",
"STIMMBETEILIGUNG": "   87.34",
"AZ_GÜLTIGE_STIMMZETTEL": 127,
"AZ_JA_STIMMEN": 27
}
,
{
"GEMEINDE": "Bassersdorf",
"BEZIRK": "Bülach",
"STIMMBETEILIGUNG": "   78.44",
"AZ_GÜLTIGE_STIMMZETTEL": 271,
"AZ_JA_STIMMEN": 42
}
,
{
"GEMEINDE": "Bülach",
"BEZIRK": "Bülach",
"STIMMBETEILIGUNG": "   76.03",
"AZ_GÜLTIGE_STIMMZETTEL": 619,
"AZ_JA_STIMMEN": 107
}
,
{
"GEMEINDE": "Dietlikon",
"BEZIRK": "Bülach",
"STIMMBETEILIGUNG": "   65.13",
"AZ_GÜLTIGE_STIMMZETTEL": 146,
"AZ_JA_STIMMEN": 27
}
,
{
"GEMEINDE": "Eglisau",
"BEZIRK": "Bülach",
"STIMMBETEILIGUNG": "   58.73",
"AZ_GÜLTIGE_STIMMZETTEL": 182,
"AZ_JA_STIMMEN": 23
}
,
{
"GEMEINDE": "Embrach",
"BEZIRK": "Bülach",
"STIMMBETEILIGUNG": "   84.88",
"AZ_GÜLTIGE_STIMMZETTEL": 351,
"AZ_JA_STIMMEN": 53
}
,
{
"GEMEINDE": "Freienstein-Teufen",
"BEZIRK": "Bülach",
"STIMMBETEILIGUNG": "   88.41",
"AZ_GÜLTIGE_STIMMZETTEL": 246,
"AZ_JA_STIMMEN": 40
}
,
{
"GEMEINDE": "Glattfelden",
"BEZIRK": "Bülach",
"STIMMBETEILIGUNG": "   82.15",
"AZ_GÜLTIGE_STIMMZETTEL": 310,
"AZ_JA_STIMMEN": 49
}
,
{
"GEMEINDE": "Hochfelden",
"BEZIRK": "Bülach",
"STIMMBETEILIGUNG": "   82.55",
"AZ_GÜLTIGE_STIMMZETTEL": 109,
"AZ_JA_STIMMEN": 12
}
,
{
"GEMEINDE": "Höri",
"BEZIRK": "Bülach",
"STIMMBETEILIGUNG": "   81.82",
"AZ_GÜLTIGE_STIMMZETTEL": 113,
"AZ_JA_STIMMEN": 16
}
,
{
"GEMEINDE": "Hüntwangen",
"BEZIRK": "Bülach",
"STIMMBETEILIGUNG": "   90.91",
"AZ_GÜLTIGE_STIMMZETTEL": 115,
"AZ_JA_STIMMEN": 6
}
,
{
"GEMEINDE": "Kloten",
"BEZIRK": "Bülach",
"STIMMBETEILIGUNG": "   78.56",
"AZ_GÜLTIGE_STIMMZETTEL": 363,
"AZ_JA_STIMMEN": 63
}
,
{
"GEMEINDE": "Lufingen",
"BEZIRK": "Bülach",
"STIMMBETEILIGUNG": "   85.22",
"AZ_GÜLTIGE_STIMMZETTEL": 95,
"AZ_JA_STIMMEN": 13
}
,
{
"GEMEINDE": "Nürensdorf",
"BEZIRK": "Bülach",
"STIMMBETEILIGUNG": "   87.16",
"AZ_GÜLTIGE_STIMMZETTEL": 247,
"AZ_JA_STIMMEN": 35
}
,
{
"GEMEINDE": "Oberembrach",
"BEZIRK": "Bülach",
"STIMMBETEILIGUNG": "   91.52",
"AZ_GÜLTIGE_STIMMZETTEL": 141,
"AZ_JA_STIMMEN": 27
}
,
{
"GEMEINDE": "Opfikon",
"BEZIRK": "Bülach",
"STIMMBETEILIGUNG": "   72.95",
"AZ_GÜLTIGE_STIMMZETTEL": 227,
"AZ_JA_STIMMEN": 25
}
,
{
"GEMEINDE": "Rafz",
"BEZIRK": "Bülach",
"STIMMBETEILIGUNG": "   61.23",
"AZ_GÜLTIGE_STIMMZETTEL": 266,
"AZ_JA_STIMMEN": 45
}
,
{
"GEMEINDE": "Rorbas",
"BEZIRK": "Bülach",
"STIMMBETEILIGUNG": "   74.85",
"AZ_GÜLTIGE_STIMMZETTEL": 226,
"AZ_JA_STIMMEN": 28
}
,
{
"GEMEINDE": "Wallisellen",
"BEZIRK": "Bülach",
"STIMMBETEILIGUNG": "   65.97",
"AZ_GÜLTIGE_STIMMZETTEL": 578,
"AZ_JA_STIMMEN": 107
}
,
{
"GEMEINDE": "Wasterkingen",
"BEZIRK": "Bülach",
"STIMMBETEILIGUNG": "   89.53",
"AZ_GÜLTIGE_STIMMZETTEL": 70,
"AZ_JA_STIMMEN": 9
}
,
{
"GEMEINDE": "Wil",
"BEZIRK": "Bülach",
"STIMMBETEILIGUNG": "   87.50",
"AZ_GÜLTIGE_STIMMZETTEL": 161,
"AZ_JA_STIMMEN": 29
}
,
{
"GEMEINDE": "Winkel",
"BEZIRK": "Bülach",
"STIMMBETEILIGUNG": "   95.07",
"AZ_GÜLTIGE_STIMMZETTEL": 116,
"AZ_JA_STIMMEN": 17
}
,
{
"GEMEINDE": "Bachs",
"BEZIRK": "Dielsdorf",
"STIMMBETEILIGUNG": "   83.87",
"AZ_GÜLTIGE_STIMMZETTEL": 102,
"AZ_JA_STIMMEN": 13
}
,
{
"GEMEINDE": "Boppelsen",
"BEZIRK": "Dielsdorf",
"STIMMBETEILIGUNG": "   91.25",
"AZ_GÜLTIGE_STIMMZETTEL": 66,
"AZ_JA_STIMMEN": 7
}
,
{
"GEMEINDE": "Buchs",
"BEZIRK": "Dielsdorf",
"STIMMBETEILIGUNG": "   70.63",
"AZ_GÜLTIGE_STIMMZETTEL": 105,
"AZ_JA_STIMMEN": 22
}
,
{
"GEMEINDE": "Dällikon",
"BEZIRK": "Dielsdorf",
"STIMMBETEILIGUNG": "   76.15",
"AZ_GÜLTIGE_STIMMZETTEL": 76,
"AZ_JA_STIMMEN": 13
}
,
{
"GEMEINDE": "Dänikon",
"BEZIRK": "Dielsdorf",
"STIMMBETEILIGUNG": "   87.50",
"AZ_GÜLTIGE_STIMMZETTEL": 42,
"AZ_JA_STIMMEN": 10
}
,
{
"GEMEINDE": "Dielsdorf",
"BEZIRK": "Dielsdorf",
"STIMMBETEILIGUNG": "   73.31",
"AZ_GÜLTIGE_STIMMZETTEL": 161,
"AZ_JA_STIMMEN": 21
}
,
{
"GEMEINDE": "Hüttikon",
"BEZIRK": "Dielsdorf",
"STIMMBETEILIGUNG": "   85.71",
"AZ_GÜLTIGE_STIMMZETTEL": 29,
"AZ_JA_STIMMEN": 9
}
,
{
"GEMEINDE": "Neerach",
"BEZIRK": "Dielsdorf",
"STIMMBETEILIGUNG": "   78.71",
"AZ_GÜLTIGE_STIMMZETTEL": 108,
"AZ_JA_STIMMEN": 25
}
,
{
"GEMEINDE": "Niederglatt",
"BEZIRK": "Dielsdorf",
"STIMMBETEILIGUNG": "   81.11",
"AZ_GÜLTIGE_STIMMZETTEL": 138,
"AZ_JA_STIMMEN": 40
}
,
{
"GEMEINDE": "Niederhasli",
"BEZIRK": "Dielsdorf",
"STIMMBETEILIGUNG": "   75.09",
"AZ_GÜLTIGE_STIMMZETTEL": 195,
"AZ_JA_STIMMEN": 40
}
,
{
"GEMEINDE": "Niederweningen",
"BEZIRK": "Dielsdorf",
"STIMMBETEILIGUNG": "   71.84",
"AZ_GÜLTIGE_STIMMZETTEL": 138,
"AZ_JA_STIMMEN": 29
}
,
{
"GEMEINDE": "Oberglatt",
"BEZIRK": "Dielsdorf",
"STIMMBETEILIGUNG": "   62.13",
"AZ_GÜLTIGE_STIMMZETTEL": 141,
"AZ_JA_STIMMEN": 29
}
,
{
"GEMEINDE": "Oberweningen",
"BEZIRK": "Dielsdorf",
"STIMMBETEILIGUNG": "   86.25",
"AZ_GÜLTIGE_STIMMZETTEL": 59,
"AZ_JA_STIMMEN": 9
}
,
{
"GEMEINDE": "Otelfingen",
"BEZIRK": "Dielsdorf",
"STIMMBETEILIGUNG": "   60.12",
"AZ_GÜLTIGE_STIMMZETTEL": 95,
"AZ_JA_STIMMEN": 16
}
,
{
"GEMEINDE": "Regensberg",
"BEZIRK": "Dielsdorf",
"STIMMBETEILIGUNG": "   77.61",
"AZ_GÜLTIGE_STIMMZETTEL": 48,
"AZ_JA_STIMMEN": 12
}
,
{
"GEMEINDE": "Regensdorf",
"BEZIRK": "Dielsdorf",
"STIMMBETEILIGUNG": "   58.30",
"AZ_GÜLTIGE_STIMMZETTEL": 261,
"AZ_JA_STIMMEN": 65
}
,
{
"GEMEINDE": "Rümlang",
"BEZIRK": "Dielsdorf",
"STIMMBETEILIGUNG": "   78.05",
"AZ_GÜLTIGE_STIMMZETTEL": 246,
"AZ_JA_STIMMEN": 46
}
,
{
"GEMEINDE": "Schleinikon",
"BEZIRK": "Dielsdorf",
"STIMMBETEILIGUNG": "   77.57",
"AZ_GÜLTIGE_STIMMZETTEL": 80,
"AZ_JA_STIMMEN": 19
}
,
{
"GEMEINDE": "Schöfflisdorf",
"BEZIRK": "Dielsdorf",
"STIMMBETEILIGUNG": "   81.71",
"AZ_GÜLTIGE_STIMMZETTEL": 66,
"AZ_JA_STIMMEN": 11
}
,
{
"GEMEINDE": "Stadel",
"BEZIRK": "Dielsdorf",
"STIMMBETEILIGUNG": "   84.53",
"AZ_GÜLTIGE_STIMMZETTEL": 218,
"AZ_JA_STIMMEN": 57
}
,
{
"GEMEINDE": "Steinmaur",
"BEZIRK": "Dielsdorf",
"STIMMBETEILIGUNG": "   82.99",
"AZ_GÜLTIGE_STIMMZETTEL": 175,
"AZ_JA_STIMMEN": 30
}
,
{
"GEMEINDE": "Weiach",
"BEZIRK": "Dielsdorf",
"STIMMBETEILIGUNG": "   82.18",
"AZ_GÜLTIGE_STIMMZETTEL": 136,
"AZ_JA_STIMMEN": 22
}
,
{
"GEMEINDE": "Aesch",
"BEZIRK": "Dietikon",
"STIMMBETEILIGUNG": "   86.67",
"AZ_GÜLTIGE_STIMMZETTEL": 76,
"AZ_JA_STIMMEN": 10
}
,
{
"GEMEINDE": "Birmensdorf",
"BEZIRK": "Dietikon",
"STIMMBETEILIGUNG": "   81.87",
"AZ_GÜLTIGE_STIMMZETTEL": 286,
"AZ_JA_STIMMEN": 44
}
,
{
"GEMEINDE": "Dietikon",
"BEZIRK": "Dietikon",
"STIMMBETEILIGUNG": "   72.17",
"AZ_GÜLTIGE_STIMMZETTEL": 994,
"AZ_JA_STIMMEN": 305
}
,
{
"GEMEINDE": "Geroldswil",
"BEZIRK": "Dietikon",
"STIMMBETEILIGUNG": "   66.67",
"AZ_GÜLTIGE_STIMMZETTEL": 43,
"AZ_JA_STIMMEN": 14
}
,
{
"GEMEINDE": "Oberengstringen",
"BEZIRK": "Dietikon",
"STIMMBETEILIGUNG": "   67.26",
"AZ_GÜLTIGE_STIMMZETTEL": 108,
"AZ_JA_STIMMEN": 44
}
,
{
"GEMEINDE": "Oetwil a.d.L",
"BEZIRK": "Dietikon",
"STIMMBETEILIGUNG": "   77.94",
"AZ_GÜLTIGE_STIMMZETTEL": 51,
"AZ_JA_STIMMEN": 16
}
,
{
"GEMEINDE": "Schlieren",
"BEZIRK": "Dietikon",
"STIMMBETEILIGUNG": "   72.83",
"AZ_GÜLTIGE_STIMMZETTEL": 680,
"AZ_JA_STIMMEN": 172
}
,
{
"GEMEINDE": "Uitikon",
"BEZIRK": "Dietikon",
"STIMMBETEILIGUNG": "   64.44",
"AZ_GÜLTIGE_STIMMZETTEL": 74,
"AZ_JA_STIMMEN": 17
}
,
{
"GEMEINDE": "Unterengstringen",
"BEZIRK": "Dietikon",
"STIMMBETEILIGUNG": "   78.92",
"AZ_GÜLTIGE_STIMMZETTEL": 125,
"AZ_JA_STIMMEN": 21
}
,
{
"GEMEINDE": "Urdorf",
"BEZIRK": "Dietikon",
"STIMMBETEILIGUNG": "   66.21",
"AZ_GÜLTIGE_STIMMZETTEL": 163,
"AZ_JA_STIMMEN": 43
}
,
{
"GEMEINDE": "Weiningen",
"BEZIRK": "Dietikon",
"STIMMBETEILIGUNG": "   72.80",
"AZ_GÜLTIGE_STIMMZETTEL": 169,
"AZ_JA_STIMMEN": 23
}
,
{
"GEMEINDE": "Bäretswil",
"BEZIRK": "Hinwil",
"STIMMBETEILIGUNG": "   75.98",
"AZ_GÜLTIGE_STIMMZETTEL": 485,
"AZ_JA_STIMMEN": 89
}
,
{
"GEMEINDE": "Bubikon",
"BEZIRK": "Hinwil",
"STIMMBETEILIGUNG": "   74.66",
"AZ_GÜLTIGE_STIMMZETTEL": 359,
"AZ_JA_STIMMEN": 59
}
,
{
"GEMEINDE": "Dürnten",
"BEZIRK": "Hinwil",
"STIMMBETEILIGUNG": "   74.84",
"AZ_GÜLTIGE_STIMMZETTEL": 621,
"AZ_JA_STIMMEN": 152
}
,
{
"GEMEINDE": "Fischenthal",
"BEZIRK": "Hinwil",
"STIMMBETEILIGUNG": "   83.33",
"AZ_GÜLTIGE_STIMMZETTEL": 407,
"AZ_JA_STIMMEN": 101
}
,
{
"GEMEINDE": "Gossau",
"BEZIRK": "Hinwil",
"STIMMBETEILIGUNG": "   75.52",
"AZ_GÜLTIGE_STIMMZETTEL": 509,
"AZ_JA_STIMMEN": 95
}
,
{
"GEMEINDE": "Grüningen",
"BEZIRK": "Hinwil",
"STIMMBETEILIGUNG": "   68.61",
"AZ_GÜLTIGE_STIMMZETTEL": 266,
"AZ_JA_STIMMEN": 56
}
,
{
"GEMEINDE": "Hinwil",
"BEZIRK": "Hinwil",
"STIMMBETEILIGUNG": "   75.11",
"AZ_GÜLTIGE_STIMMZETTEL": 613,
"AZ_JA_STIMMEN": 130
}
,
{
"GEMEINDE": "Rüti",
"BEZIRK": "Hinwil",
"STIMMBETEILIGUNG": "   61.15",
"AZ_GÜLTIGE_STIMMZETTEL": 919,
"AZ_JA_STIMMEN": 197
}
,
{
"GEMEINDE": "Seegräben",
"BEZIRK": "Hinwil",
"STIMMBETEILIGUNG": "   68.02",
"AZ_GÜLTIGE_STIMMZETTEL": 135,
"AZ_JA_STIMMEN": 34
}
,
{
"GEMEINDE": "Wald",
"BEZIRK": "Hinwil",
"STIMMBETEILIGUNG": "   70.33",
"AZ_GÜLTIGE_STIMMZETTEL": 1262,
"AZ_JA_STIMMEN": 340
}
,
{
"GEMEINDE": "Wetzikon",
"BEZIRK": "Hinwil",
"STIMMBETEILIGUNG": "   73.41",
"AZ_GÜLTIGE_STIMMZETTEL": 1186,
"AZ_JA_STIMMEN": 276
}
,
{
"GEMEINDE": "Adliswil",
"BEZIRK": "Horgen",
"STIMMBETEILIGUNG": "   69.90",
"AZ_GÜLTIGE_STIMMZETTEL": 866,
"AZ_JA_STIMMEN": 318
}
,
{
"GEMEINDE": "Hirzel",
"BEZIRK": "Horgen",
"STIMMBETEILIGUNG": "   77.10",
"AZ_GÜLTIGE_STIMMZETTEL": 211,
"AZ_JA_STIMMEN": 43
}
,
{
"GEMEINDE": "Horgen",
"BEZIRK": "Horgen",
"STIMMBETEILIGUNG": "   72.37",
"AZ_GÜLTIGE_STIMMZETTEL": 1739,
"AZ_JA_STIMMEN": 607
}
,
{
"GEMEINDE": "Hütten",
"BEZIRK": "Horgen",
"STIMMBETEILIGUNG": "   70.51",
"AZ_GÜLTIGE_STIMMZETTEL": 107,
"AZ_JA_STIMMEN": 22
}
,
{
"GEMEINDE": "Kilchberg",
"BEZIRK": "Horgen",
"STIMMBETEILIGUNG": "   66.03",
"AZ_GÜLTIGE_STIMMZETTEL": 592,
"AZ_JA_STIMMEN": 148
}
,
{
"GEMEINDE": "Langnau a.A.",
"BEZIRK": "Horgen",
"STIMMBETEILIGUNG": "   60.29",
"AZ_GÜLTIGE_STIMMZETTEL": 307,
"AZ_JA_STIMMEN": 134
}
,
{
"GEMEINDE": "Oberrieden",
"BEZIRK": "Horgen",
"STIMMBETEILIGUNG": "   64.93",
"AZ_GÜLTIGE_STIMMZETTEL": 274,
"AZ_JA_STIMMEN": 79
}
,
{
"GEMEINDE": "Richterswil",
"BEZIRK": "Horgen",
"STIMMBETEILIGUNG": "   72.21",
"AZ_GÜLTIGE_STIMMZETTEL": 828,
"AZ_JA_STIMMEN": 358
}
,
{
"GEMEINDE": "Rüschlikon",
"BEZIRK": "Horgen",
"STIMMBETEILIGUNG": "   72.13",
"AZ_GÜLTIGE_STIMMZETTEL": 439,
"AZ_JA_STIMMEN": 126
}
,
{
"GEMEINDE": "Schönenberg",
"BEZIRK": "Horgen",
"STIMMBETEILIGUNG": "   69.83",
"AZ_GÜLTIGE_STIMMZETTEL": 234,
"AZ_JA_STIMMEN": 59
}
,
{
"GEMEINDE": "Thalwil",
"BEZIRK": "Horgen",
"STIMMBETEILIGUNG": "   77.43",
"AZ_GÜLTIGE_STIMMZETTEL": 1549,
"AZ_JA_STIMMEN": 525
}
,
{
"GEMEINDE": "Wädenswil",
"BEZIRK": "Horgen",
"STIMMBETEILIGUNG": "   71.87",
"AZ_GÜLTIGE_STIMMZETTEL": 1644,
"AZ_JA_STIMMEN": 657
}
,
{
"GEMEINDE": "Erlenbach",
"BEZIRK": "Meilen",
"STIMMBETEILIGUNG": "   59.52",
"AZ_GÜLTIGE_STIMMZETTEL": 338,
"AZ_JA_STIMMEN": 75
}
,
{
"GEMEINDE": "Herrliberg",
"BEZIRK": "Meilen",
"STIMMBETEILIGUNG": "   61.80",
"AZ_GÜLTIGE_STIMMZETTEL": 228,
"AZ_JA_STIMMEN": 50
}
,
{
"GEMEINDE": "Hombrechtikon",
"BEZIRK": "Meilen",
"STIMMBETEILIGUNG": "   78.41",
"AZ_GÜLTIGE_STIMMZETTEL": 507,
"AZ_JA_STIMMEN": 124
}
,
{
"GEMEINDE": "Küsnacht",
"BEZIRK": "Meilen",
"STIMMBETEILIGUNG": "   68.83",
"AZ_GÜLTIGE_STIMMZETTEL": 914,
"AZ_JA_STIMMEN": 153
}
,
{
"GEMEINDE": "Männedorf",
"BEZIRK": "Meilen",
"STIMMBETEILIGUNG": "   71.95",
"AZ_GÜLTIGE_STIMMZETTEL": 588,
"AZ_JA_STIMMEN": 150
}
,
{
"GEMEINDE": "Meilen",
"BEZIRK": "Meilen",
"STIMMBETEILIGUNG": "   66.02",
"AZ_GÜLTIGE_STIMMZETTEL": 717,
"AZ_JA_STIMMEN": 185
}
,
{
"GEMEINDE": "Oetwil a.S.",
"BEZIRK": "Meilen",
"STIMMBETEILIGUNG": "   84.64",
"AZ_GÜLTIGE_STIMMZETTEL": 218,
"AZ_JA_STIMMEN": 50
}
,
{
"GEMEINDE": "Stäfa",
"BEZIRK": "Meilen",
"STIMMBETEILIGUNG": "   73.36",
"AZ_GÜLTIGE_STIMMZETTEL": 878,
"AZ_JA_STIMMEN": 201
}
,
{
"GEMEINDE": "Uetikon a.S.",
"BEZIRK": "Meilen",
"STIMMBETEILIGUNG": "   62.23",
"AZ_GÜLTIGE_STIMMZETTEL": 301,
"AZ_JA_STIMMEN": 62
}
,
{
"GEMEINDE": "Zollikon",
"BEZIRK": "Meilen",
"STIMMBETEILIGUNG": "   64.36",
"AZ_GÜLTIGE_STIMMZETTEL": 644,
"AZ_JA_STIMMEN": 170
}
,
{
"GEMEINDE": "Zumikon",
"BEZIRK": "Meilen",
"STIMMBETEILIGUNG": "   69.84",
"AZ_GÜLTIGE_STIMMZETTEL": 125,
"AZ_JA_STIMMEN": 18
}
,
{
"GEMEINDE": "Bauma",
"BEZIRK": "Pfäffikon",
"STIMMBETEILIGUNG": "   73.06",
"AZ_GÜLTIGE_STIMMZETTEL": 636,
"AZ_JA_STIMMEN": 176
}
,
{
"GEMEINDE": "Fehraltorf",
"BEZIRK": "Pfäffikon",
"STIMMBETEILIGUNG": "   75.00",
"AZ_GÜLTIGE_STIMMZETTEL": 185,
"AZ_JA_STIMMEN": 59
}
,
{
"GEMEINDE": "Hittnau",
"BEZIRK": "Pfäffikon",
"STIMMBETEILIGUNG": "   88.51",
"AZ_GÜLTIGE_STIMMZETTEL": 280,
"AZ_JA_STIMMEN": 138
}
,
{
"GEMEINDE": "Illnau-Effretikon",
"BEZIRK": "Pfäffikon",
"STIMMBETEILIGUNG": "   75.54",
"AZ_GÜLTIGE_STIMMZETTEL": 750,
"AZ_JA_STIMMEN": 300
}
,
{
"GEMEINDE": "Lindau",
"BEZIRK": "Pfäffikon",
"STIMMBETEILIGUNG": "   80.69",
"AZ_GÜLTIGE_STIMMZETTEL": 347,
"AZ_JA_STIMMEN": 97
}
,
{
"GEMEINDE": "Pfäffikon",
"BEZIRK": "Pfäffikon",
"STIMMBETEILIGUNG": "   80.22",
"AZ_GÜLTIGE_STIMMZETTEL": 772,
"AZ_JA_STIMMEN": 362
}
,
{
"GEMEINDE": "Russikon",
"BEZIRK": "Pfäffikon",
"STIMMBETEILIGUNG": "   81.63",
"AZ_GÜLTIGE_STIMMZETTEL": 281,
"AZ_JA_STIMMEN": 127
}
,
{
"GEMEINDE": "Weisslingen",
"BEZIRK": "Pfäffikon",
"STIMMBETEILIGUNG": "   85.43",
"AZ_GÜLTIGE_STIMMZETTEL": 280,
"AZ_JA_STIMMEN": 127
}
,
{
"GEMEINDE": "Wila",
"BEZIRK": "Pfäffikon",
"STIMMBETEILIGUNG": "   72.33",
"AZ_GÜLTIGE_STIMMZETTEL": 167,
"AZ_JA_STIMMEN": 55
}
,
{
"GEMEINDE": "Wildberg",
"BEZIRK": "Pfäffikon",
"STIMMBETEILIGUNG": "   76.44",
"AZ_GÜLTIGE_STIMMZETTEL": 133,
"AZ_JA_STIMMEN": 47
}
,
{
"GEMEINDE": "Dübendorf",
"BEZIRK": "Uster",
"STIMMBETEILIGUNG": "   67.46",
"AZ_GÜLTIGE_STIMMZETTEL": 790,
"AZ_JA_STIMMEN": 184
}
,
{
"GEMEINDE": "Egg",
"BEZIRK": "Uster",
"STIMMBETEILIGUNG": "   75.00",
"AZ_GÜLTIGE_STIMMZETTEL": 434,
"AZ_JA_STIMMEN": 100
}
,
{
"GEMEINDE": "Fällanden",
"BEZIRK": "Uster",
"STIMMBETEILIGUNG": "   70.59",
"AZ_GÜLTIGE_STIMMZETTEL": 139,
"AZ_JA_STIMMEN": 54
}
,
{
"GEMEINDE": "Greifensee",
"BEZIRK": "Uster",
"STIMMBETEILIGUNG": "   84.04",
"AZ_GÜLTIGE_STIMMZETTEL": 77,
"AZ_JA_STIMMEN": 18
}
,
{
"GEMEINDE": "Maur",
"BEZIRK": "Uster",
"STIMMBETEILIGUNG": "   84.42",
"AZ_GÜLTIGE_STIMMZETTEL": 338,
"AZ_JA_STIMMEN": 74
}
,
{
"GEMEINDE": "Mönchaltorf",
"BEZIRK": "Uster",
"STIMMBETEILIGUNG": "   75.78",
"AZ_GÜLTIGE_STIMMZETTEL": 161,
"AZ_JA_STIMMEN": 36
}
,
{
"GEMEINDE": "Schwerzenbach",
"BEZIRK": "Uster",
"STIMMBETEILIGUNG": "   83.70",
"AZ_GÜLTIGE_STIMMZETTEL": 76,
"AZ_JA_STIMMEN": 36
}
,
{
"GEMEINDE": "Uster",
"BEZIRK": "Uster",
"STIMMBETEILIGUNG": "   65.19",
"AZ_GÜLTIGE_STIMMZETTEL": 1570,
"AZ_JA_STIMMEN": 492
}
,
{
"GEMEINDE": "Volketswil",
"BEZIRK": "Uster",
"STIMMBETEILIGUNG": "   78.86",
"AZ_GÜLTIGE_STIMMZETTEL": 358,
"AZ_JA_STIMMEN": 107
}
,
{
"GEMEINDE": "Wangen-Brüttisellen",
"BEZIRK": "Uster",
"STIMMBETEILIGUNG": "   70.76",
"AZ_GÜLTIGE_STIMMZETTEL": 277,
"AZ_JA_STIMMEN": 59
}
,
{
"GEMEINDE": "Altikon",
"BEZIRK": "Winterthur",
"STIMMBETEILIGUNG": "   80.28",
"AZ_GÜLTIGE_STIMMZETTEL": 111,
"AZ_JA_STIMMEN": 29
}
,
{
"GEMEINDE": "Brütten",
"BEZIRK": "Winterthur",
"STIMMBETEILIGUNG": "   81.33",
"AZ_GÜLTIGE_STIMMZETTEL": 107,
"AZ_JA_STIMMEN": 27
}
,
{
"GEMEINDE": "Dägerlen",
"BEZIRK": "Winterthur",
"STIMMBETEILIGUNG": "   91.50",
"AZ_GÜLTIGE_STIMMZETTEL": 136,
"AZ_JA_STIMMEN": 41
}
,
{
"GEMEINDE": "Dättlikon",
"BEZIRK": "Winterthur",
"STIMMBETEILIGUNG": "   82.35",
"AZ_GÜLTIGE_STIMMZETTEL": 67,
"AZ_JA_STIMMEN": 28
}
,
{
"GEMEINDE": "Dinhard",
"BEZIRK": "Winterthur",
"STIMMBETEILIGUNG": "   85.71",
"AZ_GÜLTIGE_STIMMZETTEL": 170,
"AZ_JA_STIMMEN": 38
}
,
{
"GEMEINDE": "Elgg",
"BEZIRK": "Winterthur",
"STIMMBETEILIGUNG": "   68.41",
"AZ_GÜLTIGE_STIMMZETTEL": 300,
"AZ_JA_STIMMEN": 72
}
,
{
"GEMEINDE": "Ellikon a.d.Th.",
"BEZIRK": "Winterthur",
"STIMMBETEILIGUNG": "   72.48",
"AZ_GÜLTIGE_STIMMZETTEL": 71,
"AZ_JA_STIMMEN": 37
}
,
{
"GEMEINDE": "Elsau",
"BEZIRK": "Winterthur",
"STIMMBETEILIGUNG": "   84.82",
"AZ_GÜLTIGE_STIMMZETTEL": 260,
"AZ_JA_STIMMEN": 62
}
,
{
"GEMEINDE": "Hagenbuch",
"BEZIRK": "Winterthur",
"STIMMBETEILIGUNG": "   76.28",
"AZ_GÜLTIGE_STIMMZETTEL": 110,
"AZ_JA_STIMMEN": 27
}
,
{
"GEMEINDE": "Hettlingen",
"BEZIRK": "Winterthur",
"STIMMBETEILIGUNG": "   75.64",
"AZ_GÜLTIGE_STIMMZETTEL": 113,
"AZ_JA_STIMMEN": 57
}
,
{
"GEMEINDE": "Hofstetten",
"BEZIRK": "Winterthur",
"STIMMBETEILIGUNG": "   86.57",
"AZ_GÜLTIGE_STIMMZETTEL": 108,
"AZ_JA_STIMMEN": 38
}
,
{
"GEMEINDE": "Neftenbach",
"BEZIRK": "Winterthur",
"STIMMBETEILIGUNG": "   76.72",
"AZ_GÜLTIGE_STIMMZETTEL": 331,
"AZ_JA_STIMMEN": 122
}
,
{
"GEMEINDE": "Pfungen",
"BEZIRK": "Winterthur",
"STIMMBETEILIGUNG": "   78.73",
"AZ_GÜLTIGE_STIMMZETTEL": 218,
"AZ_JA_STIMMEN": 52
}
,
{
"GEMEINDE": "Rickenbach",
"BEZIRK": "Winterthur",
"STIMMBETEILIGUNG": "   83.74",
"AZ_GÜLTIGE_STIMMZETTEL": 97,
"AZ_JA_STIMMEN": 21
}
,
{
"GEMEINDE": "Schlatt",
"BEZIRK": "Winterthur",
"STIMMBETEILIGUNG": "   85.00",
"AZ_GÜLTIGE_STIMMZETTEL": 113,
"AZ_JA_STIMMEN": 17
}
,
{
"GEMEINDE": "Seuzach",
"BEZIRK": "Winterthur",
"STIMMBETEILIGUNG": "   81.29",
"AZ_GÜLTIGE_STIMMZETTEL": 256,
"AZ_JA_STIMMEN": 55
}
,
{
"GEMEINDE": "Turbenthal",
"BEZIRK": "Winterthur",
"STIMMBETEILIGUNG": "   85.07",
"AZ_GÜLTIGE_STIMMZETTEL": 518,
"AZ_JA_STIMMEN": 106
}
,
{
"GEMEINDE": "Wiesendangen",
"BEZIRK": "Winterthur",
"STIMMBETEILIGUNG": "   84.42",
"AZ_GÜLTIGE_STIMMZETTEL": 419,
"AZ_JA_STIMMEN": 108
}
,
{
"GEMEINDE": "Winterthur",
"BEZIRK": "Winterthur",
"STIMMBETEILIGUNG": "   80.63",
"AZ_GÜLTIGE_STIMMZETTEL": 11095,
"AZ_JA_STIMMEN": 3178
}
,
{
"GEMEINDE": "Zell",
"BEZIRK": "Winterthur",
"STIMMBETEILIGUNG": "   80.92",
"AZ_GÜLTIGE_STIMMZETTEL": 509,
"AZ_JA_STIMMEN": 131
}
,
{
"GEMEINDE": "Zürich",
"BEZIRK": "Zürich",
"STIMMBETEILIGUNG": "   65.79",
"AZ_GÜLTIGE_STIMMZETTEL": 43982,
"AZ_JA_STIMMEN": 12164
}
]
