[
{
"GEMEINDE": "Aeugst a.A.",
"BEZIRK": "Affoltern",
"STIMMBETEILIGUNG": "   46.99",
"AZ_GÜLTIGE_STIMMZETTEL": 579,
"AZ_JA_STIMMEN": 476
}
,
{
"GEMEINDE": "Affoltern a.A.",
"BEZIRK": "Affoltern",
"STIMMBETEILIGUNG": "   42.39",
"AZ_GÜLTIGE_STIMMZETTEL": 2692,
"AZ_JA_STIMMEN": 2093
}
,
{
"GEMEINDE": "Bonstetten",
"BEZIRK": "Affoltern",
"STIMMBETEILIGUNG": "   52.88",
"AZ_GÜLTIGE_STIMMZETTEL": 1764,
"AZ_JA_STIMMEN": 1411
}
,
{
"GEMEINDE": "Hausen a.A.",
"BEZIRK": "Affoltern",
"STIMMBETEILIGUNG": "   47.73",
"AZ_GÜLTIGE_STIMMZETTEL": 1099,
"AZ_JA_STIMMEN": 844
}
,
{
"GEMEINDE": "Hedingen",
"BEZIRK": "Affoltern",
"STIMMBETEILIGUNG": "   50.06",
"AZ_GÜLTIGE_STIMMZETTEL": 1133,
"AZ_JA_STIMMEN": 891
}
,
{
"GEMEINDE": "Kappel a.A.",
"BEZIRK": "Affoltern",
"STIMMBETEILIGUNG": "   46.66",
"AZ_GÜLTIGE_STIMMZETTEL": 290,
"AZ_JA_STIMMEN": 205
}
,
{
"GEMEINDE": "Knonau",
"BEZIRK": "Affoltern",
"STIMMBETEILIGUNG": "   44.78",
"AZ_GÜLTIGE_STIMMZETTEL": 519,
"AZ_JA_STIMMEN": 380
}
,
{
"GEMEINDE": "Maschwanden",
"BEZIRK": "Affoltern",
"STIMMBETEILIGUNG": "   46.07",
"AZ_GÜLTIGE_STIMMZETTEL": 193,
"AZ_JA_STIMMEN": 135
}
,
{
"GEMEINDE": "Mettmenstetten",
"BEZIRK": "Affoltern",
"STIMMBETEILIGUNG": "   57.88",
"AZ_GÜLTIGE_STIMMZETTEL": 1613,
"AZ_JA_STIMMEN": 1222
}
,
{
"GEMEINDE": "Obfelden",
"BEZIRK": "Affoltern",
"STIMMBETEILIGUNG": "   43.22",
"AZ_GÜLTIGE_STIMMZETTEL": 1268,
"AZ_JA_STIMMEN": 969
}
,
{
"GEMEINDE": "Ottenbach",
"BEZIRK": "Affoltern",
"STIMMBETEILIGUNG": "   48.73",
"AZ_GÜLTIGE_STIMMZETTEL": 831,
"AZ_JA_STIMMEN": 666
}
,
{
"GEMEINDE": "Rifferswil",
"BEZIRK": "Affoltern",
"STIMMBETEILIGUNG": "   52.03",
"AZ_GÜLTIGE_STIMMZETTEL": 324,
"AZ_JA_STIMMEN": 252
}
,
{
"GEMEINDE": "Stallikon",
"BEZIRK": "Affoltern",
"STIMMBETEILIGUNG": "   52.29",
"AZ_GÜLTIGE_STIMMZETTEL": 1091,
"AZ_JA_STIMMEN": 886
}
,
{
"GEMEINDE": "Wettswil a.A.",
"BEZIRK": "Affoltern",
"STIMMBETEILIGUNG": "   58.87",
"AZ_GÜLTIGE_STIMMZETTEL": 1812,
"AZ_JA_STIMMEN": 1506
}
,
{
"GEMEINDE": "Adlikon",
"BEZIRK": "Andelfingen",
"STIMMBETEILIGUNG": "   65.42",
"AZ_GÜLTIGE_STIMMZETTEL": 308,
"AZ_JA_STIMMEN": 160
}
,
{
"GEMEINDE": "Andelfingen",
"BEZIRK": "Andelfingen",
"STIMMBETEILIGUNG": "   55.12",
"AZ_GÜLTIGE_STIMMZETTEL": 693,
"AZ_JA_STIMMEN": 527
}
,
{
"GEMEINDE": "Benken",
"BEZIRK": "Andelfingen",
"STIMMBETEILIGUNG": "   57.14",
"AZ_GÜLTIGE_STIMMZETTEL": 323,
"AZ_JA_STIMMEN": 211
}
,
{
"GEMEINDE": "Berg a.I.",
"BEZIRK": "Andelfingen",
"STIMMBETEILIGUNG": "   59.54",
"AZ_GÜLTIGE_STIMMZETTEL": 277,
"AZ_JA_STIMMEN": 186
}
,
{
"GEMEINDE": "Buch a.I.",
"BEZIRK": "Andelfingen",
"STIMMBETEILIGUNG": "   59.05",
"AZ_GÜLTIGE_STIMMZETTEL": 347,
"AZ_JA_STIMMEN": 250
}
,
{
"GEMEINDE": "Dachsen",
"BEZIRK": "Andelfingen",
"STIMMBETEILIGUNG": "   50.27",
"AZ_GÜLTIGE_STIMMZETTEL": 623,
"AZ_JA_STIMMEN": 496
}
,
{
"GEMEINDE": "Dorf",
"BEZIRK": "Andelfingen",
"STIMMBETEILIGUNG": "   59.55",
"AZ_GÜLTIGE_STIMMZETTEL": 250,
"AZ_JA_STIMMEN": 170
}
,
{
"GEMEINDE": "Feuerthalen",
"BEZIRK": "Andelfingen",
"STIMMBETEILIGUNG": "   45.96",
"AZ_GÜLTIGE_STIMMZETTEL": 978,
"AZ_JA_STIMMEN": 737
}
,
{
"GEMEINDE": "Flaach",
"BEZIRK": "Andelfingen",
"STIMMBETEILIGUNG": "   58.44",
"AZ_GÜLTIGE_STIMMZETTEL": 474,
"AZ_JA_STIMMEN": 309
}
,
{
"GEMEINDE": "Flurlingen",
"BEZIRK": "Andelfingen",
"STIMMBETEILIGUNG": "   52.30",
"AZ_GÜLTIGE_STIMMZETTEL": 489,
"AZ_JA_STIMMEN": 399
}
,
{
"GEMEINDE": "Henggart",
"BEZIRK": "Andelfingen",
"STIMMBETEILIGUNG": "   50.82",
"AZ_GÜLTIGE_STIMMZETTEL": 757,
"AZ_JA_STIMMEN": 583
}
,
{
"GEMEINDE": "Humlikon",
"BEZIRK": "Andelfingen",
"STIMMBETEILIGUNG": "   59.18",
"AZ_GÜLTIGE_STIMMZETTEL": 185,
"AZ_JA_STIMMEN": 130
}
,
{
"GEMEINDE": "Kleinandelfingen",
"BEZIRK": "Andelfingen",
"STIMMBETEILIGUNG": "   50.30",
"AZ_GÜLTIGE_STIMMZETTEL": 719,
"AZ_JA_STIMMEN": 511
}
,
{
"GEMEINDE": "Laufen-Uhwiesen",
"BEZIRK": "Andelfingen",
"STIMMBETEILIGUNG": "   47.35",
"AZ_GÜLTIGE_STIMMZETTEL": 491,
"AZ_JA_STIMMEN": 355
}
,
{
"GEMEINDE": "Marthalen",
"BEZIRK": "Andelfingen",
"STIMMBETEILIGUNG": "   50.85",
"AZ_GÜLTIGE_STIMMZETTEL": 702,
"AZ_JA_STIMMEN": 445
}
,
{
"GEMEINDE": "Oberstammheim",
"BEZIRK": "Andelfingen",
"STIMMBETEILIGUNG": "   55.42",
"AZ_GÜLTIGE_STIMMZETTEL": 437,
"AZ_JA_STIMMEN": 301
}
,
{
"GEMEINDE": "Ossingen",
"BEZIRK": "Andelfingen",
"STIMMBETEILIGUNG": "   55.91",
"AZ_GÜLTIGE_STIMMZETTEL": 538,
"AZ_JA_STIMMEN": 368
}
,
{
"GEMEINDE": "Rheinau",
"BEZIRK": "Andelfingen",
"STIMMBETEILIGUNG": "   60.14",
"AZ_GÜLTIGE_STIMMZETTEL": 503,
"AZ_JA_STIMMEN": 406
}
,
{
"GEMEINDE": "Thalheim a.d.Th.",
"BEZIRK": "Andelfingen",
"STIMMBETEILIGUNG": "   45.47",
"AZ_GÜLTIGE_STIMMZETTEL": 247,
"AZ_JA_STIMMEN": 161
}
,
{
"GEMEINDE": "Trüllikon",
"BEZIRK": "Andelfingen",
"STIMMBETEILIGUNG": "   50.69",
"AZ_GÜLTIGE_STIMMZETTEL": 388,
"AZ_JA_STIMMEN": 255
}
,
{
"GEMEINDE": "Truttikon",
"BEZIRK": "Andelfingen",
"STIMMBETEILIGUNG": "   61.92",
"AZ_GÜLTIGE_STIMMZETTEL": 202,
"AZ_JA_STIMMEN": 122
}
,
{
"GEMEINDE": "Unterstammheim",
"BEZIRK": "Andelfingen",
"STIMMBETEILIGUNG": "   66.56",
"AZ_GÜLTIGE_STIMMZETTEL": 400,
"AZ_JA_STIMMEN": 283
}
,
{
"GEMEINDE": "Volken",
"BEZIRK": "Andelfingen",
"STIMMBETEILIGUNG": "   65.40",
"AZ_GÜLTIGE_STIMMZETTEL": 130,
"AZ_JA_STIMMEN": 87
}
,
{
"GEMEINDE": "Waltalingen",
"BEZIRK": "Andelfingen",
"STIMMBETEILIGUNG": "   55.47",
"AZ_GÜLTIGE_STIMMZETTEL": 259,
"AZ_JA_STIMMEN": 156
}
,
{
"GEMEINDE": "Bachenbülach",
"BEZIRK": "Bülach",
"STIMMBETEILIGUNG": "   39.58",
"AZ_GÜLTIGE_STIMMZETTEL": 897,
"AZ_JA_STIMMEN": 636
}
,
{
"GEMEINDE": "Bassersdorf",
"BEZIRK": "Bülach",
"STIMMBETEILIGUNG": "   40.86",
"AZ_GÜLTIGE_STIMMZETTEL": 2667,
"AZ_JA_STIMMEN": 2133
}
,
{
"GEMEINDE": "Bülach",
"BEZIRK": "Bülach",
"STIMMBETEILIGUNG": "   40.03",
"AZ_GÜLTIGE_STIMMZETTEL": 4174,
"AZ_JA_STIMMEN": 3158
}
,
{
"GEMEINDE": "Dietlikon",
"BEZIRK": "Bülach",
"STIMMBETEILIGUNG": "   46.82",
"AZ_GÜLTIGE_STIMMZETTEL": 2064,
"AZ_JA_STIMMEN": 1616
}
,
{
"GEMEINDE": "Eglisau",
"BEZIRK": "Bülach",
"STIMMBETEILIGUNG": "   64.75",
"AZ_GÜLTIGE_STIMMZETTEL": 1618,
"AZ_JA_STIMMEN": 1205
}
,
{
"GEMEINDE": "Embrach",
"BEZIRK": "Bülach",
"STIMMBETEILIGUNG": "   40.84",
"AZ_GÜLTIGE_STIMMZETTEL": 2139,
"AZ_JA_STIMMEN": 1635
}
,
{
"GEMEINDE": "Freienstein-Teufen",
"BEZIRK": "Bülach",
"STIMMBETEILIGUNG": "   56.45",
"AZ_GÜLTIGE_STIMMZETTEL": 874,
"AZ_JA_STIMMEN": 653
}
,
{
"GEMEINDE": "Glattfelden",
"BEZIRK": "Bülach",
"STIMMBETEILIGUNG": "   49.26",
"AZ_GÜLTIGE_STIMMZETTEL": 1250,
"AZ_JA_STIMMEN": 867
}
,
{
"GEMEINDE": "Hochfelden",
"BEZIRK": "Bülach",
"STIMMBETEILIGUNG": "   50.15",
"AZ_GÜLTIGE_STIMMZETTEL": 626,
"AZ_JA_STIMMEN": 469
}
,
{
"GEMEINDE": "Höri",
"BEZIRK": "Bülach",
"STIMMBETEILIGUNG": "   46.06",
"AZ_GÜLTIGE_STIMMZETTEL": 611,
"AZ_JA_STIMMEN": 397
}
,
{
"GEMEINDE": "Hüntwangen",
"BEZIRK": "Bülach",
"STIMMBETEILIGUNG": "   56.34",
"AZ_GÜLTIGE_STIMMZETTEL": 378,
"AZ_JA_STIMMEN": 296
}
,
{
"GEMEINDE": "Kloten",
"BEZIRK": "Bülach",
"STIMMBETEILIGUNG": "   36.65",
"AZ_GÜLTIGE_STIMMZETTEL": 3826,
"AZ_JA_STIMMEN": 2873
}
,
{
"GEMEINDE": "Lufingen",
"BEZIRK": "Bülach",
"STIMMBETEILIGUNG": "   46.63",
"AZ_GÜLTIGE_STIMMZETTEL": 511,
"AZ_JA_STIMMEN": 377
}
,
{
"GEMEINDE": "Nürensdorf",
"BEZIRK": "Bülach",
"STIMMBETEILIGUNG": "   48.03",
"AZ_GÜLTIGE_STIMMZETTEL": 1731,
"AZ_JA_STIMMEN": 1365
}
,
{
"GEMEINDE": "Oberembrach",
"BEZIRK": "Bülach",
"STIMMBETEILIGUNG": "   49.93",
"AZ_GÜLTIGE_STIMMZETTEL": 364,
"AZ_JA_STIMMEN": 265
}
,
{
"GEMEINDE": "Opfikon",
"BEZIRK": "Bülach",
"STIMMBETEILIGUNG": "   33.96",
"AZ_GÜLTIGE_STIMMZETTEL": 2483,
"AZ_JA_STIMMEN": 1823
}
,
{
"GEMEINDE": "Rafz",
"BEZIRK": "Bülach",
"STIMMBETEILIGUNG": "   53.89",
"AZ_GÜLTIGE_STIMMZETTEL": 1365,
"AZ_JA_STIMMEN": 908
}
,
{
"GEMEINDE": "Rorbas",
"BEZIRK": "Bülach",
"STIMMBETEILIGUNG": "   40.84",
"AZ_GÜLTIGE_STIMMZETTEL": 570,
"AZ_JA_STIMMEN": 425
}
,
{
"GEMEINDE": "Wallisellen",
"BEZIRK": "Bülach",
"STIMMBETEILIGUNG": "   43.73",
"AZ_GÜLTIGE_STIMMZETTEL": 3540,
"AZ_JA_STIMMEN": 2843
}
,
{
"GEMEINDE": "Wasterkingen",
"BEZIRK": "Bülach",
"STIMMBETEILIGUNG": "   58.27",
"AZ_GÜLTIGE_STIMMZETTEL": 221,
"AZ_JA_STIMMEN": 161
}
,
{
"GEMEINDE": "Wil",
"BEZIRK": "Bülach",
"STIMMBETEILIGUNG": "   62.54",
"AZ_GÜLTIGE_STIMMZETTEL": 604,
"AZ_JA_STIMMEN": 440
}
,
{
"GEMEINDE": "Winkel",
"BEZIRK": "Bülach",
"STIMMBETEILIGUNG": "   49.09",
"AZ_GÜLTIGE_STIMMZETTEL": 1361,
"AZ_JA_STIMMEN": 1052
}
,
{
"GEMEINDE": "Bachs",
"BEZIRK": "Dielsdorf",
"STIMMBETEILIGUNG": "   48.20",
"AZ_GÜLTIGE_STIMMZETTEL": 208,
"AZ_JA_STIMMEN": 132
}
,
{
"GEMEINDE": "Boppelsen",
"BEZIRK": "Dielsdorf",
"STIMMBETEILIGUNG": "   69.28",
"AZ_GÜLTIGE_STIMMZETTEL": 576,
"AZ_JA_STIMMEN": 444
}
,
{
"GEMEINDE": "Buchs",
"BEZIRK": "Dielsdorf",
"STIMMBETEILIGUNG": "   39.47",
"AZ_GÜLTIGE_STIMMZETTEL": 1291,
"AZ_JA_STIMMEN": 973
}
,
{
"GEMEINDE": "Dällikon",
"BEZIRK": "Dielsdorf",
"STIMMBETEILIGUNG": "   41.85",
"AZ_GÜLTIGE_STIMMZETTEL": 892,
"AZ_JA_STIMMEN": 679
}
,
{
"GEMEINDE": "Dänikon",
"BEZIRK": "Dielsdorf",
"STIMMBETEILIGUNG": "   44.73",
"AZ_GÜLTIGE_STIMMZETTEL": 476,
"AZ_JA_STIMMEN": 347
}
,
{
"GEMEINDE": "Dielsdorf",
"BEZIRK": "Dielsdorf",
"STIMMBETEILIGUNG": "   42.63",
"AZ_GÜLTIGE_STIMMZETTEL": 1424,
"AZ_JA_STIMMEN": 1079
}
,
{
"GEMEINDE": "Hüttikon",
"BEZIRK": "Dielsdorf",
"STIMMBETEILIGUNG": "   45.51",
"AZ_GÜLTIGE_STIMMZETTEL": 210,
"AZ_JA_STIMMEN": 137
}
,
{
"GEMEINDE": "Neerach",
"BEZIRK": "Dielsdorf",
"STIMMBETEILIGUNG": "   47.64",
"AZ_GÜLTIGE_STIMMZETTEL": 1010,
"AZ_JA_STIMMEN": 783
}
,
{
"GEMEINDE": "Niederglatt",
"BEZIRK": "Dielsdorf",
"STIMMBETEILIGUNG": "   41.95",
"AZ_GÜLTIGE_STIMMZETTEL": 1141,
"AZ_JA_STIMMEN": 823
}
,
{
"GEMEINDE": "Niederhasli",
"BEZIRK": "Dielsdorf",
"STIMMBETEILIGUNG": "   42.32",
"AZ_GÜLTIGE_STIMMZETTEL": 2099,
"AZ_JA_STIMMEN": 1609
}
,
{
"GEMEINDE": "Niederweningen",
"BEZIRK": "Dielsdorf",
"STIMMBETEILIGUNG": "   44.25",
"AZ_GÜLTIGE_STIMMZETTEL": 751,
"AZ_JA_STIMMEN": 582
}
,
{
"GEMEINDE": "Oberglatt",
"BEZIRK": "Dielsdorf",
"STIMMBETEILIGUNG": "   34.76",
"AZ_GÜLTIGE_STIMMZETTEL": 1018,
"AZ_JA_STIMMEN": 732
}
,
{
"GEMEINDE": "Oberweningen",
"BEZIRK": "Dielsdorf",
"STIMMBETEILIGUNG": "   46.61",
"AZ_GÜLTIGE_STIMMZETTEL": 494,
"AZ_JA_STIMMEN": 385
}
,
{
"GEMEINDE": "Otelfingen",
"BEZIRK": "Dielsdorf",
"STIMMBETEILIGUNG": "   47.03",
"AZ_GÜLTIGE_STIMMZETTEL": 698,
"AZ_JA_STIMMEN": 545
}
,
{
"GEMEINDE": "Regensberg",
"BEZIRK": "Dielsdorf",
"STIMMBETEILIGUNG": "   53.42",
"AZ_GÜLTIGE_STIMMZETTEL": 168,
"AZ_JA_STIMMEN": 137
}
,
{
"GEMEINDE": "Regensdorf",
"BEZIRK": "Dielsdorf",
"STIMMBETEILIGUNG": "   40.43",
"AZ_GÜLTIGE_STIMMZETTEL": 3625,
"AZ_JA_STIMMEN": 2755
}
,
{
"GEMEINDE": "Rümlang",
"BEZIRK": "Dielsdorf",
"STIMMBETEILIGUNG": "   38.80",
"AZ_GÜLTIGE_STIMMZETTEL": 1524,
"AZ_JA_STIMMEN": 1081
}
,
{
"GEMEINDE": "Schleinikon",
"BEZIRK": "Dielsdorf",
"STIMMBETEILIGUNG": "   44.66",
"AZ_GÜLTIGE_STIMMZETTEL": 224,
"AZ_JA_STIMMEN": 146
}
,
{
"GEMEINDE": "Schöfflisdorf",
"BEZIRK": "Dielsdorf",
"STIMMBETEILIGUNG": "   53.62",
"AZ_GÜLTIGE_STIMMZETTEL": 492,
"AZ_JA_STIMMEN": 379
}
,
{
"GEMEINDE": "Stadel",
"BEZIRK": "Dielsdorf",
"STIMMBETEILIGUNG": "   37.83",
"AZ_GÜLTIGE_STIMMZETTEL": 530,
"AZ_JA_STIMMEN": 377
}
,
{
"GEMEINDE": "Steinmaur",
"BEZIRK": "Dielsdorf",
"STIMMBETEILIGUNG": "   44.38",
"AZ_GÜLTIGE_STIMMZETTEL": 918,
"AZ_JA_STIMMEN": 677
}
,
{
"GEMEINDE": "Weiach",
"BEZIRK": "Dielsdorf",
"STIMMBETEILIGUNG": "   44.86",
"AZ_GÜLTIGE_STIMMZETTEL": 314,
"AZ_JA_STIMMEN": 204
}
,
{
"GEMEINDE": "Aesch",
"BEZIRK": "Dietikon",
"STIMMBETEILIGUNG": "   58.55",
"AZ_GÜLTIGE_STIMMZETTEL": 419,
"AZ_JA_STIMMEN": 300
}
,
{
"GEMEINDE": "Birmensdorf",
"BEZIRK": "Dietikon",
"STIMMBETEILIGUNG": "   49.41",
"AZ_GÜLTIGE_STIMMZETTEL": 1854,
"AZ_JA_STIMMEN": 1451
}
,
{
"GEMEINDE": "Dietikon",
"BEZIRK": "Dietikon",
"STIMMBETEILIGUNG": "   35.61",
"AZ_GÜLTIGE_STIMMZETTEL": 4030,
"AZ_JA_STIMMEN": 3066
}
,
{
"GEMEINDE": "Geroldswil",
"BEZIRK": "Dietikon",
"STIMMBETEILIGUNG": "   39.86",
"AZ_GÜLTIGE_STIMMZETTEL": 1175,
"AZ_JA_STIMMEN": 942
}
,
{
"GEMEINDE": "Oberengstringen",
"BEZIRK": "Dietikon",
"STIMMBETEILIGUNG": "   40.54",
"AZ_GÜLTIGE_STIMMZETTEL": 1524,
"AZ_JA_STIMMEN": 1233
}
,
{
"GEMEINDE": "Oetwil a.d.L",
"BEZIRK": "Dietikon",
"STIMMBETEILIGUNG": "   42.51",
"AZ_GÜLTIGE_STIMMZETTEL": 693,
"AZ_JA_STIMMEN": 532
}
,
{
"GEMEINDE": "Schlieren",
"BEZIRK": "Dietikon",
"STIMMBETEILIGUNG": "   35.91",
"AZ_GÜLTIGE_STIMMZETTEL": 2520,
"AZ_JA_STIMMEN": 1907
}
,
{
"GEMEINDE": "Uitikon",
"BEZIRK": "Dietikon",
"STIMMBETEILIGUNG": "   41.71",
"AZ_GÜLTIGE_STIMMZETTEL": 1162,
"AZ_JA_STIMMEN": 995
}
,
{
"GEMEINDE": "Unterengstringen",
"BEZIRK": "Dietikon",
"STIMMBETEILIGUNG": "   49.14",
"AZ_GÜLTIGE_STIMMZETTEL": 1063,
"AZ_JA_STIMMEN": 798
}
,
{
"GEMEINDE": "Urdorf",
"BEZIRK": "Dietikon",
"STIMMBETEILIGUNG": "   46.16",
"AZ_GÜLTIGE_STIMMZETTEL": 2711,
"AZ_JA_STIMMEN": 2155
}
,
{
"GEMEINDE": "Weiningen",
"BEZIRK": "Dietikon",
"STIMMBETEILIGUNG": "   44.65",
"AZ_GÜLTIGE_STIMMZETTEL": 1122,
"AZ_JA_STIMMEN": 869
}
,
{
"GEMEINDE": "Bäretswil",
"BEZIRK": "Hinwil",
"STIMMBETEILIGUNG": "   44.81",
"AZ_GÜLTIGE_STIMMZETTEL": 1481,
"AZ_JA_STIMMEN": 1019
}
,
{
"GEMEINDE": "Bubikon",
"BEZIRK": "Hinwil",
"STIMMBETEILIGUNG": "   48.87",
"AZ_GÜLTIGE_STIMMZETTEL": 2193,
"AZ_JA_STIMMEN": 1615
}
,
{
"GEMEINDE": "Dürnten",
"BEZIRK": "Hinwil",
"STIMMBETEILIGUNG": "   44.31",
"AZ_GÜLTIGE_STIMMZETTEL": 1878,
"AZ_JA_STIMMEN": 1403
}
,
{
"GEMEINDE": "Fischenthal",
"BEZIRK": "Hinwil",
"STIMMBETEILIGUNG": "   42.40",
"AZ_GÜLTIGE_STIMMZETTEL": 645,
"AZ_JA_STIMMEN": 415
}
,
{
"GEMEINDE": "Gossau",
"BEZIRK": "Hinwil",
"STIMMBETEILIGUNG": "   45.45",
"AZ_GÜLTIGE_STIMMZETTEL": 2996,
"AZ_JA_STIMMEN": 2212
}
,
{
"GEMEINDE": "Grüningen",
"BEZIRK": "Hinwil",
"STIMMBETEILIGUNG": "   48.19",
"AZ_GÜLTIGE_STIMMZETTEL": 1013,
"AZ_JA_STIMMEN": 736
}
,
{
"GEMEINDE": "Hinwil",
"BEZIRK": "Hinwil",
"STIMMBETEILIGUNG": "   45.37",
"AZ_GÜLTIGE_STIMMZETTEL": 3128,
"AZ_JA_STIMMEN": 2304
}
,
{
"GEMEINDE": "Rüti",
"BEZIRK": "Hinwil",
"STIMMBETEILIGUNG": "   42.84",
"AZ_GÜLTIGE_STIMMZETTEL": 3224,
"AZ_JA_STIMMEN": 2346
}
,
{
"GEMEINDE": "Seegräben",
"BEZIRK": "Hinwil",
"STIMMBETEILIGUNG": "   53.53",
"AZ_GÜLTIGE_STIMMZETTEL": 444,
"AZ_JA_STIMMEN": 355
}
,
{
"GEMEINDE": "Wald",
"BEZIRK": "Hinwil",
"STIMMBETEILIGUNG": "   42.03",
"AZ_GÜLTIGE_STIMMZETTEL": 2274,
"AZ_JA_STIMMEN": 1654
}
,
{
"GEMEINDE": "Wetzikon",
"BEZIRK": "Hinwil",
"STIMMBETEILIGUNG": "   40.67",
"AZ_GÜLTIGE_STIMMZETTEL": 5379,
"AZ_JA_STIMMEN": 4009
}
,
{
"GEMEINDE": "Adliswil",
"BEZIRK": "Horgen",
"STIMMBETEILIGUNG": "   43.93",
"AZ_GÜLTIGE_STIMMZETTEL": 4152,
"AZ_JA_STIMMEN": 3300
}
,
{
"GEMEINDE": "Hirzel",
"BEZIRK": "Horgen",
"STIMMBETEILIGUNG": "   45.19",
"AZ_GÜLTIGE_STIMMZETTEL": 644,
"AZ_JA_STIMMEN": 475
}
,
{
"GEMEINDE": "Horgen",
"BEZIRK": "Horgen",
"STIMMBETEILIGUNG": "   44.72",
"AZ_GÜLTIGE_STIMMZETTEL": 4825,
"AZ_JA_STIMMEN": 3805
}
,
{
"GEMEINDE": "Hütten",
"BEZIRK": "Horgen",
"STIMMBETEILIGUNG": "   46.46",
"AZ_GÜLTIGE_STIMMZETTEL": 301,
"AZ_JA_STIMMEN": 211
}
,
{
"GEMEINDE": "Kilchberg",
"BEZIRK": "Horgen",
"STIMMBETEILIGUNG": "   46.91",
"AZ_GÜLTIGE_STIMMZETTEL": 2159,
"AZ_JA_STIMMEN": 1809
}
,
{
"GEMEINDE": "Langnau a.A.",
"BEZIRK": "Horgen",
"STIMMBETEILIGUNG": "   51.25",
"AZ_GÜLTIGE_STIMMZETTEL": 2265,
"AZ_JA_STIMMEN": 1832
}
,
{
"GEMEINDE": "Oberrieden",
"BEZIRK": "Horgen",
"STIMMBETEILIGUNG": "   54.88",
"AZ_GÜLTIGE_STIMMZETTEL": 1880,
"AZ_JA_STIMMEN": 1570
}
,
{
"GEMEINDE": "Richterswil",
"BEZIRK": "Horgen",
"STIMMBETEILIGUNG": "   45.84",
"AZ_GÜLTIGE_STIMMZETTEL": 3541,
"AZ_JA_STIMMEN": 2776
}
,
{
"GEMEINDE": "Rüschlikon",
"BEZIRK": "Horgen",
"STIMMBETEILIGUNG": "   48.67",
"AZ_GÜLTIGE_STIMMZETTEL": 1570,
"AZ_JA_STIMMEN": 1309
}
,
{
"GEMEINDE": "Schönenberg",
"BEZIRK": "Horgen",
"STIMMBETEILIGUNG": "   58.10",
"AZ_GÜLTIGE_STIMMZETTEL": 782,
"AZ_JA_STIMMEN": 597
}
,
{
"GEMEINDE": "Thalwil",
"BEZIRK": "Horgen",
"STIMMBETEILIGUNG": "   48.56",
"AZ_GÜLTIGE_STIMMZETTEL": 5232,
"AZ_JA_STIMMEN": 4284
}
,
{
"GEMEINDE": "Wädenswil",
"BEZIRK": "Horgen",
"STIMMBETEILIGUNG": "   49.55",
"AZ_GÜLTIGE_STIMMZETTEL": 6323,
"AZ_JA_STIMMEN": 4953
}
,
{
"GEMEINDE": "Erlenbach",
"BEZIRK": "Meilen",
"STIMMBETEILIGUNG": "   50.49",
"AZ_GÜLTIGE_STIMMZETTEL": 1707,
"AZ_JA_STIMMEN": 1460
}
,
{
"GEMEINDE": "Herrliberg",
"BEZIRK": "Meilen",
"STIMMBETEILIGUNG": "   51.35",
"AZ_GÜLTIGE_STIMMZETTEL": 2055,
"AZ_JA_STIMMEN": 1736
}
,
{
"GEMEINDE": "Hombrechtikon",
"BEZIRK": "Meilen",
"STIMMBETEILIGUNG": "   44.51",
"AZ_GÜLTIGE_STIMMZETTEL": 2309,
"AZ_JA_STIMMEN": 1657
}
,
{
"GEMEINDE": "Küsnacht",
"BEZIRK": "Meilen",
"STIMMBETEILIGUNG": "   53.07",
"AZ_GÜLTIGE_STIMMZETTEL": 4649,
"AZ_JA_STIMMEN": 3866
}
,
{
"GEMEINDE": "Männedorf",
"BEZIRK": "Meilen",
"STIMMBETEILIGUNG": "   50.53",
"AZ_GÜLTIGE_STIMMZETTEL": 3311,
"AZ_JA_STIMMEN": 2674
}
,
{
"GEMEINDE": "Meilen",
"BEZIRK": "Meilen",
"STIMMBETEILIGUNG": "   50.72",
"AZ_GÜLTIGE_STIMMZETTEL": 4121,
"AZ_JA_STIMMEN": 3300
}
,
{
"GEMEINDE": "Oetwil a.S.",
"BEZIRK": "Meilen",
"STIMMBETEILIGUNG": "   38.67",
"AZ_GÜLTIGE_STIMMZETTEL": 974,
"AZ_JA_STIMMEN": 707
}
,
{
"GEMEINDE": "Stäfa",
"BEZIRK": "Meilen",
"STIMMBETEILIGUNG": "   51.29",
"AZ_GÜLTIGE_STIMMZETTEL": 4901,
"AZ_JA_STIMMEN": 3828
}
,
{
"GEMEINDE": "Uetikon a.S.",
"BEZIRK": "Meilen",
"STIMMBETEILIGUNG": "   49.35",
"AZ_GÜLTIGE_STIMMZETTEL": 1827,
"AZ_JA_STIMMEN": 1468
}
,
{
"GEMEINDE": "Zollikon",
"BEZIRK": "Meilen",
"STIMMBETEILIGUNG": "   52.88",
"AZ_GÜLTIGE_STIMMZETTEL": 4317,
"AZ_JA_STIMMEN": 3570
}
,
{
"GEMEINDE": "Zumikon",
"BEZIRK": "Meilen",
"STIMMBETEILIGUNG": "   53.84",
"AZ_GÜLTIGE_STIMMZETTEL": 1800,
"AZ_JA_STIMMEN": 1505
}
,
{
"GEMEINDE": "Bauma",
"BEZIRK": "Pfäffikon",
"STIMMBETEILIGUNG": "   44.01",
"AZ_GÜLTIGE_STIMMZETTEL": 1335,
"AZ_JA_STIMMEN": 854
}
,
{
"GEMEINDE": "Fehraltorf",
"BEZIRK": "Pfäffikon",
"STIMMBETEILIGUNG": "   47.03",
"AZ_GÜLTIGE_STIMMZETTEL": 1781,
"AZ_JA_STIMMEN": 1338
}
,
{
"GEMEINDE": "Hittnau",
"BEZIRK": "Pfäffikon",
"STIMMBETEILIGUNG": "   51.44",
"AZ_GÜLTIGE_STIMMZETTEL": 1199,
"AZ_JA_STIMMEN": 882
}
,
{
"GEMEINDE": "Illnau-Effretikon",
"BEZIRK": "Pfäffikon",
"STIMMBETEILIGUNG": "   48.90",
"AZ_GÜLTIGE_STIMMZETTEL": 4867,
"AZ_JA_STIMMEN": 3683
}
,
{
"GEMEINDE": "Lindau",
"BEZIRK": "Pfäffikon",
"STIMMBETEILIGUNG": "   47.80",
"AZ_GÜLTIGE_STIMMZETTEL": 1473,
"AZ_JA_STIMMEN": 1118
}
,
{
"GEMEINDE": "Pfäffikon",
"BEZIRK": "Pfäffikon",
"STIMMBETEILIGUNG": "   48.52",
"AZ_GÜLTIGE_STIMMZETTEL": 3300,
"AZ_JA_STIMMEN": 2537
}
,
{
"GEMEINDE": "Russikon",
"BEZIRK": "Pfäffikon",
"STIMMBETEILIGUNG": "   49.81",
"AZ_GÜLTIGE_STIMMZETTEL": 1403,
"AZ_JA_STIMMEN": 1001
}
,
{
"GEMEINDE": "Weisslingen",
"BEZIRK": "Pfäffikon",
"STIMMBETEILIGUNG": "   48.73",
"AZ_GÜLTIGE_STIMMZETTEL": 1108,
"AZ_JA_STIMMEN": 844
}
,
{
"GEMEINDE": "Wila",
"BEZIRK": "Pfäffikon",
"STIMMBETEILIGUNG": "   45.23",
"AZ_GÜLTIGE_STIMMZETTEL": 616,
"AZ_JA_STIMMEN": 379
}
,
{
"GEMEINDE": "Wildberg",
"BEZIRK": "Pfäffikon",
"STIMMBETEILIGUNG": "   52.73",
"AZ_GÜLTIGE_STIMMZETTEL": 363,
"AZ_JA_STIMMEN": 253
}
,
{
"GEMEINDE": "Dübendorf",
"BEZIRK": "Uster",
"STIMMBETEILIGUNG": "   41.80",
"AZ_GÜLTIGE_STIMMZETTEL": 5749,
"AZ_JA_STIMMEN": 4431
}
,
{
"GEMEINDE": "Egg",
"BEZIRK": "Uster",
"STIMMBETEILIGUNG": "   47.76",
"AZ_GÜLTIGE_STIMMZETTEL": 2474,
"AZ_JA_STIMMEN": 1924
}
,
{
"GEMEINDE": "Fällanden",
"BEZIRK": "Uster",
"STIMMBETEILIGUNG": "   44.37",
"AZ_GÜLTIGE_STIMMZETTEL": 2191,
"AZ_JA_STIMMEN": 1782
}
,
{
"GEMEINDE": "Greifensee",
"BEZIRK": "Uster",
"STIMMBETEILIGUNG": "   50.72",
"AZ_GÜLTIGE_STIMMZETTEL": 1671,
"AZ_JA_STIMMEN": 1406
}
,
{
"GEMEINDE": "Maur",
"BEZIRK": "Uster",
"STIMMBETEILIGUNG": "   55.73",
"AZ_GÜLTIGE_STIMMZETTEL": 3358,
"AZ_JA_STIMMEN": 2680
}
,
{
"GEMEINDE": "Mönchaltorf",
"BEZIRK": "Uster",
"STIMMBETEILIGUNG": "   50.24",
"AZ_GÜLTIGE_STIMMZETTEL": 1198,
"AZ_JA_STIMMEN": 935
}
,
{
"GEMEINDE": "Schwerzenbach",
"BEZIRK": "Uster",
"STIMMBETEILIGUNG": "   45.49",
"AZ_GÜLTIGE_STIMMZETTEL": 1283,
"AZ_JA_STIMMEN": 982
}
,
{
"GEMEINDE": "Uster",
"BEZIRK": "Uster",
"STIMMBETEILIGUNG": "   48.67",
"AZ_GÜLTIGE_STIMMZETTEL": 9626,
"AZ_JA_STIMMEN": 7547
}
,
{
"GEMEINDE": "Volketswil",
"BEZIRK": "Uster",
"STIMMBETEILIGUNG": "   42.80",
"AZ_GÜLTIGE_STIMMZETTEL": 4369,
"AZ_JA_STIMMEN": 3385
}
,
{
"GEMEINDE": "Wangen-Brüttisellen",
"BEZIRK": "Uster",
"STIMMBETEILIGUNG": "   42.36",
"AZ_GÜLTIGE_STIMMZETTEL": 1837,
"AZ_JA_STIMMEN": 1445
}
,
{
"GEMEINDE": "Altikon",
"BEZIRK": "Winterthur",
"STIMMBETEILIGUNG": "   51.48",
"AZ_GÜLTIGE_STIMMZETTEL": 232,
"AZ_JA_STIMMEN": 153
}
,
{
"GEMEINDE": "Brütten",
"BEZIRK": "Winterthur",
"STIMMBETEILIGUNG": "   51.86",
"AZ_GÜLTIGE_STIMMZETTEL": 715,
"AZ_JA_STIMMEN": 570
}
,
{
"GEMEINDE": "Dägerlen",
"BEZIRK": "Winterthur",
"STIMMBETEILIGUNG": "   49.86",
"AZ_GÜLTIGE_STIMMZETTEL": 340,
"AZ_JA_STIMMEN": 240
}
,
{
"GEMEINDE": "Dättlikon",
"BEZIRK": "Winterthur",
"STIMMBETEILIGUNG": "   53.08",
"AZ_GÜLTIGE_STIMMZETTEL": 260,
"AZ_JA_STIMMEN": 196
}
,
{
"GEMEINDE": "Dinhard",
"BEZIRK": "Winterthur",
"STIMMBETEILIGUNG": "   60.55",
"AZ_GÜLTIGE_STIMMZETTEL": 607,
"AZ_JA_STIMMEN": 392
}
,
{
"GEMEINDE": "Elgg",
"BEZIRK": "Winterthur",
"STIMMBETEILIGUNG": "   49.91",
"AZ_GÜLTIGE_STIMMZETTEL": 1285,
"AZ_JA_STIMMEN": 973
}
,
{
"GEMEINDE": "Ellikon a.d.Th.",
"BEZIRK": "Winterthur",
"STIMMBETEILIGUNG": "   63.56",
"AZ_GÜLTIGE_STIMMZETTEL": 373,
"AZ_JA_STIMMEN": 272
}
,
{
"GEMEINDE": "Elsau",
"BEZIRK": "Winterthur",
"STIMMBETEILIGUNG": "   53.00",
"AZ_GÜLTIGE_STIMMZETTEL": 1204,
"AZ_JA_STIMMEN": 906
}
,
{
"GEMEINDE": "Hagenbuch",
"BEZIRK": "Winterthur",
"STIMMBETEILIGUNG": "   45.06",
"AZ_GÜLTIGE_STIMMZETTEL": 346,
"AZ_JA_STIMMEN": 249
}
,
{
"GEMEINDE": "Hettlingen",
"BEZIRK": "Winterthur",
"STIMMBETEILIGUNG": "   54.86",
"AZ_GÜLTIGE_STIMMZETTEL": 1080,
"AZ_JA_STIMMEN": 882
}
,
{
"GEMEINDE": "Hofstetten",
"BEZIRK": "Winterthur",
"STIMMBETEILIGUNG": "   50.00",
"AZ_GÜLTIGE_STIMMZETTEL": 157,
"AZ_JA_STIMMEN": 90
}
,
{
"GEMEINDE": "Neftenbach",
"BEZIRK": "Winterthur",
"STIMMBETEILIGUNG": "   47.81",
"AZ_GÜLTIGE_STIMMZETTEL": 1652,
"AZ_JA_STIMMEN": 1272
}
,
{
"GEMEINDE": "Pfungen",
"BEZIRK": "Winterthur",
"STIMMBETEILIGUNG": "   47.98",
"AZ_GÜLTIGE_STIMMZETTEL": 789,
"AZ_JA_STIMMEN": 597
}
,
{
"GEMEINDE": "Rickenbach",
"BEZIRK": "Winterthur",
"STIMMBETEILIGUNG": "   52.00",
"AZ_GÜLTIGE_STIMMZETTEL": 916,
"AZ_JA_STIMMEN": 686
}
,
{
"GEMEINDE": "Schlatt",
"BEZIRK": "Winterthur",
"STIMMBETEILIGUNG": "   50.19",
"AZ_GÜLTIGE_STIMMZETTEL": 246,
"AZ_JA_STIMMEN": 153
}
,
{
"GEMEINDE": "Seuzach",
"BEZIRK": "Winterthur",
"STIMMBETEILIGUNG": "   52.09",
"AZ_GÜLTIGE_STIMMZETTEL": 2573,
"AZ_JA_STIMMEN": 2037
}
,
{
"GEMEINDE": "Turbenthal",
"BEZIRK": "Winterthur",
"STIMMBETEILIGUNG": "   45.93",
"AZ_GÜLTIGE_STIMMZETTEL": 1217,
"AZ_JA_STIMMEN": 841
}
,
{
"GEMEINDE": "Wiesendangen",
"BEZIRK": "Winterthur",
"STIMMBETEILIGUNG": "   54.94",
"AZ_GÜLTIGE_STIMMZETTEL": 2236,
"AZ_JA_STIMMEN": 1686
}
,
{
"GEMEINDE": "Winterthur",
"BEZIRK": "Winterthur",
"STIMMBETEILIGUNG": "   49.76",
"AZ_GÜLTIGE_STIMMZETTEL": 30791,
"AZ_JA_STIMMEN": 23846
}
,
{
"GEMEINDE": "Zell",
"BEZIRK": "Winterthur",
"STIMMBETEILIGUNG": "   44.36",
"AZ_GÜLTIGE_STIMMZETTEL": 1502,
"AZ_JA_STIMMEN": 1065
}
,
{
"GEMEINDE": "Zürich",
"BEZIRK": "Zürich",
"STIMMBETEILIGUNG": "   43.97",
"AZ_GÜLTIGE_STIMMZETTEL": 95025,
"AZ_JA_STIMMEN": 77069
}
]
