[
{
"GEMEINDE": "Aeugst a.A.",
"BEZIRK": "Affoltern",
"STIMMBETEILIGUNG": "   48.19",
"AZ_GÜLTIGE_STIMMZETTEL": 472,
"AZ_JA_STIMMEN": 148
}
,
{
"GEMEINDE": "Affoltern a.A.",
"BEZIRK": "Affoltern",
"STIMMBETEILIGUNG": "   39.91",
"AZ_GÜLTIGE_STIMMZETTEL": 2195,
"AZ_JA_STIMMEN": 708
}
,
{
"GEMEINDE": "Bonstetten",
"BEZIRK": "Affoltern",
"STIMMBETEILIGUNG": "   45.61",
"AZ_GÜLTIGE_STIMMZETTEL": 1035,
"AZ_JA_STIMMEN": 407
}
,
{
"GEMEINDE": "Hausen a.A.",
"BEZIRK": "Affoltern",
"STIMMBETEILIGUNG": "   44.40",
"AZ_GÜLTIGE_STIMMZETTEL": 859,
"AZ_JA_STIMMEN": 278
}
,
{
"GEMEINDE": "Hedingen",
"BEZIRK": "Affoltern",
"STIMMBETEILIGUNG": "   46.16",
"AZ_GÜLTIGE_STIMMZETTEL": 778,
"AZ_JA_STIMMEN": 207
}
,
{
"GEMEINDE": "Kappel a.A.",
"BEZIRK": "Affoltern",
"STIMMBETEILIGUNG": "   49.82",
"AZ_GÜLTIGE_STIMMZETTEL": 276,
"AZ_JA_STIMMEN": 99
}
,
{
"GEMEINDE": "Knonau",
"BEZIRK": "Affoltern",
"STIMMBETEILIGUNG": "   56.93",
"AZ_GÜLTIGE_STIMMZETTEL": 444,
"AZ_JA_STIMMEN": 137
}
,
{
"GEMEINDE": "Maschwanden",
"BEZIRK": "Affoltern",
"STIMMBETEILIGUNG": "   51.21",
"AZ_GÜLTIGE_STIMMZETTEL": 185,
"AZ_JA_STIMMEN": 37
}
,
{
"GEMEINDE": "Mettmenstetten",
"BEZIRK": "Affoltern",
"STIMMBETEILIGUNG": "   47.54",
"AZ_GÜLTIGE_STIMMZETTEL": 990,
"AZ_JA_STIMMEN": 332
}
,
{
"GEMEINDE": "Obfelden",
"BEZIRK": "Affoltern",
"STIMMBETEILIGUNG": "   41.01",
"AZ_GÜLTIGE_STIMMZETTEL": 1037,
"AZ_JA_STIMMEN": 377
}
,
{
"GEMEINDE": "Ottenbach",
"BEZIRK": "Affoltern",
"STIMMBETEILIGUNG": "   42.24",
"AZ_GÜLTIGE_STIMMZETTEL": 614,
"AZ_JA_STIMMEN": 216
}
,
{
"GEMEINDE": "Rifferswil",
"BEZIRK": "Affoltern",
"STIMMBETEILIGUNG": "   62.34",
"AZ_GÜLTIGE_STIMMZETTEL": 291,
"AZ_JA_STIMMEN": 71
}
,
{
"GEMEINDE": "Stallikon",
"BEZIRK": "Affoltern",
"STIMMBETEILIGUNG": "   41.60",
"AZ_GÜLTIGE_STIMMZETTEL": 695,
"AZ_JA_STIMMEN": 288
}
,
{
"GEMEINDE": "Wettswil a.A.",
"BEZIRK": "Affoltern",
"STIMMBETEILIGUNG": "   50.02",
"AZ_GÜLTIGE_STIMMZETTEL": 1227,
"AZ_JA_STIMMEN": 453
}
,
{
"GEMEINDE": "Adlikon",
"BEZIRK": "Andelfingen",
"STIMMBETEILIGUNG": "   64.91",
"AZ_GÜLTIGE_STIMMZETTEL": 238,
"AZ_JA_STIMMEN": 54
}
,
{
"GEMEINDE": "Andelfingen",
"BEZIRK": "Andelfingen",
"STIMMBETEILIGUNG": "   58.01",
"AZ_GÜLTIGE_STIMMZETTEL": 621,
"AZ_JA_STIMMEN": 125
}
,
{
"GEMEINDE": "Benken",
"BEZIRK": "Andelfingen",
"STIMMBETEILIGUNG": "   56.93",
"AZ_GÜLTIGE_STIMMZETTEL": 260,
"AZ_JA_STIMMEN": 82
}
,
{
"GEMEINDE": "Berg a.I.",
"BEZIRK": "Andelfingen",
"STIMMBETEILIGUNG": "   60.28",
"AZ_GÜLTIGE_STIMMZETTEL": 198,
"AZ_JA_STIMMEN": 42
}
,
{
"GEMEINDE": "Buch a.I.",
"BEZIRK": "Andelfingen",
"STIMMBETEILIGUNG": "   53.33",
"AZ_GÜLTIGE_STIMMZETTEL": 246,
"AZ_JA_STIMMEN": 79
}
,
{
"GEMEINDE": "Dachsen",
"BEZIRK": "Andelfingen",
"STIMMBETEILIGUNG": "   43.30",
"AZ_GÜLTIGE_STIMMZETTEL": 377,
"AZ_JA_STIMMEN": 109
}
,
{
"GEMEINDE": "Dorf",
"BEZIRK": "Andelfingen",
"STIMMBETEILIGUNG": "   57.18",
"AZ_GÜLTIGE_STIMMZETTEL": 192,
"AZ_JA_STIMMEN": 49
}
,
{
"GEMEINDE": "Feuerthalen",
"BEZIRK": "Andelfingen",
"STIMMBETEILIGUNG": "   32.77",
"AZ_GÜLTIGE_STIMMZETTEL": 610,
"AZ_JA_STIMMEN": 181
}
,
{
"GEMEINDE": "Flaach",
"BEZIRK": "Andelfingen",
"STIMMBETEILIGUNG": "   51.32",
"AZ_GÜLTIGE_STIMMZETTEL": 365,
"AZ_JA_STIMMEN": 86
}
,
{
"GEMEINDE": "Flurlingen",
"BEZIRK": "Andelfingen",
"STIMMBETEILIGUNG": "   39.58",
"AZ_GÜLTIGE_STIMMZETTEL": 327,
"AZ_JA_STIMMEN": 103
}
,
{
"GEMEINDE": "Henggart",
"BEZIRK": "Andelfingen",
"STIMMBETEILIGUNG": "   56.21",
"AZ_GÜLTIGE_STIMMZETTEL": 544,
"AZ_JA_STIMMEN": 157
}
,
{
"GEMEINDE": "Humlikon",
"BEZIRK": "Andelfingen",
"STIMMBETEILIGUNG": "   58.91",
"AZ_GÜLTIGE_STIMMZETTEL": 161,
"AZ_JA_STIMMEN": 47
}
,
{
"GEMEINDE": "Kleinandelfingen",
"BEZIRK": "Andelfingen",
"STIMMBETEILIGUNG": "   52.51",
"AZ_GÜLTIGE_STIMMZETTEL": 574,
"AZ_JA_STIMMEN": 175
}
,
{
"GEMEINDE": "Laufen-Uhwiesen",
"BEZIRK": "Andelfingen",
"STIMMBETEILIGUNG": "   40.48",
"AZ_GÜLTIGE_STIMMZETTEL": 401,
"AZ_JA_STIMMEN": 117
}
,
{
"GEMEINDE": "Marthalen",
"BEZIRK": "Andelfingen",
"STIMMBETEILIGUNG": "   47.77",
"AZ_GÜLTIGE_STIMMZETTEL": 568,
"AZ_JA_STIMMEN": 184
}
,
{
"GEMEINDE": "Oberstammheim",
"BEZIRK": "Andelfingen",
"STIMMBETEILIGUNG": "   56.52",
"AZ_GÜLTIGE_STIMMZETTEL": 411,
"AZ_JA_STIMMEN": 74
}
,
{
"GEMEINDE": "Ossingen",
"BEZIRK": "Andelfingen",
"STIMMBETEILIGUNG": "   52.00",
"AZ_GÜLTIGE_STIMMZETTEL": 422,
"AZ_JA_STIMMEN": 134
}
,
{
"GEMEINDE": "Rheinau",
"BEZIRK": "Andelfingen",
"STIMMBETEILIGUNG": "   48.28",
"AZ_GÜLTIGE_STIMMZETTEL": 355,
"AZ_JA_STIMMEN": 107
}
,
{
"GEMEINDE": "Thalheim a.d.Th.",
"BEZIRK": "Andelfingen",
"STIMMBETEILIGUNG": "   44.32",
"AZ_GÜLTIGE_STIMMZETTEL": 188,
"AZ_JA_STIMMEN": 60
}
,
{
"GEMEINDE": "Trüllikon",
"BEZIRK": "Andelfingen",
"STIMMBETEILIGUNG": "   42.80",
"AZ_GÜLTIGE_STIMMZETTEL": 304,
"AZ_JA_STIMMEN": 100
}
,
{
"GEMEINDE": "Truttikon",
"BEZIRK": "Andelfingen",
"STIMMBETEILIGUNG": "   60.43",
"AZ_GÜLTIGE_STIMMZETTEL": 166,
"AZ_JA_STIMMEN": 51
}
,
{
"GEMEINDE": "Unterstammheim",
"BEZIRK": "Andelfingen",
"STIMMBETEILIGUNG": "   45.26",
"AZ_GÜLTIGE_STIMMZETTEL": 265,
"AZ_JA_STIMMEN": 48
}
,
{
"GEMEINDE": "Volken",
"BEZIRK": "Andelfingen",
"STIMMBETEILIGUNG": "   63.10",
"AZ_GÜLTIGE_STIMMZETTEL": 107,
"AZ_JA_STIMMEN": 19
}
,
{
"GEMEINDE": "Waltalingen",
"BEZIRK": "Andelfingen",
"STIMMBETEILIGUNG": "   53.09",
"AZ_GÜLTIGE_STIMMZETTEL": 198,
"AZ_JA_STIMMEN": 43
}
,
{
"GEMEINDE": "Bachenbülach",
"BEZIRK": "Bülach",
"STIMMBETEILIGUNG": "   39.47",
"AZ_GÜLTIGE_STIMMZETTEL": 672,
"AZ_JA_STIMMEN": 267
}
,
{
"GEMEINDE": "Bassersdorf",
"BEZIRK": "Bülach",
"STIMMBETEILIGUNG": "   37.11",
"AZ_GÜLTIGE_STIMMZETTEL": 1601,
"AZ_JA_STIMMEN": 546
}
,
{
"GEMEINDE": "Bülach",
"BEZIRK": "Bülach",
"STIMMBETEILIGUNG": "   42.81",
"AZ_GÜLTIGE_STIMMZETTEL": 3625,
"AZ_JA_STIMMEN": 1363
}
,
{
"GEMEINDE": "Dietlikon",
"BEZIRK": "Bülach",
"STIMMBETEILIGUNG": "   38.12",
"AZ_GÜLTIGE_STIMMZETTEL": 1454,
"AZ_JA_STIMMEN": 481
}
,
{
"GEMEINDE": "Eglisau",
"BEZIRK": "Bülach",
"STIMMBETEILIGUNG": "   49.18",
"AZ_GÜLTIGE_STIMMZETTEL": 873,
"AZ_JA_STIMMEN": 301
}
,
{
"GEMEINDE": "Embrach",
"BEZIRK": "Bülach",
"STIMMBETEILIGUNG": "   35.26",
"AZ_GÜLTIGE_STIMMZETTEL": 1513,
"AZ_JA_STIMMEN": 536
}
,
{
"GEMEINDE": "Freienstein-Teufen",
"BEZIRK": "Bülach",
"STIMMBETEILIGUNG": "   40.17",
"AZ_GÜLTIGE_STIMMZETTEL": 508,
"AZ_JA_STIMMEN": 180
}
,
{
"GEMEINDE": "Glattfelden",
"BEZIRK": "Bülach",
"STIMMBETEILIGUNG": "   34.09",
"AZ_GÜLTIGE_STIMMZETTEL": 694,
"AZ_JA_STIMMEN": 277
}
,
{
"GEMEINDE": "Hochfelden",
"BEZIRK": "Bülach",
"STIMMBETEILIGUNG": "   43.92",
"AZ_GÜLTIGE_STIMMZETTEL": 372,
"AZ_JA_STIMMEN": 153
}
,
{
"GEMEINDE": "Höri",
"BEZIRK": "Bülach",
"STIMMBETEILIGUNG": "   33.68",
"AZ_GÜLTIGE_STIMMZETTEL": 350,
"AZ_JA_STIMMEN": 156
}
,
{
"GEMEINDE": "Hüntwangen",
"BEZIRK": "Bülach",
"STIMMBETEILIGUNG": "   45.51",
"AZ_GÜLTIGE_STIMMZETTEL": 234,
"AZ_JA_STIMMEN": 98
}
,
{
"GEMEINDE": "Kloten",
"BEZIRK": "Bülach",
"STIMMBETEILIGUNG": "   37.18",
"AZ_GÜLTIGE_STIMMZETTEL": 3670,
"AZ_JA_STIMMEN": 1243
}
,
{
"GEMEINDE": "Lufingen",
"BEZIRK": "Bülach",
"STIMMBETEILIGUNG": "   48.43",
"AZ_GÜLTIGE_STIMMZETTEL": 363,
"AZ_JA_STIMMEN": 139
}
,
{
"GEMEINDE": "Nürensdorf",
"BEZIRK": "Bülach",
"STIMMBETEILIGUNG": "   42.30",
"AZ_GÜLTIGE_STIMMZETTEL": 1197,
"AZ_JA_STIMMEN": 420
}
,
{
"GEMEINDE": "Oberembrach",
"BEZIRK": "Bülach",
"STIMMBETEILIGUNG": "   42.79",
"AZ_GÜLTIGE_STIMMZETTEL": 288,
"AZ_JA_STIMMEN": 82
}
,
{
"GEMEINDE": "Opfikon",
"BEZIRK": "Bülach",
"STIMMBETEILIGUNG": "   36.65",
"AZ_GÜLTIGE_STIMMZETTEL": 2502,
"AZ_JA_STIMMEN": 914
}
,
{
"GEMEINDE": "Rafz",
"BEZIRK": "Bülach",
"STIMMBETEILIGUNG": "   46.21",
"AZ_GÜLTIGE_STIMMZETTEL": 858,
"AZ_JA_STIMMEN": 278
}
,
{
"GEMEINDE": "Rorbas",
"BEZIRK": "Bülach",
"STIMMBETEILIGUNG": "   34.15",
"AZ_GÜLTIGE_STIMMZETTEL": 455,
"AZ_JA_STIMMEN": 158
}
,
{
"GEMEINDE": "Wallisellen",
"BEZIRK": "Bülach",
"STIMMBETEILIGUNG": "   40.06",
"AZ_GÜLTIGE_STIMMZETTEL": 2992,
"AZ_JA_STIMMEN": 995
}
,
{
"GEMEINDE": "Wasterkingen",
"BEZIRK": "Bülach",
"STIMMBETEILIGUNG": "   42.74",
"AZ_GÜLTIGE_STIMMZETTEL": 155,
"AZ_JA_STIMMEN": 42
}
,
{
"GEMEINDE": "Wil",
"BEZIRK": "Bülach",
"STIMMBETEILIGUNG": "   42.94",
"AZ_GÜLTIGE_STIMMZETTEL": 364,
"AZ_JA_STIMMEN": 127
}
,
{
"GEMEINDE": "Winkel",
"BEZIRK": "Bülach",
"STIMMBETEILIGUNG": "   43.18",
"AZ_GÜLTIGE_STIMMZETTEL": 778,
"AZ_JA_STIMMEN": 373
}
,
{
"GEMEINDE": "Bachs",
"BEZIRK": "Dielsdorf",
"STIMMBETEILIGUNG": "   58.21",
"AZ_GÜLTIGE_STIMMZETTEL": 229,
"AZ_JA_STIMMEN": 73
}
,
{
"GEMEINDE": "Boppelsen",
"BEZIRK": "Dielsdorf",
"STIMMBETEILIGUNG": "   38.93",
"AZ_GÜLTIGE_STIMMZETTEL": 223,
"AZ_JA_STIMMEN": 79
}
,
{
"GEMEINDE": "Buchs",
"BEZIRK": "Dielsdorf",
"STIMMBETEILIGUNG": "   30.12",
"AZ_GÜLTIGE_STIMMZETTEL": 747,
"AZ_JA_STIMMEN": 284
}
,
{
"GEMEINDE": "Dällikon",
"BEZIRK": "Dielsdorf",
"STIMMBETEILIGUNG": "   28.07",
"AZ_GÜLTIGE_STIMMZETTEL": 485,
"AZ_JA_STIMMEN": 209
}
,
{
"GEMEINDE": "Dänikon",
"BEZIRK": "Dielsdorf",
"STIMMBETEILIGUNG": "   35.11",
"AZ_GÜLTIGE_STIMMZETTEL": 305,
"AZ_JA_STIMMEN": 137
}
,
{
"GEMEINDE": "Dielsdorf",
"BEZIRK": "Dielsdorf",
"STIMMBETEILIGUNG": "   35.85",
"AZ_GÜLTIGE_STIMMZETTEL": 939,
"AZ_JA_STIMMEN": 327
}
,
{
"GEMEINDE": "Hüttikon",
"BEZIRK": "Dielsdorf",
"STIMMBETEILIGUNG": "   40.50",
"AZ_GÜLTIGE_STIMMZETTEL": 126,
"AZ_JA_STIMMEN": 47
}
,
{
"GEMEINDE": "Neerach",
"BEZIRK": "Dielsdorf",
"STIMMBETEILIGUNG": "   37.11",
"AZ_GÜLTIGE_STIMMZETTEL": 511,
"AZ_JA_STIMMEN": 217
}
,
{
"GEMEINDE": "Niederglatt",
"BEZIRK": "Dielsdorf",
"STIMMBETEILIGUNG": "   36.87",
"AZ_GÜLTIGE_STIMMZETTEL": 806,
"AZ_JA_STIMMEN": 302
}
,
{
"GEMEINDE": "Niederhasli",
"BEZIRK": "Dielsdorf",
"STIMMBETEILIGUNG": "   36.53",
"AZ_GÜLTIGE_STIMMZETTEL": 1396,
"AZ_JA_STIMMEN": 561
}
,
{
"GEMEINDE": "Niederweningen",
"BEZIRK": "Dielsdorf",
"STIMMBETEILIGUNG": "   36.82",
"AZ_GÜLTIGE_STIMMZETTEL": 417,
"AZ_JA_STIMMEN": 118
}
,
{
"GEMEINDE": "Oberglatt",
"BEZIRK": "Dielsdorf",
"STIMMBETEILIGUNG": "   31.50",
"AZ_GÜLTIGE_STIMMZETTEL": 840,
"AZ_JA_STIMMEN": 426
}
,
{
"GEMEINDE": "Oberweningen",
"BEZIRK": "Dielsdorf",
"STIMMBETEILIGUNG": "   42.01",
"AZ_GÜLTIGE_STIMMZETTEL": 340,
"AZ_JA_STIMMEN": 120
}
,
{
"GEMEINDE": "Otelfingen",
"BEZIRK": "Dielsdorf",
"STIMMBETEILIGUNG": "   39.33",
"AZ_GÜLTIGE_STIMMZETTEL": 420,
"AZ_JA_STIMMEN": 134
}
,
{
"GEMEINDE": "Regensberg",
"BEZIRK": "Dielsdorf",
"STIMMBETEILIGUNG": "   50.41",
"AZ_GÜLTIGE_STIMMZETTEL": 178,
"AZ_JA_STIMMEN": 52
}
,
{
"GEMEINDE": "Regensdorf",
"BEZIRK": "Dielsdorf",
"STIMMBETEILIGUNG": "   32.34",
"AZ_GÜLTIGE_STIMMZETTEL": 2566,
"AZ_JA_STIMMEN": 1088
}
,
{
"GEMEINDE": "Rümlang",
"BEZIRK": "Dielsdorf",
"STIMMBETEILIGUNG": "   37.05",
"AZ_GÜLTIGE_STIMMZETTEL": 1238,
"AZ_JA_STIMMEN": 450
}
,
{
"GEMEINDE": "Schleinikon",
"BEZIRK": "Dielsdorf",
"STIMMBETEILIGUNG": "   42.38",
"AZ_GÜLTIGE_STIMMZETTEL": 176,
"AZ_JA_STIMMEN": 42
}
,
{
"GEMEINDE": "Schöfflisdorf",
"BEZIRK": "Dielsdorf",
"STIMMBETEILIGUNG": "   42.78",
"AZ_GÜLTIGE_STIMMZETTEL": 315,
"AZ_JA_STIMMEN": 128
}
,
{
"GEMEINDE": "Stadel",
"BEZIRK": "Dielsdorf",
"STIMMBETEILIGUNG": "   48.70",
"AZ_GÜLTIGE_STIMMZETTEL": 535,
"AZ_JA_STIMMEN": 109
}
,
{
"GEMEINDE": "Steinmaur",
"BEZIRK": "Dielsdorf",
"STIMMBETEILIGUNG": "   38.40",
"AZ_GÜLTIGE_STIMMZETTEL": 688,
"AZ_JA_STIMMEN": 282
}
,
{
"GEMEINDE": "Weiach",
"BEZIRK": "Dielsdorf",
"STIMMBETEILIGUNG": "   44.63",
"AZ_GÜLTIGE_STIMMZETTEL": 258,
"AZ_JA_STIMMEN": 71
}
,
{
"GEMEINDE": "Aesch",
"BEZIRK": "Dietikon",
"STIMMBETEILIGUNG": "   51.79",
"AZ_GÜLTIGE_STIMMZETTEL": 377,
"AZ_JA_STIMMEN": 133
}
,
{
"GEMEINDE": "Birmensdorf",
"BEZIRK": "Dietikon",
"STIMMBETEILIGUNG": "   41.92",
"AZ_GÜLTIGE_STIMMZETTEL": 1379,
"AZ_JA_STIMMEN": 558
}
,
{
"GEMEINDE": "Dietikon",
"BEZIRK": "Dietikon",
"STIMMBETEILIGUNG": "   34.06",
"AZ_GÜLTIGE_STIMMZETTEL": 3880,
"AZ_JA_STIMMEN": 1302
}
,
{
"GEMEINDE": "Geroldswil",
"BEZIRK": "Dietikon",
"STIMMBETEILIGUNG": "   34.82",
"AZ_GÜLTIGE_STIMMZETTEL": 1048,
"AZ_JA_STIMMEN": 426
}
,
{
"GEMEINDE": "Oberengstringen",
"BEZIRK": "Dietikon",
"STIMMBETEILIGUNG": "   35.82",
"AZ_GÜLTIGE_STIMMZETTEL": 1369,
"AZ_JA_STIMMEN": 541
}
,
{
"GEMEINDE": "Oetwil a.d.L",
"BEZIRK": "Dietikon",
"STIMMBETEILIGUNG": "   35.36",
"AZ_GÜLTIGE_STIMMZETTEL": 705,
"AZ_JA_STIMMEN": 249
}
,
{
"GEMEINDE": "Schlieren",
"BEZIRK": "Dietikon",
"STIMMBETEILIGUNG": "   34.25",
"AZ_GÜLTIGE_STIMMZETTEL": 2418,
"AZ_JA_STIMMEN": 844
}
,
{
"GEMEINDE": "Uitikon",
"BEZIRK": "Dietikon",
"STIMMBETEILIGUNG": "   51.56",
"AZ_GÜLTIGE_STIMMZETTEL": 1181,
"AZ_JA_STIMMEN": 483
}
,
{
"GEMEINDE": "Unterengstringen",
"BEZIRK": "Dietikon",
"STIMMBETEILIGUNG": "   40.59",
"AZ_GÜLTIGE_STIMMZETTEL": 737,
"AZ_JA_STIMMEN": 270
}
,
{
"GEMEINDE": "Urdorf",
"BEZIRK": "Dietikon",
"STIMMBETEILIGUNG": "   38.74",
"AZ_GÜLTIGE_STIMMZETTEL": 2169,
"AZ_JA_STIMMEN": 709
}
,
{
"GEMEINDE": "Weiningen",
"BEZIRK": "Dietikon",
"STIMMBETEILIGUNG": "   37.88",
"AZ_GÜLTIGE_STIMMZETTEL": 874,
"AZ_JA_STIMMEN": 291
}
,
{
"GEMEINDE": "Bäretswil",
"BEZIRK": "Hinwil",
"STIMMBETEILIGUNG": "   40.13",
"AZ_GÜLTIGE_STIMMZETTEL": 1099,
"AZ_JA_STIMMEN": 402
}
,
{
"GEMEINDE": "Bubikon",
"BEZIRK": "Hinwil",
"STIMMBETEILIGUNG": "   41.03",
"AZ_GÜLTIGE_STIMMZETTEL": 1305,
"AZ_JA_STIMMEN": 419
}
,
{
"GEMEINDE": "Dürnten",
"BEZIRK": "Hinwil",
"STIMMBETEILIGUNG": "   39.96",
"AZ_GÜLTIGE_STIMMZETTEL": 1502,
"AZ_JA_STIMMEN": 436
}
,
{
"GEMEINDE": "Fischenthal",
"BEZIRK": "Hinwil",
"STIMMBETEILIGUNG": "   38.12",
"AZ_GÜLTIGE_STIMMZETTEL": 465,
"AZ_JA_STIMMEN": 111
}
,
{
"GEMEINDE": "Gossau",
"BEZIRK": "Hinwil",
"STIMMBETEILIGUNG": "   43.22",
"AZ_GÜLTIGE_STIMMZETTEL": 2230,
"AZ_JA_STIMMEN": 856
}
,
{
"GEMEINDE": "Grüningen",
"BEZIRK": "Hinwil",
"STIMMBETEILIGUNG": "   44.12",
"AZ_GÜLTIGE_STIMMZETTEL": 765,
"AZ_JA_STIMMEN": 203
}
,
{
"GEMEINDE": "Hinwil",
"BEZIRK": "Hinwil",
"STIMMBETEILIGUNG": "   40.77",
"AZ_GÜLTIGE_STIMMZETTEL": 2349,
"AZ_JA_STIMMEN": 806
}
,
{
"GEMEINDE": "Rüti",
"BEZIRK": "Hinwil",
"STIMMBETEILIGUNG": "   40.43",
"AZ_GÜLTIGE_STIMMZETTEL": 2618,
"AZ_JA_STIMMEN": 788
}
,
{
"GEMEINDE": "Seegräben",
"BEZIRK": "Hinwil",
"STIMMBETEILIGUNG": "   54.85",
"AZ_GÜLTIGE_STIMMZETTEL": 391,
"AZ_JA_STIMMEN": 126
}
,
{
"GEMEINDE": "Wald",
"BEZIRK": "Hinwil",
"STIMMBETEILIGUNG": "   38.46",
"AZ_GÜLTIGE_STIMMZETTEL": 1859,
"AZ_JA_STIMMEN": 574
}
,
{
"GEMEINDE": "Wetzikon",
"BEZIRK": "Hinwil",
"STIMMBETEILIGUNG": "   39.48",
"AZ_GÜLTIGE_STIMMZETTEL": 4117,
"AZ_JA_STIMMEN": 1462
}
,
{
"GEMEINDE": "Adliswil",
"BEZIRK": "Horgen",
"STIMMBETEILIGUNG": "   37.99",
"AZ_GÜLTIGE_STIMMZETTEL": 3855,
"AZ_JA_STIMMEN": 1409
}
,
{
"GEMEINDE": "Hirzel",
"BEZIRK": "Horgen",
"STIMMBETEILIGUNG": "   48.23",
"AZ_GÜLTIGE_STIMMZETTEL": 611,
"AZ_JA_STIMMEN": 166
}
,
{
"GEMEINDE": "Horgen",
"BEZIRK": "Horgen",
"STIMMBETEILIGUNG": "   39.38",
"AZ_GÜLTIGE_STIMMZETTEL": 3953,
"AZ_JA_STIMMEN": 1357
}
,
{
"GEMEINDE": "Hütten",
"BEZIRK": "Horgen",
"STIMMBETEILIGUNG": "   42.47",
"AZ_GÜLTIGE_STIMMZETTEL": 234,
"AZ_JA_STIMMEN": 58
}
,
{
"GEMEINDE": "Kilchberg",
"BEZIRK": "Horgen",
"STIMMBETEILIGUNG": "   46.46",
"AZ_GÜLTIGE_STIMMZETTEL": 2263,
"AZ_JA_STIMMEN": 826
}
,
{
"GEMEINDE": "Langnau a.A.",
"BEZIRK": "Horgen",
"STIMMBETEILIGUNG": "   42.70",
"AZ_GÜLTIGE_STIMMZETTEL": 1841,
"AZ_JA_STIMMEN": 662
}
,
{
"GEMEINDE": "Oberrieden",
"BEZIRK": "Horgen",
"STIMMBETEILIGUNG": "   49.83",
"AZ_GÜLTIGE_STIMMZETTEL": 1571,
"AZ_JA_STIMMEN": 540
}
,
{
"GEMEINDE": "Richterswil",
"BEZIRK": "Horgen",
"STIMMBETEILIGUNG": "   38.20",
"AZ_GÜLTIGE_STIMMZETTEL": 2436,
"AZ_JA_STIMMEN": 939
}
,
{
"GEMEINDE": "Rüschlikon",
"BEZIRK": "Horgen",
"STIMMBETEILIGUNG": "   46.48",
"AZ_GÜLTIGE_STIMMZETTEL": 1490,
"AZ_JA_STIMMEN": 584
}
,
{
"GEMEINDE": "Schönenberg",
"BEZIRK": "Horgen",
"STIMMBETEILIGUNG": "   47.35",
"AZ_GÜLTIGE_STIMMZETTEL": 581,
"AZ_JA_STIMMEN": 180
}
,
{
"GEMEINDE": "Thalwil",
"BEZIRK": "Horgen",
"STIMMBETEILIGUNG": "   42.93",
"AZ_GÜLTIGE_STIMMZETTEL": 4337,
"AZ_JA_STIMMEN": 1494
}
,
{
"GEMEINDE": "Wädenswil",
"BEZIRK": "Horgen",
"STIMMBETEILIGUNG": "   41.27",
"AZ_GÜLTIGE_STIMMZETTEL": 5047,
"AZ_JA_STIMMEN": 1726
}
,
{
"GEMEINDE": "Erlenbach",
"BEZIRK": "Meilen",
"STIMMBETEILIGUNG": "   44.08",
"AZ_GÜLTIGE_STIMMZETTEL": 1314,
"AZ_JA_STIMMEN": 497
}
,
{
"GEMEINDE": "Herrliberg",
"BEZIRK": "Meilen",
"STIMMBETEILIGUNG": "   43.83",
"AZ_GÜLTIGE_STIMMZETTEL": 1498,
"AZ_JA_STIMMEN": 598
}
,
{
"GEMEINDE": "Hombrechtikon",
"BEZIRK": "Meilen",
"STIMMBETEILIGUNG": "   38.55",
"AZ_GÜLTIGE_STIMMZETTEL": 1721,
"AZ_JA_STIMMEN": 621
}
,
{
"GEMEINDE": "Küsnacht",
"BEZIRK": "Meilen",
"STIMMBETEILIGUNG": "   47.96",
"AZ_GÜLTIGE_STIMMZETTEL": 4084,
"AZ_JA_STIMMEN": 1518
}
,
{
"GEMEINDE": "Männedorf",
"BEZIRK": "Meilen",
"STIMMBETEILIGUNG": "   43.66",
"AZ_GÜLTIGE_STIMMZETTEL": 2301,
"AZ_JA_STIMMEN": 869
}
,
{
"GEMEINDE": "Meilen",
"BEZIRK": "Meilen",
"STIMMBETEILIGUNG": "   45.64",
"AZ_GÜLTIGE_STIMMZETTEL": 3381,
"AZ_JA_STIMMEN": 1247
}
,
{
"GEMEINDE": "Oetwil a.S.",
"BEZIRK": "Meilen",
"STIMMBETEILIGUNG": "   36.42",
"AZ_GÜLTIGE_STIMMZETTEL": 558,
"AZ_JA_STIMMEN": 262
}
,
{
"GEMEINDE": "Stäfa",
"BEZIRK": "Meilen",
"STIMMBETEILIGUNG": "   41.10",
"AZ_GÜLTIGE_STIMMZETTEL": 2963,
"AZ_JA_STIMMEN": 1032
}
,
{
"GEMEINDE": "Uetikon a.S.",
"BEZIRK": "Meilen",
"STIMMBETEILIGUNG": "   43.31",
"AZ_GÜLTIGE_STIMMZETTEL": 1075,
"AZ_JA_STIMMEN": 394
}
,
{
"GEMEINDE": "Zollikon",
"BEZIRK": "Meilen",
"STIMMBETEILIGUNG": "   47.67",
"AZ_GÜLTIGE_STIMMZETTEL": 3886,
"AZ_JA_STIMMEN": 1464
}
,
{
"GEMEINDE": "Zumikon",
"BEZIRK": "Meilen",
"STIMMBETEILIGUNG": "   50.48",
"AZ_GÜLTIGE_STIMMZETTEL": 1579,
"AZ_JA_STIMMEN": 665
}
,
{
"GEMEINDE": "Bauma",
"BEZIRK": "Pfäffikon",
"STIMMBETEILIGUNG": "   38.19",
"AZ_GÜLTIGE_STIMMZETTEL": 1093,
"AZ_JA_STIMMEN": 366
}
,
{
"GEMEINDE": "Fehraltorf",
"BEZIRK": "Pfäffikon",
"STIMMBETEILIGUNG": "   37.14",
"AZ_GÜLTIGE_STIMMZETTEL": 1048,
"AZ_JA_STIMMEN": 347
}
,
{
"GEMEINDE": "Hittnau",
"BEZIRK": "Pfäffikon",
"STIMMBETEILIGUNG": "   46.91",
"AZ_GÜLTIGE_STIMMZETTEL": 748,
"AZ_JA_STIMMEN": 261
}
,
{
"GEMEINDE": "Illnau-Effretikon",
"BEZIRK": "Pfäffikon",
"STIMMBETEILIGUNG": "   41.22",
"AZ_GÜLTIGE_STIMMZETTEL": 3953,
"AZ_JA_STIMMEN": 1395
}
,
{
"GEMEINDE": "Lindau",
"BEZIRK": "Pfäffikon",
"STIMMBETEILIGUNG": "   47.42",
"AZ_GÜLTIGE_STIMMZETTEL": 964,
"AZ_JA_STIMMEN": 299
}
,
{
"GEMEINDE": "Pfäffikon",
"BEZIRK": "Pfäffikon",
"STIMMBETEILIGUNG": "   39.63",
"AZ_GÜLTIGE_STIMMZETTEL": 2208,
"AZ_JA_STIMMEN": 743
}
,
{
"GEMEINDE": "Russikon",
"BEZIRK": "Pfäffikon",
"STIMMBETEILIGUNG": "   43.97",
"AZ_GÜLTIGE_STIMMZETTEL": 1051,
"AZ_JA_STIMMEN": 331
}
,
{
"GEMEINDE": "Weisslingen",
"BEZIRK": "Pfäffikon",
"STIMMBETEILIGUNG": "   52.43",
"AZ_GÜLTIGE_STIMMZETTEL": 930,
"AZ_JA_STIMMEN": 353
}
,
{
"GEMEINDE": "Wila",
"BEZIRK": "Pfäffikon",
"STIMMBETEILIGUNG": "   43.98",
"AZ_GÜLTIGE_STIMMZETTEL": 566,
"AZ_JA_STIMMEN": 190
}
,
{
"GEMEINDE": "Wildberg",
"BEZIRK": "Pfäffikon",
"STIMMBETEILIGUNG": "   55.90",
"AZ_GÜLTIGE_STIMMZETTEL": 334,
"AZ_JA_STIMMEN": 90
}
,
{
"GEMEINDE": "Dübendorf",
"BEZIRK": "Uster",
"STIMMBETEILIGUNG": "   35.39",
"AZ_GÜLTIGE_STIMMZETTEL": 4767,
"AZ_JA_STIMMEN": 1785
}
,
{
"GEMEINDE": "Egg",
"BEZIRK": "Uster",
"STIMMBETEILIGUNG": "   41.31",
"AZ_GÜLTIGE_STIMMZETTEL": 1825,
"AZ_JA_STIMMEN": 702
}
,
{
"GEMEINDE": "Fällanden",
"BEZIRK": "Uster",
"STIMMBETEILIGUNG": "   38.63",
"AZ_GÜLTIGE_STIMMZETTEL": 1718,
"AZ_JA_STIMMEN": 712
}
,
{
"GEMEINDE": "Greifensee",
"BEZIRK": "Uster",
"STIMMBETEILIGUNG": "   41.87",
"AZ_GÜLTIGE_STIMMZETTEL": 1373,
"AZ_JA_STIMMEN": 471
}
,
{
"GEMEINDE": "Maur",
"BEZIRK": "Uster",
"STIMMBETEILIGUNG": "   44.31",
"AZ_GÜLTIGE_STIMMZETTEL": 2250,
"AZ_JA_STIMMEN": 915
}
,
{
"GEMEINDE": "Mönchaltorf",
"BEZIRK": "Uster",
"STIMMBETEILIGUNG": "   44.01",
"AZ_GÜLTIGE_STIMMZETTEL": 998,
"AZ_JA_STIMMEN": 344
}
,
{
"GEMEINDE": "Schwerzenbach",
"BEZIRK": "Uster",
"STIMMBETEILIGUNG": "   37.69",
"AZ_GÜLTIGE_STIMMZETTEL": 914,
"AZ_JA_STIMMEN": 342
}
,
{
"GEMEINDE": "Uster",
"BEZIRK": "Uster",
"STIMMBETEILIGUNG": "   40.83",
"AZ_GÜLTIGE_STIMMZETTEL": 6368,
"AZ_JA_STIMMEN": 2183
}
,
{
"GEMEINDE": "Volketswil",
"BEZIRK": "Uster",
"STIMMBETEILIGUNG": "   33.93",
"AZ_GÜLTIGE_STIMMZETTEL": 2715,
"AZ_JA_STIMMEN": 1099
}
,
{
"GEMEINDE": "Wangen-Brüttisellen",
"BEZIRK": "Uster",
"STIMMBETEILIGUNG": "   38.52",
"AZ_GÜLTIGE_STIMMZETTEL": 1088,
"AZ_JA_STIMMEN": 395
}
,
{
"GEMEINDE": "Altikon",
"BEZIRK": "Winterthur",
"STIMMBETEILIGUNG": "   51.86",
"AZ_GÜLTIGE_STIMMZETTEL": 221,
"AZ_JA_STIMMEN": 44
}
,
{
"GEMEINDE": "Brütten",
"BEZIRK": "Winterthur",
"STIMMBETEILIGUNG": "   52.09",
"AZ_GÜLTIGE_STIMMZETTEL": 581,
"AZ_JA_STIMMEN": 190
}
,
{
"GEMEINDE": "Dägerlen",
"BEZIRK": "Winterthur",
"STIMMBETEILIGUNG": "   58.96",
"AZ_GÜLTIGE_STIMMZETTEL": 307,
"AZ_JA_STIMMEN": 88
}
,
{
"GEMEINDE": "Dättlikon",
"BEZIRK": "Winterthur",
"STIMMBETEILIGUNG": "   57.41",
"AZ_GÜLTIGE_STIMMZETTEL": 207,
"AZ_JA_STIMMEN": 35
}
,
{
"GEMEINDE": "Dinhard",
"BEZIRK": "Winterthur",
"STIMMBETEILIGUNG": "   59.59",
"AZ_GÜLTIGE_STIMMZETTEL": 518,
"AZ_JA_STIMMEN": 123
}
,
{
"GEMEINDE": "Elgg",
"BEZIRK": "Winterthur",
"STIMMBETEILIGUNG": "   43.55",
"AZ_GÜLTIGE_STIMMZETTEL": 999,
"AZ_JA_STIMMEN": 269
}
,
{
"GEMEINDE": "Ellikon a.d.Th.",
"BEZIRK": "Winterthur",
"STIMMBETEILIGUNG": "   47.75",
"AZ_GÜLTIGE_STIMMZETTEL": 219,
"AZ_JA_STIMMEN": 81
}
,
{
"GEMEINDE": "Elsau",
"BEZIRK": "Winterthur",
"STIMMBETEILIGUNG": "   44.51",
"AZ_GÜLTIGE_STIMMZETTEL": 823,
"AZ_JA_STIMMEN": 246
}
,
{
"GEMEINDE": "Hagenbuch",
"BEZIRK": "Winterthur",
"STIMMBETEILIGUNG": "   40.86",
"AZ_GÜLTIGE_STIMMZETTEL": 237,
"AZ_JA_STIMMEN": 81
}
,
{
"GEMEINDE": "Hettlingen",
"BEZIRK": "Winterthur",
"STIMMBETEILIGUNG": "   48.46",
"AZ_GÜLTIGE_STIMMZETTEL": 605,
"AZ_JA_STIMMEN": 163
}
,
{
"GEMEINDE": "Hofstetten",
"BEZIRK": "Winterthur",
"STIMMBETEILIGUNG": "   58.86",
"AZ_GÜLTIGE_STIMMZETTEL": 171,
"AZ_JA_STIMMEN": 54
}
,
{
"GEMEINDE": "Neftenbach",
"BEZIRK": "Winterthur",
"STIMMBETEILIGUNG": "   40.57",
"AZ_GÜLTIGE_STIMMZETTEL": 1161,
"AZ_JA_STIMMEN": 398
}
,
{
"GEMEINDE": "Pfungen",
"BEZIRK": "Winterthur",
"STIMMBETEILIGUNG": "   40.64",
"AZ_GÜLTIGE_STIMMZETTEL": 572,
"AZ_JA_STIMMEN": 169
}
,
{
"GEMEINDE": "Rickenbach",
"BEZIRK": "Winterthur",
"STIMMBETEILIGUNG": "   44.98",
"AZ_GÜLTIGE_STIMMZETTEL": 608,
"AZ_JA_STIMMEN": 177
}
,
{
"GEMEINDE": "Schlatt",
"BEZIRK": "Winterthur",
"STIMMBETEILIGUNG": "   63.53",
"AZ_GÜLTIGE_STIMMZETTEL": 271,
"AZ_JA_STIMMEN": 90
}
,
{
"GEMEINDE": "Seuzach",
"BEZIRK": "Winterthur",
"STIMMBETEILIGUNG": "   43.25",
"AZ_GÜLTIGE_STIMMZETTEL": 1732,
"AZ_JA_STIMMEN": 589
}
,
{
"GEMEINDE": "Turbenthal",
"BEZIRK": "Winterthur",
"STIMMBETEILIGUNG": "   39.84",
"AZ_GÜLTIGE_STIMMZETTEL": 941,
"AZ_JA_STIMMEN": 302
}
,
{
"GEMEINDE": "Wiesendangen",
"BEZIRK": "Winterthur",
"STIMMBETEILIGUNG": "   50.05",
"AZ_GÜLTIGE_STIMMZETTEL": 1650,
"AZ_JA_STIMMEN": 493
}
,
{
"GEMEINDE": "Winterthur",
"BEZIRK": "Winterthur",
"STIMMBETEILIGUNG": "   39.61",
"AZ_GÜLTIGE_STIMMZETTEL": 21823,
"AZ_JA_STIMMEN": 7142
}
,
{
"GEMEINDE": "Zell",
"BEZIRK": "Winterthur",
"STIMMBETEILIGUNG": "   41.82",
"AZ_GÜLTIGE_STIMMZETTEL": 1076,
"AZ_JA_STIMMEN": 443
}
,
{
"GEMEINDE": "Zürich",
"BEZIRK": "Zürich",
"STIMMBETEILIGUNG": "   38.34",
"AZ_GÜLTIGE_STIMMZETTEL": 81805,
"AZ_JA_STIMMEN": 29505
}
]
