[
{
"GEMEINDE": "Aeugst a.A.",
"BEZIRK": "Affoltern",
"STIMMBETEILIGUNG": "   60.31",
"AZ_GÜLTIGE_STIMMZETTEL": 800,
"AZ_JA_STIMMEN": 699
}
,
{
"GEMEINDE": "Affoltern a.A.",
"BEZIRK": "Affoltern",
"STIMMBETEILIGUNG": "   53.28",
"AZ_GÜLTIGE_STIMMZETTEL": 3592,
"AZ_JA_STIMMEN": 3123
}
,
{
"GEMEINDE": "Bonstetten",
"BEZIRK": "Affoltern",
"STIMMBETEILIGUNG": "   64.43",
"AZ_GÜLTIGE_STIMMZETTEL": 2208,
"AZ_JA_STIMMEN": 1921
}
,
{
"GEMEINDE": "Hausen a.A.",
"BEZIRK": "Affoltern",
"STIMMBETEILIGUNG": "   61.51",
"AZ_GÜLTIGE_STIMMZETTEL": 1423,
"AZ_JA_STIMMEN": 1183
}
,
{
"GEMEINDE": "Hedingen",
"BEZIRK": "Affoltern",
"STIMMBETEILIGUNG": "   61.62",
"AZ_GÜLTIGE_STIMMZETTEL": 1464,
"AZ_JA_STIMMEN": 1260
}
,
{
"GEMEINDE": "Kappel a.A.",
"BEZIRK": "Affoltern",
"STIMMBETEILIGUNG": "   59.38",
"AZ_GÜLTIGE_STIMMZETTEL": 388,
"AZ_JA_STIMMEN": 333
}
,
{
"GEMEINDE": "Knonau",
"BEZIRK": "Affoltern",
"STIMMBETEILIGUNG": "   60.06",
"AZ_GÜLTIGE_STIMMZETTEL": 779,
"AZ_JA_STIMMEN": 653
}
,
{
"GEMEINDE": "Maschwanden",
"BEZIRK": "Affoltern",
"STIMMBETEILIGUNG": "   60.47",
"AZ_GÜLTIGE_STIMMZETTEL": 270,
"AZ_JA_STIMMEN": 240
}
,
{
"GEMEINDE": "Mettmenstetten",
"BEZIRK": "Affoltern",
"STIMMBETEILIGUNG": "   62.33",
"AZ_GÜLTIGE_STIMMZETTEL": 1878,
"AZ_JA_STIMMEN": 1610
}
,
{
"GEMEINDE": "Obfelden",
"BEZIRK": "Affoltern",
"STIMMBETEILIGUNG": "   57.88",
"AZ_GÜLTIGE_STIMMZETTEL": 1761,
"AZ_JA_STIMMEN": 1541
}
,
{
"GEMEINDE": "Ottenbach",
"BEZIRK": "Affoltern",
"STIMMBETEILIGUNG": "   66.10",
"AZ_GÜLTIGE_STIMMZETTEL": 1168,
"AZ_JA_STIMMEN": 1019
}
,
{
"GEMEINDE": "Rifferswil",
"BEZIRK": "Affoltern",
"STIMMBETEILIGUNG": "   67.82",
"AZ_GÜLTIGE_STIMMZETTEL": 458,
"AZ_JA_STIMMEN": 383
}
,
{
"GEMEINDE": "Stallikon",
"BEZIRK": "Affoltern",
"STIMMBETEILIGUNG": "   60.26",
"AZ_GÜLTIGE_STIMMZETTEL": 1318,
"AZ_JA_STIMMEN": 1123
}
,
{
"GEMEINDE": "Wettswil a.A.",
"BEZIRK": "Affoltern",
"STIMMBETEILIGUNG": "   66.08",
"AZ_GÜLTIGE_STIMMZETTEL": 2063,
"AZ_JA_STIMMEN": 1789
}
,
{
"GEMEINDE": "Adlikon",
"BEZIRK": "Andelfingen",
"STIMMBETEILIGUNG": "   66.74",
"AZ_GÜLTIGE_STIMMZETTEL": 295,
"AZ_JA_STIMMEN": 212
}
,
{
"GEMEINDE": "Andelfingen",
"BEZIRK": "Andelfingen",
"STIMMBETEILIGUNG": "   73.88",
"AZ_GÜLTIGE_STIMMZETTEL": 1052,
"AZ_JA_STIMMEN": 901
}
,
{
"GEMEINDE": "Benken",
"BEZIRK": "Andelfingen",
"STIMMBETEILIGUNG": "   67.87",
"AZ_GÜLTIGE_STIMMZETTEL": 399,
"AZ_JA_STIMMEN": 337
}
,
{
"GEMEINDE": "Berg a.I.",
"BEZIRK": "Andelfingen",
"STIMMBETEILIGUNG": "   69.05",
"AZ_GÜLTIGE_STIMMZETTEL": 305,
"AZ_JA_STIMMEN": 236
}
,
{
"GEMEINDE": "Buch a.I.",
"BEZIRK": "Andelfingen",
"STIMMBETEILIGUNG": "   67.78",
"AZ_GÜLTIGE_STIMMZETTEL": 429,
"AZ_JA_STIMMEN": 343
}
,
{
"GEMEINDE": "Dachsen",
"BEZIRK": "Andelfingen",
"STIMMBETEILIGUNG": "   60.69",
"AZ_GÜLTIGE_STIMMZETTEL": 774,
"AZ_JA_STIMMEN": 685
}
,
{
"GEMEINDE": "Dorf",
"BEZIRK": "Andelfingen",
"STIMMBETEILIGUNG": "   66.88",
"AZ_GÜLTIGE_STIMMZETTEL": 290,
"AZ_JA_STIMMEN": 255
}
,
{
"GEMEINDE": "Feuerthalen",
"BEZIRK": "Andelfingen",
"STIMMBETEILIGUNG": "   56.45",
"AZ_GÜLTIGE_STIMMZETTEL": 1190,
"AZ_JA_STIMMEN": 1017
}
,
{
"GEMEINDE": "Flaach",
"BEZIRK": "Andelfingen",
"STIMMBETEILIGUNG": "   63.25",
"AZ_GÜLTIGE_STIMMZETTEL": 585,
"AZ_JA_STIMMEN": 477
}
,
{
"GEMEINDE": "Flurlingen",
"BEZIRK": "Andelfingen",
"STIMMBETEILIGUNG": "   65.44",
"AZ_GÜLTIGE_STIMMZETTEL": 617,
"AZ_JA_STIMMEN": 536
}
,
{
"GEMEINDE": "Henggart",
"BEZIRK": "Andelfingen",
"STIMMBETEILIGUNG": "   60.66",
"AZ_GÜLTIGE_STIMMZETTEL": 921,
"AZ_JA_STIMMEN": 785
}
,
{
"GEMEINDE": "Humlikon",
"BEZIRK": "Andelfingen",
"STIMMBETEILIGUNG": "   66.58",
"AZ_GÜLTIGE_STIMMZETTEL": 226,
"AZ_JA_STIMMEN": 183
}
,
{
"GEMEINDE": "Kleinandelfingen",
"BEZIRK": "Andelfingen",
"STIMMBETEILIGUNG": "   63.99",
"AZ_GÜLTIGE_STIMMZETTEL": 891,
"AZ_JA_STIMMEN": 748
}
,
{
"GEMEINDE": "Laufen-Uhwiesen",
"BEZIRK": "Andelfingen",
"STIMMBETEILIGUNG": "   61.24",
"AZ_GÜLTIGE_STIMMZETTEL": 678,
"AZ_JA_STIMMEN": 561
}
,
{
"GEMEINDE": "Marthalen",
"BEZIRK": "Andelfingen",
"STIMMBETEILIGUNG": "   60.68",
"AZ_GÜLTIGE_STIMMZETTEL": 857,
"AZ_JA_STIMMEN": 684
}
,
{
"GEMEINDE": "Oberstammheim",
"BEZIRK": "Andelfingen",
"STIMMBETEILIGUNG": "   62.40",
"AZ_GÜLTIGE_STIMMZETTEL": 538,
"AZ_JA_STIMMEN": 453
}
,
{
"GEMEINDE": "Ossingen",
"BEZIRK": "Andelfingen",
"STIMMBETEILIGUNG": "   62.16",
"AZ_GÜLTIGE_STIMMZETTEL": 592,
"AZ_JA_STIMMEN": 476
}
,
{
"GEMEINDE": "Rheinau",
"BEZIRK": "Andelfingen",
"STIMMBETEILIGUNG": "   63.74",
"AZ_GÜLTIGE_STIMMZETTEL": 563,
"AZ_JA_STIMMEN": 479
}
,
{
"GEMEINDE": "Thalheim a.d.Th.",
"BEZIRK": "Andelfingen",
"STIMMBETEILIGUNG": "   59.60",
"AZ_GÜLTIGE_STIMMZETTEL": 375,
"AZ_JA_STIMMEN": 285
}
,
{
"GEMEINDE": "Trüllikon",
"BEZIRK": "Andelfingen",
"STIMMBETEILIGUNG": "   57.92",
"AZ_GÜLTIGE_STIMMZETTEL": 432,
"AZ_JA_STIMMEN": 341
}
,
{
"GEMEINDE": "Truttikon",
"BEZIRK": "Andelfingen",
"STIMMBETEILIGUNG": "   66.57",
"AZ_GÜLTIGE_STIMMZETTEL": 218,
"AZ_JA_STIMMEN": 170
}
,
{
"GEMEINDE": "Unterstammheim",
"BEZIRK": "Andelfingen",
"STIMMBETEILIGUNG": "   66.67",
"AZ_GÜLTIGE_STIMMZETTEL": 407,
"AZ_JA_STIMMEN": 341
}
,
{
"GEMEINDE": "Volken",
"BEZIRK": "Andelfingen",
"STIMMBETEILIGUNG": "   64.53",
"AZ_GÜLTIGE_STIMMZETTEL": 128,
"AZ_JA_STIMMEN": 105
}
,
{
"GEMEINDE": "Waltalingen",
"BEZIRK": "Andelfingen",
"STIMMBETEILIGUNG": "   61.04",
"AZ_GÜLTIGE_STIMMZETTEL": 310,
"AZ_JA_STIMMEN": 270
}
,
{
"GEMEINDE": "Bachenbülach",
"BEZIRK": "Bülach",
"STIMMBETEILIGUNG": "   49.01",
"AZ_GÜLTIGE_STIMMZETTEL": 1173,
"AZ_JA_STIMMEN": 1043
}
,
{
"GEMEINDE": "Bassersdorf",
"BEZIRK": "Bülach",
"STIMMBETEILIGUNG": "   52.74",
"AZ_GÜLTIGE_STIMMZETTEL": 3571,
"AZ_JA_STIMMEN": 3087
}
,
{
"GEMEINDE": "Bülach",
"BEZIRK": "Bülach",
"STIMMBETEILIGUNG": "   51.66",
"AZ_GÜLTIGE_STIMMZETTEL": 5684,
"AZ_JA_STIMMEN": 5028
}
,
{
"GEMEINDE": "Dietlikon",
"BEZIRK": "Bülach",
"STIMMBETEILIGUNG": "   57.15",
"AZ_GÜLTIGE_STIMMZETTEL": 2567,
"AZ_JA_STIMMEN": 2245
}
,
{
"GEMEINDE": "Eglisau",
"BEZIRK": "Bülach",
"STIMMBETEILIGUNG": "   62.63",
"AZ_GÜLTIGE_STIMMZETTEL": 1869,
"AZ_JA_STIMMEN": 1637
}
,
{
"GEMEINDE": "Embrach",
"BEZIRK": "Bülach",
"STIMMBETEILIGUNG": "   49.95",
"AZ_GÜLTIGE_STIMMZETTEL": 2653,
"AZ_JA_STIMMEN": 2281
}
,
{
"GEMEINDE": "Freienstein-Teufen",
"BEZIRK": "Bülach",
"STIMMBETEILIGUNG": "   63.18",
"AZ_GÜLTIGE_STIMMZETTEL": 990,
"AZ_JA_STIMMEN": 879
}
,
{
"GEMEINDE": "Glattfelden",
"BEZIRK": "Bülach",
"STIMMBETEILIGUNG": "   57.94",
"AZ_GÜLTIGE_STIMMZETTEL": 1642,
"AZ_JA_STIMMEN": 1420
}
,
{
"GEMEINDE": "Hochfelden",
"BEZIRK": "Bülach",
"STIMMBETEILIGUNG": "   59.40",
"AZ_GÜLTIGE_STIMMZETTEL": 759,
"AZ_JA_STIMMEN": 662
}
,
{
"GEMEINDE": "Höri",
"BEZIRK": "Bülach",
"STIMMBETEILIGUNG": "   45.20",
"AZ_GÜLTIGE_STIMMZETTEL": 659,
"AZ_JA_STIMMEN": 514
}
,
{
"GEMEINDE": "Hüntwangen",
"BEZIRK": "Bülach",
"STIMMBETEILIGUNG": "   67.75",
"AZ_GÜLTIGE_STIMMZETTEL": 499,
"AZ_JA_STIMMEN": 427
}
,
{
"GEMEINDE": "Kloten",
"BEZIRK": "Bülach",
"STIMMBETEILIGUNG": "   47.91",
"AZ_GÜLTIGE_STIMMZETTEL": 4932,
"AZ_JA_STIMMEN": 4125
}
,
{
"GEMEINDE": "Lufingen",
"BEZIRK": "Bülach",
"STIMMBETEILIGUNG": "   56.79",
"AZ_GÜLTIGE_STIMMZETTEL": 669,
"AZ_JA_STIMMEN": 563
}
,
{
"GEMEINDE": "Nürensdorf",
"BEZIRK": "Bülach",
"STIMMBETEILIGUNG": "   64.38",
"AZ_GÜLTIGE_STIMMZETTEL": 2357,
"AZ_JA_STIMMEN": 1975
}
,
{
"GEMEINDE": "Oberembrach",
"BEZIRK": "Bülach",
"STIMMBETEILIGUNG": "   60.10",
"AZ_GÜLTIGE_STIMMZETTEL": 478,
"AZ_JA_STIMMEN": 367
}
,
{
"GEMEINDE": "Opfikon",
"BEZIRK": "Bülach",
"STIMMBETEILIGUNG": "   45.08",
"AZ_GÜLTIGE_STIMMZETTEL": 3340,
"AZ_JA_STIMMEN": 2754
}
,
{
"GEMEINDE": "Rafz",
"BEZIRK": "Bülach",
"STIMMBETEILIGUNG": "   62.56",
"AZ_GÜLTIGE_STIMMZETTEL": 1636,
"AZ_JA_STIMMEN": 1382
}
,
{
"GEMEINDE": "Rorbas",
"BEZIRK": "Bülach",
"STIMMBETEILIGUNG": "   49.12",
"AZ_GÜLTIGE_STIMMZETTEL": 728,
"AZ_JA_STIMMEN": 617
}
,
{
"GEMEINDE": "Wallisellen",
"BEZIRK": "Bülach",
"STIMMBETEILIGUNG": "   54.83",
"AZ_GÜLTIGE_STIMMZETTEL": 4717,
"AZ_JA_STIMMEN": 4117
}
,
{
"GEMEINDE": "Wasterkingen",
"BEZIRK": "Bülach",
"STIMMBETEILIGUNG": "   63.32",
"AZ_GÜLTIGE_STIMMZETTEL": 262,
"AZ_JA_STIMMEN": 229
}
,
{
"GEMEINDE": "Wil",
"BEZIRK": "Bülach",
"STIMMBETEILIGUNG": "   61.32",
"AZ_GÜLTIGE_STIMMZETTEL": 597,
"AZ_JA_STIMMEN": 494
}
,
{
"GEMEINDE": "Winkel",
"BEZIRK": "Bülach",
"STIMMBETEILIGUNG": "   60.61",
"AZ_GÜLTIGE_STIMMZETTEL": 1744,
"AZ_JA_STIMMEN": 1480
}
,
{
"GEMEINDE": "Bachs",
"BEZIRK": "Dielsdorf",
"STIMMBETEILIGUNG": "   61.57",
"AZ_GÜLTIGE_STIMMZETTEL": 266,
"AZ_JA_STIMMEN": 214
}
,
{
"GEMEINDE": "Boppelsen",
"BEZIRK": "Dielsdorf",
"STIMMBETEILIGUNG": "   62.01",
"AZ_GÜLTIGE_STIMMZETTEL": 530,
"AZ_JA_STIMMEN": 435
}
,
{
"GEMEINDE": "Buchs",
"BEZIRK": "Dielsdorf",
"STIMMBETEILIGUNG": "   50.09",
"AZ_GÜLTIGE_STIMMZETTEL": 1828,
"AZ_JA_STIMMEN": 1530
}
,
{
"GEMEINDE": "Dällikon",
"BEZIRK": "Dielsdorf",
"STIMMBETEILIGUNG": "   50.02",
"AZ_GÜLTIGE_STIMMZETTEL": 1090,
"AZ_JA_STIMMEN": 932
}
,
{
"GEMEINDE": "Dänikon",
"BEZIRK": "Dielsdorf",
"STIMMBETEILIGUNG": "   54.75",
"AZ_GÜLTIGE_STIMMZETTEL": 603,
"AZ_JA_STIMMEN": 505
}
,
{
"GEMEINDE": "Dielsdorf",
"BEZIRK": "Dielsdorf",
"STIMMBETEILIGUNG": "   53.03",
"AZ_GÜLTIGE_STIMMZETTEL": 1805,
"AZ_JA_STIMMEN": 1556
}
,
{
"GEMEINDE": "Hüttikon",
"BEZIRK": "Dielsdorf",
"STIMMBETEILIGUNG": "   58.49",
"AZ_GÜLTIGE_STIMMZETTEL": 274,
"AZ_JA_STIMMEN": 217
}
,
{
"GEMEINDE": "Neerach",
"BEZIRK": "Dielsdorf",
"STIMMBETEILIGUNG": "   61.50",
"AZ_GÜLTIGE_STIMMZETTEL": 1362,
"AZ_JA_STIMMEN": 1135
}
,
{
"GEMEINDE": "Niederglatt",
"BEZIRK": "Dielsdorf",
"STIMMBETEILIGUNG": "   50.09",
"AZ_GÜLTIGE_STIMMZETTEL": 1375,
"AZ_JA_STIMMEN": 1156
}
,
{
"GEMEINDE": "Niederhasli",
"BEZIRK": "Dielsdorf",
"STIMMBETEILIGUNG": "   49.79",
"AZ_GÜLTIGE_STIMMZETTEL": 2605,
"AZ_JA_STIMMEN": 2222
}
,
{
"GEMEINDE": "Niederweningen",
"BEZIRK": "Dielsdorf",
"STIMMBETEILIGUNG": "   59.21",
"AZ_GÜLTIGE_STIMMZETTEL": 1072,
"AZ_JA_STIMMEN": 948
}
,
{
"GEMEINDE": "Oberglatt",
"BEZIRK": "Dielsdorf",
"STIMMBETEILIGUNG": "   41.75",
"AZ_GÜLTIGE_STIMMZETTEL": 1342,
"AZ_JA_STIMMEN": 1162
}
,
{
"GEMEINDE": "Oberweningen",
"BEZIRK": "Dielsdorf",
"STIMMBETEILIGUNG": "   60.98",
"AZ_GÜLTIGE_STIMMZETTEL": 670,
"AZ_JA_STIMMEN": 580
}
,
{
"GEMEINDE": "Otelfingen",
"BEZIRK": "Dielsdorf",
"STIMMBETEILIGUNG": "   58.91",
"AZ_GÜLTIGE_STIMMZETTEL": 991,
"AZ_JA_STIMMEN": 837
}
,
{
"GEMEINDE": "Regensberg",
"BEZIRK": "Dielsdorf",
"STIMMBETEILIGUNG": "   66.25",
"AZ_GÜLTIGE_STIMMZETTEL": 202,
"AZ_JA_STIMMEN": 169
}
,
{
"GEMEINDE": "Regensdorf",
"BEZIRK": "Dielsdorf",
"STIMMBETEILIGUNG": "   48.41",
"AZ_GÜLTIGE_STIMMZETTEL": 4382,
"AZ_JA_STIMMEN": 3690
}
,
{
"GEMEINDE": "Rümlang",
"BEZIRK": "Dielsdorf",
"STIMMBETEILIGUNG": "   48.37",
"AZ_GÜLTIGE_STIMMZETTEL": 1996,
"AZ_JA_STIMMEN": 1673
}
,
{
"GEMEINDE": "Schleinikon",
"BEZIRK": "Dielsdorf",
"STIMMBETEILIGUNG": "   57.87",
"AZ_GÜLTIGE_STIMMZETTEL": 303,
"AZ_JA_STIMMEN": 265
}
,
{
"GEMEINDE": "Schöfflisdorf",
"BEZIRK": "Dielsdorf",
"STIMMBETEILIGUNG": "   60.19",
"AZ_GÜLTIGE_STIMMZETTEL": 564,
"AZ_JA_STIMMEN": 498
}
,
{
"GEMEINDE": "Stadel",
"BEZIRK": "Dielsdorf",
"STIMMBETEILIGUNG": "   53.22",
"AZ_GÜLTIGE_STIMMZETTEL": 772,
"AZ_JA_STIMMEN": 659
}
,
{
"GEMEINDE": "Steinmaur",
"BEZIRK": "Dielsdorf",
"STIMMBETEILIGUNG": "   57.76",
"AZ_GÜLTIGE_STIMMZETTEL": 1201,
"AZ_JA_STIMMEN": 1049
}
,
{
"GEMEINDE": "Weiach",
"BEZIRK": "Dielsdorf",
"STIMMBETEILIGUNG": "   53.42",
"AZ_GÜLTIGE_STIMMZETTEL": 387,
"AZ_JA_STIMMEN": 321
}
,
{
"GEMEINDE": "Aesch",
"BEZIRK": "Dietikon",
"STIMMBETEILIGUNG": "   69.39",
"AZ_GÜLTIGE_STIMMZETTEL": 543,
"AZ_JA_STIMMEN": 434
}
,
{
"GEMEINDE": "Birmensdorf",
"BEZIRK": "Dietikon",
"STIMMBETEILIGUNG": "   59.45",
"AZ_GÜLTIGE_STIMMZETTEL": 2260,
"AZ_JA_STIMMEN": 1927
}
,
{
"GEMEINDE": "Dietikon",
"BEZIRK": "Dietikon",
"STIMMBETEILIGUNG": "   44.71",
"AZ_GÜLTIGE_STIMMZETTEL": 5380,
"AZ_JA_STIMMEN": 4693
}
,
{
"GEMEINDE": "Geroldswil",
"BEZIRK": "Dietikon",
"STIMMBETEILIGUNG": "   54.06",
"AZ_GÜLTIGE_STIMMZETTEL": 1533,
"AZ_JA_STIMMEN": 1306
}
,
{
"GEMEINDE": "Oberengstringen",
"BEZIRK": "Dietikon",
"STIMMBETEILIGUNG": "   51.09",
"AZ_GÜLTIGE_STIMMZETTEL": 1915,
"AZ_JA_STIMMEN": 1681
}
,
{
"GEMEINDE": "Oetwil a.d.L",
"BEZIRK": "Dietikon",
"STIMMBETEILIGUNG": "   59.03",
"AZ_GÜLTIGE_STIMMZETTEL": 958,
"AZ_JA_STIMMEN": 806
}
,
{
"GEMEINDE": "Schlieren",
"BEZIRK": "Dietikon",
"STIMMBETEILIGUNG": "   41.56",
"AZ_GÜLTIGE_STIMMZETTEL": 3212,
"AZ_JA_STIMMEN": 2811
}
,
{
"GEMEINDE": "Uitikon",
"BEZIRK": "Dietikon",
"STIMMBETEILIGUNG": "   69.40",
"AZ_GÜLTIGE_STIMMZETTEL": 1878,
"AZ_JA_STIMMEN": 1587
}
,
{
"GEMEINDE": "Unterengstringen",
"BEZIRK": "Dietikon",
"STIMMBETEILIGUNG": "   57.43",
"AZ_GÜLTIGE_STIMMZETTEL": 1291,
"AZ_JA_STIMMEN": 1092
}
,
{
"GEMEINDE": "Urdorf",
"BEZIRK": "Dietikon",
"STIMMBETEILIGUNG": "   54.86",
"AZ_GÜLTIGE_STIMMZETTEL": 3218,
"AZ_JA_STIMMEN": 2809
}
,
{
"GEMEINDE": "Weiningen",
"BEZIRK": "Dietikon",
"STIMMBETEILIGUNG": "   53.27",
"AZ_GÜLTIGE_STIMMZETTEL": 1369,
"AZ_JA_STIMMEN": 1118
}
,
{
"GEMEINDE": "Bäretswil",
"BEZIRK": "Hinwil",
"STIMMBETEILIGUNG": "   62.62",
"AZ_GÜLTIGE_STIMMZETTEL": 2151,
"AZ_JA_STIMMEN": 1791
}
,
{
"GEMEINDE": "Bubikon",
"BEZIRK": "Hinwil",
"STIMMBETEILIGUNG": "   59.32",
"AZ_GÜLTIGE_STIMMZETTEL": 2835,
"AZ_JA_STIMMEN": 2437
}
,
{
"GEMEINDE": "Dürnten",
"BEZIRK": "Hinwil",
"STIMMBETEILIGUNG": "   57.18",
"AZ_GÜLTIGE_STIMMZETTEL": 2644,
"AZ_JA_STIMMEN": 2292
}
,
{
"GEMEINDE": "Fischenthal",
"BEZIRK": "Hinwil",
"STIMMBETEILIGUNG": "   47.72",
"AZ_GÜLTIGE_STIMMZETTEL": 746,
"AZ_JA_STIMMEN": 566
}
,
{
"GEMEINDE": "Gossau",
"BEZIRK": "Hinwil",
"STIMMBETEILIGUNG": "   58.84",
"AZ_GÜLTIGE_STIMMZETTEL": 3850,
"AZ_JA_STIMMEN": 3250
}
,
{
"GEMEINDE": "Grüningen",
"BEZIRK": "Hinwil",
"STIMMBETEILIGUNG": "   60.51",
"AZ_GÜLTIGE_STIMMZETTEL": 1375,
"AZ_JA_STIMMEN": 1152
}
,
{
"GEMEINDE": "Hinwil",
"BEZIRK": "Hinwil",
"STIMMBETEILIGUNG": "   57.19",
"AZ_GÜLTIGE_STIMMZETTEL": 4120,
"AZ_JA_STIMMEN": 3460
}
,
{
"GEMEINDE": "Rüti",
"BEZIRK": "Hinwil",
"STIMMBETEILIGUNG": "   53.22",
"AZ_GÜLTIGE_STIMMZETTEL": 3904,
"AZ_JA_STIMMEN": 3391
}
,
{
"GEMEINDE": "Seegräben",
"BEZIRK": "Hinwil",
"STIMMBETEILIGUNG": "   63.52",
"AZ_GÜLTIGE_STIMMZETTEL": 572,
"AZ_JA_STIMMEN": 512
}
,
{
"GEMEINDE": "Wald",
"BEZIRK": "Hinwil",
"STIMMBETEILIGUNG": "   52.59",
"AZ_GÜLTIGE_STIMMZETTEL": 2947,
"AZ_JA_STIMMEN": 2510
}
,
{
"GEMEINDE": "Wetzikon",
"BEZIRK": "Hinwil",
"STIMMBETEILIGUNG": "   52.14",
"AZ_GÜLTIGE_STIMMZETTEL": 7463,
"AZ_JA_STIMMEN": 6359
}
,
{
"GEMEINDE": "Adliswil",
"BEZIRK": "Horgen",
"STIMMBETEILIGUNG": "   55.19",
"AZ_GÜLTIGE_STIMMZETTEL": 5437,
"AZ_JA_STIMMEN": 4756
}
,
{
"GEMEINDE": "Hirzel",
"BEZIRK": "Horgen",
"STIMMBETEILIGUNG": "   62.16",
"AZ_GÜLTIGE_STIMMZETTEL": 886,
"AZ_JA_STIMMEN": 789
}
,
{
"GEMEINDE": "Horgen",
"BEZIRK": "Horgen",
"STIMMBETEILIGUNG": "   55.89",
"AZ_GÜLTIGE_STIMMZETTEL": 6266,
"AZ_JA_STIMMEN": 5552
}
,
{
"GEMEINDE": "Hütten",
"BEZIRK": "Horgen",
"STIMMBETEILIGUNG": "   54.07",
"AZ_GÜLTIGE_STIMMZETTEL": 356,
"AZ_JA_STIMMEN": 291
}
,
{
"GEMEINDE": "Kilchberg",
"BEZIRK": "Horgen",
"STIMMBETEILIGUNG": "   63.44",
"AZ_GÜLTIGE_STIMMZETTEL": 2887,
"AZ_JA_STIMMEN": 2480
}
,
{
"GEMEINDE": "Langnau a.A.",
"BEZIRK": "Horgen",
"STIMMBETEILIGUNG": "   58.19",
"AZ_GÜLTIGE_STIMMZETTEL": 2569,
"AZ_JA_STIMMEN": 2281
}
,
{
"GEMEINDE": "Oberrieden",
"BEZIRK": "Horgen",
"STIMMBETEILIGUNG": "   67.15",
"AZ_GÜLTIGE_STIMMZETTEL": 2255,
"AZ_JA_STIMMEN": 1982
}
,
{
"GEMEINDE": "Richterswil",
"BEZIRK": "Horgen",
"STIMMBETEILIGUNG": "   59.04",
"AZ_GÜLTIGE_STIMMZETTEL": 4840,
"AZ_JA_STIMMEN": 4218
}
,
{
"GEMEINDE": "Rüschlikon",
"BEZIRK": "Horgen",
"STIMMBETEILIGUNG": "   61.65",
"AZ_GÜLTIGE_STIMMZETTEL": 2036,
"AZ_JA_STIMMEN": 1772
}
,
{
"GEMEINDE": "Schönenberg",
"BEZIRK": "Horgen",
"STIMMBETEILIGUNG": "   62.10",
"AZ_GÜLTIGE_STIMMZETTEL": 843,
"AZ_JA_STIMMEN": 707
}
,
{
"GEMEINDE": "Thalwil",
"BEZIRK": "Horgen",
"STIMMBETEILIGUNG": "   60.54",
"AZ_GÜLTIGE_STIMMZETTEL": 6425,
"AZ_JA_STIMMEN": 5666
}
,
{
"GEMEINDE": "Wädenswil",
"BEZIRK": "Horgen",
"STIMMBETEILIGUNG": "   57.23",
"AZ_GÜLTIGE_STIMMZETTEL": 7573,
"AZ_JA_STIMMEN": 6622
}
,
{
"GEMEINDE": "Erlenbach",
"BEZIRK": "Meilen",
"STIMMBETEILIGUNG": "   67.80",
"AZ_GÜLTIGE_STIMMZETTEL": 2294,
"AZ_JA_STIMMEN": 1965
}
,
{
"GEMEINDE": "Herrliberg",
"BEZIRK": "Meilen",
"STIMMBETEILIGUNG": "   67.43",
"AZ_GÜLTIGE_STIMMZETTEL": 2677,
"AZ_JA_STIMMEN": 2229
}
,
{
"GEMEINDE": "Hombrechtikon",
"BEZIRK": "Meilen",
"STIMMBETEILIGUNG": "   58.67",
"AZ_GÜLTIGE_STIMMZETTEL": 3133,
"AZ_JA_STIMMEN": 2671
}
,
{
"GEMEINDE": "Küsnacht",
"BEZIRK": "Meilen",
"STIMMBETEILIGUNG": "   65.59",
"AZ_GÜLTIGE_STIMMZETTEL": 5776,
"AZ_JA_STIMMEN": 4919
}
,
{
"GEMEINDE": "Männedorf",
"BEZIRK": "Meilen",
"STIMMBETEILIGUNG": "   65.04",
"AZ_GÜLTIGE_STIMMZETTEL": 4442,
"AZ_JA_STIMMEN": 3882
}
,
{
"GEMEINDE": "Meilen",
"BEZIRK": "Meilen",
"STIMMBETEILIGUNG": "   63.81",
"AZ_GÜLTIGE_STIMMZETTEL": 5270,
"AZ_JA_STIMMEN": 4474
}
,
{
"GEMEINDE": "Oetwil a.S.",
"BEZIRK": "Meilen",
"STIMMBETEILIGUNG": "   52.34",
"AZ_GÜLTIGE_STIMMZETTEL": 1342,
"AZ_JA_STIMMEN": 1136
}
,
{
"GEMEINDE": "Stäfa",
"BEZIRK": "Meilen",
"STIMMBETEILIGUNG": "   65.62",
"AZ_GÜLTIGE_STIMMZETTEL": 6089,
"AZ_JA_STIMMEN": 5324
}
,
{
"GEMEINDE": "Uetikon a.S.",
"BEZIRK": "Meilen",
"STIMMBETEILIGUNG": "   64.75",
"AZ_GÜLTIGE_STIMMZETTEL": 2473,
"AZ_JA_STIMMEN": 2147
}
,
{
"GEMEINDE": "Zollikon",
"BEZIRK": "Meilen",
"STIMMBETEILIGUNG": "   66.26",
"AZ_GÜLTIGE_STIMMZETTEL": 5280,
"AZ_JA_STIMMEN": 4422
}
,
{
"GEMEINDE": "Zumikon",
"BEZIRK": "Meilen",
"STIMMBETEILIGUNG": "   69.37",
"AZ_GÜLTIGE_STIMMZETTEL": 2248,
"AZ_JA_STIMMEN": 1892
}
,
{
"GEMEINDE": "Bauma",
"BEZIRK": "Pfäffikon",
"STIMMBETEILIGUNG": "   58.93",
"AZ_GÜLTIGE_STIMMZETTEL": 1866,
"AZ_JA_STIMMEN": 1514
}
,
{
"GEMEINDE": "Fehraltorf",
"BEZIRK": "Pfäffikon",
"STIMMBETEILIGUNG": "   56.59",
"AZ_GÜLTIGE_STIMMZETTEL": 2317,
"AZ_JA_STIMMEN": 1956
}
,
{
"GEMEINDE": "Hittnau",
"BEZIRK": "Pfäffikon",
"STIMMBETEILIGUNG": "   62.06",
"AZ_GÜLTIGE_STIMMZETTEL": 1534,
"AZ_JA_STIMMEN": 1308
}
,
{
"GEMEINDE": "Illnau-Effretikon",
"BEZIRK": "Pfäffikon",
"STIMMBETEILIGUNG": "   55.02",
"AZ_GÜLTIGE_STIMMZETTEL": 5564,
"AZ_JA_STIMMEN": 4784
}
,
{
"GEMEINDE": "Lindau",
"BEZIRK": "Pfäffikon",
"STIMMBETEILIGUNG": "   58.51",
"AZ_GÜLTIGE_STIMMZETTEL": 1907,
"AZ_JA_STIMMEN": 1630
}
,
{
"GEMEINDE": "Pfäffikon",
"BEZIRK": "Pfäffikon",
"STIMMBETEILIGUNG": "   58.81",
"AZ_GÜLTIGE_STIMMZETTEL": 4252,
"AZ_JA_STIMMEN": 3654
}
,
{
"GEMEINDE": "Russikon",
"BEZIRK": "Pfäffikon",
"STIMMBETEILIGUNG": "   59.95",
"AZ_GÜLTIGE_STIMMZETTEL": 1676,
"AZ_JA_STIMMEN": 1350
}
,
{
"GEMEINDE": "Weisslingen",
"BEZIRK": "Pfäffikon",
"STIMMBETEILIGUNG": "   63.08",
"AZ_GÜLTIGE_STIMMZETTEL": 1435,
"AZ_JA_STIMMEN": 1202
}
,
{
"GEMEINDE": "Wila",
"BEZIRK": "Pfäffikon",
"STIMMBETEILIGUNG": "   57.07",
"AZ_GÜLTIGE_STIMMZETTEL": 772,
"AZ_JA_STIMMEN": 645
}
,
{
"GEMEINDE": "Wildberg",
"BEZIRK": "Pfäffikon",
"STIMMBETEILIGUNG": "   65.89",
"AZ_GÜLTIGE_STIMMZETTEL": 465,
"AZ_JA_STIMMEN": 373
}
,
{
"GEMEINDE": "Dübendorf",
"BEZIRK": "Uster",
"STIMMBETEILIGUNG": "   51.14",
"AZ_GÜLTIGE_STIMMZETTEL": 7270,
"AZ_JA_STIMMEN": 6193
}
,
{
"GEMEINDE": "Egg",
"BEZIRK": "Uster",
"STIMMBETEILIGUNG": "   61.70",
"AZ_GÜLTIGE_STIMMZETTEL": 3278,
"AZ_JA_STIMMEN": 2771
}
,
{
"GEMEINDE": "Fällanden",
"BEZIRK": "Uster",
"STIMMBETEILIGUNG": "   54.25",
"AZ_GÜLTIGE_STIMMZETTEL": 2716,
"AZ_JA_STIMMEN": 2337
}
,
{
"GEMEINDE": "Greifensee",
"BEZIRK": "Uster",
"STIMMBETEILIGUNG": "   63.55",
"AZ_GÜLTIGE_STIMMZETTEL": 2115,
"AZ_JA_STIMMEN": 1877
}
,
{
"GEMEINDE": "Maur",
"BEZIRK": "Uster",
"STIMMBETEILIGUNG": "   63.58",
"AZ_GÜLTIGE_STIMMZETTEL": 3950,
"AZ_JA_STIMMEN": 3403
}
,
{
"GEMEINDE": "Mönchaltorf",
"BEZIRK": "Uster",
"STIMMBETEILIGUNG": "   60.71",
"AZ_GÜLTIGE_STIMMZETTEL": 1434,
"AZ_JA_STIMMEN": 1270
}
,
{
"GEMEINDE": "Schwerzenbach",
"BEZIRK": "Uster",
"STIMMBETEILIGUNG": "   54.51",
"AZ_GÜLTIGE_STIMMZETTEL": 1658,
"AZ_JA_STIMMEN": 1455
}
,
{
"GEMEINDE": "Uster",
"BEZIRK": "Uster",
"STIMMBETEILIGUNG": "   58.72",
"AZ_GÜLTIGE_STIMMZETTEL": 11948,
"AZ_JA_STIMMEN": 10445
}
,
{
"GEMEINDE": "Volketswil",
"BEZIRK": "Uster",
"STIMMBETEILIGUNG": "   52.06",
"AZ_GÜLTIGE_STIMMZETTEL": 5604,
"AZ_JA_STIMMEN": 4696
}
,
{
"GEMEINDE": "Wangen-Brüttisellen",
"BEZIRK": "Uster",
"STIMMBETEILIGUNG": "   51.25",
"AZ_GÜLTIGE_STIMMZETTEL": 2257,
"AZ_JA_STIMMEN": 1885
}
,
{
"GEMEINDE": "Altikon",
"BEZIRK": "Winterthur",
"STIMMBETEILIGUNG": "   65.68",
"AZ_GÜLTIGE_STIMMZETTEL": 302,
"AZ_JA_STIMMEN": 239
}
,
{
"GEMEINDE": "Brütten",
"BEZIRK": "Winterthur",
"STIMMBETEILIGUNG": "   67.32",
"AZ_GÜLTIGE_STIMMZETTEL": 988,
"AZ_JA_STIMMEN": 835
}
,
{
"GEMEINDE": "Dägerlen",
"BEZIRK": "Winterthur",
"STIMMBETEILIGUNG": "   63.88",
"AZ_GÜLTIGE_STIMMZETTEL": 433,
"AZ_JA_STIMMEN": 363
}
,
{
"GEMEINDE": "Dättlikon",
"BEZIRK": "Winterthur",
"STIMMBETEILIGUNG": "   69.91",
"AZ_GÜLTIGE_STIMMZETTEL": 361,
"AZ_JA_STIMMEN": 313
}
,
{
"GEMEINDE": "Dinhard",
"BEZIRK": "Winterthur",
"STIMMBETEILIGUNG": "   62.90",
"AZ_GÜLTIGE_STIMMZETTEL": 653,
"AZ_JA_STIMMEN": 499
}
,
{
"GEMEINDE": "Elgg",
"BEZIRK": "Winterthur",
"STIMMBETEILIGUNG": "   61.10",
"AZ_GÜLTIGE_STIMMZETTEL": 1631,
"AZ_JA_STIMMEN": 1375
}
,
{
"GEMEINDE": "Ellikon a.d.Th.",
"BEZIRK": "Winterthur",
"STIMMBETEILIGUNG": "   62.99",
"AZ_GÜLTIGE_STIMMZETTEL": 376,
"AZ_JA_STIMMEN": 308
}
,
{
"GEMEINDE": "Elsau",
"BEZIRK": "Winterthur",
"STIMMBETEILIGUNG": "   61.10",
"AZ_GÜLTIGE_STIMMZETTEL": 1410,
"AZ_JA_STIMMEN": 1207
}
,
{
"GEMEINDE": "Hagenbuch",
"BEZIRK": "Winterthur",
"STIMMBETEILIGUNG": "   54.39",
"AZ_GÜLTIGE_STIMMZETTEL": 428,
"AZ_JA_STIMMEN": 328
}
,
{
"GEMEINDE": "Hettlingen",
"BEZIRK": "Winterthur",
"STIMMBETEILIGUNG": "   69.02",
"AZ_GÜLTIGE_STIMMZETTEL": 1407,
"AZ_JA_STIMMEN": 1240
}
,
{
"GEMEINDE": "Hofstetten",
"BEZIRK": "Winterthur",
"STIMMBETEILIGUNG": "   60.33",
"AZ_GÜLTIGE_STIMMZETTEL": 209,
"AZ_JA_STIMMEN": 155
}
,
{
"GEMEINDE": "Neftenbach",
"BEZIRK": "Winterthur",
"STIMMBETEILIGUNG": "   62.08",
"AZ_GÜLTIGE_STIMMZETTEL": 2247,
"AZ_JA_STIMMEN": 1940
}
,
{
"GEMEINDE": "Pfungen",
"BEZIRK": "Winterthur",
"STIMMBETEILIGUNG": "   52.72",
"AZ_GÜLTIGE_STIMMZETTEL": 1064,
"AZ_JA_STIMMEN": 916
}
,
{
"GEMEINDE": "Rickenbach",
"BEZIRK": "Winterthur",
"STIMMBETEILIGUNG": "   60.39",
"AZ_GÜLTIGE_STIMMZETTEL": 1034,
"AZ_JA_STIMMEN": 884
}
,
{
"GEMEINDE": "Schlatt",
"BEZIRK": "Winterthur",
"STIMMBETEILIGUNG": "   67.56",
"AZ_GÜLTIGE_STIMMZETTEL": 331,
"AZ_JA_STIMMEN": 278
}
,
{
"GEMEINDE": "Seuzach",
"BEZIRK": "Winterthur",
"STIMMBETEILIGUNG": "   60.79",
"AZ_GÜLTIGE_STIMMZETTEL": 3071,
"AZ_JA_STIMMEN": 2651
}
,
{
"GEMEINDE": "Turbenthal",
"BEZIRK": "Winterthur",
"STIMMBETEILIGUNG": "   52.89",
"AZ_GÜLTIGE_STIMMZETTEL": 1479,
"AZ_JA_STIMMEN": 1228
}
,
{
"GEMEINDE": "Wiesendangen",
"BEZIRK": "Winterthur",
"STIMMBETEILIGUNG": "   64.76",
"AZ_GÜLTIGE_STIMMZETTEL": 2785,
"AZ_JA_STIMMEN": 2391
}
,
{
"GEMEINDE": "Winterthur",
"BEZIRK": "Winterthur",
"STIMMBETEILIGUNG": "   56.33",
"AZ_GÜLTIGE_STIMMZETTEL": 36992,
"AZ_JA_STIMMEN": 32989
}
,
{
"GEMEINDE": "Zell",
"BEZIRK": "Winterthur",
"STIMMBETEILIGUNG": "   51.94",
"AZ_GÜLTIGE_STIMMZETTEL": 1808,
"AZ_JA_STIMMEN": 1595
}
,
{
"GEMEINDE": "Zürich",
"BEZIRK": "Zürich",
"STIMMBETEILIGUNG": "   53.14",
"AZ_GÜLTIGE_STIMMZETTEL": 118236,
"AZ_JA_STIMMEN": 105516
}
]
