[
{
"GEMEINDE": "Aeugst a.A.",
"BEZIRK": "Affoltern",
"STIMMBETEILIGUNG": "   56.02",
"AZ_GÜLTIGE_STIMMZETTEL": 665,
"AZ_JA_STIMMEN": 309
}
,
{
"GEMEINDE": "Affoltern a.A.",
"BEZIRK": "Affoltern",
"STIMMBETEILIGUNG": "   47.11",
"AZ_GÜLTIGE_STIMMZETTEL": 2891,
"AZ_JA_STIMMEN": 1578
}
,
{
"GEMEINDE": "Bonstetten",
"BEZIRK": "Affoltern",
"STIMMBETEILIGUNG": "   55.66",
"AZ_GÜLTIGE_STIMMZETTEL": 1836,
"AZ_JA_STIMMEN": 979
}
,
{
"GEMEINDE": "Hausen a.A.",
"BEZIRK": "Affoltern",
"STIMMBETEILIGUNG": "   50.99",
"AZ_GÜLTIGE_STIMMZETTEL": 1133,
"AZ_JA_STIMMEN": 588
}
,
{
"GEMEINDE": "Hedingen",
"BEZIRK": "Affoltern",
"STIMMBETEILIGUNG": "   54.33",
"AZ_GÜLTIGE_STIMMZETTEL": 1192,
"AZ_JA_STIMMEN": 572
}
,
{
"GEMEINDE": "Kappel a.A.",
"BEZIRK": "Affoltern",
"STIMMBETEILIGUNG": "   53.65",
"AZ_GÜLTIGE_STIMMZETTEL": 325,
"AZ_JA_STIMMEN": 157
}
,
{
"GEMEINDE": "Knonau",
"BEZIRK": "Affoltern",
"STIMMBETEILIGUNG": "   53.55",
"AZ_GÜLTIGE_STIMMZETTEL": 615,
"AZ_JA_STIMMEN": 316
}
,
{
"GEMEINDE": "Maschwanden",
"BEZIRK": "Affoltern",
"STIMMBETEILIGUNG": "   50.00",
"AZ_GÜLTIGE_STIMMZETTEL": 208,
"AZ_JA_STIMMEN": 119
}
,
{
"GEMEINDE": "Mettmenstetten",
"BEZIRK": "Affoltern",
"STIMMBETEILIGUNG": "   52.92",
"AZ_GÜLTIGE_STIMMZETTEL": 1474,
"AZ_JA_STIMMEN": 734
}
,
{
"GEMEINDE": "Obfelden",
"BEZIRK": "Affoltern",
"STIMMBETEILIGUNG": "   47.28",
"AZ_GÜLTIGE_STIMMZETTEL": 1393,
"AZ_JA_STIMMEN": 724
}
,
{
"GEMEINDE": "Ottenbach",
"BEZIRK": "Affoltern",
"STIMMBETEILIGUNG": "   54.94",
"AZ_GÜLTIGE_STIMMZETTEL": 909,
"AZ_JA_STIMMEN": 484
}
,
{
"GEMEINDE": "Rifferswil",
"BEZIRK": "Affoltern",
"STIMMBETEILIGUNG": "   57.61",
"AZ_GÜLTIGE_STIMMZETTEL": 350,
"AZ_JA_STIMMEN": 197
}
,
{
"GEMEINDE": "Stallikon",
"BEZIRK": "Affoltern",
"STIMMBETEILIGUNG": "   60.46",
"AZ_GÜLTIGE_STIMMZETTEL": 1198,
"AZ_JA_STIMMEN": 554
}
,
{
"GEMEINDE": "Wettswil a.A.",
"BEZIRK": "Affoltern",
"STIMMBETEILIGUNG": "   54.81",
"AZ_GÜLTIGE_STIMMZETTEL": 1659,
"AZ_JA_STIMMEN": 735
}
,
{
"GEMEINDE": "Adlikon",
"BEZIRK": "Andelfingen",
"STIMMBETEILIGUNG": "   61.45",
"AZ_GÜLTIGE_STIMMZETTEL": 277,
"AZ_JA_STIMMEN": 124
}
,
{
"GEMEINDE": "Andelfingen",
"BEZIRK": "Andelfingen",
"STIMMBETEILIGUNG": "   63.55",
"AZ_GÜLTIGE_STIMMZETTEL": 763,
"AZ_JA_STIMMEN": 344
}
,
{
"GEMEINDE": "Benken",
"BEZIRK": "Andelfingen",
"STIMMBETEILIGUNG": "   58.95",
"AZ_GÜLTIGE_STIMMZETTEL": 314,
"AZ_JA_STIMMEN": 165
}
,
{
"GEMEINDE": "Berg a.I.",
"BEZIRK": "Andelfingen",
"STIMMBETEILIGUNG": "   57.11",
"AZ_GÜLTIGE_STIMMZETTEL": 260,
"AZ_JA_STIMMEN": 124
}
,
{
"GEMEINDE": "Buch a.I.",
"BEZIRK": "Andelfingen",
"STIMMBETEILIGUNG": "   52.79",
"AZ_GÜLTIGE_STIMMZETTEL": 319,
"AZ_JA_STIMMEN": 163
}
,
{
"GEMEINDE": "Dachsen",
"BEZIRK": "Andelfingen",
"STIMMBETEILIGUNG": "   54.81",
"AZ_GÜLTIGE_STIMMZETTEL": 667,
"AZ_JA_STIMMEN": 407
}
,
{
"GEMEINDE": "Dorf",
"BEZIRK": "Andelfingen",
"STIMMBETEILIGUNG": "   57.60",
"AZ_GÜLTIGE_STIMMZETTEL": 246,
"AZ_JA_STIMMEN": 110
}
,
{
"GEMEINDE": "Feuerthalen",
"BEZIRK": "Andelfingen",
"STIMMBETEILIGUNG": "   48.58",
"AZ_GÜLTIGE_STIMMZETTEL": 1014,
"AZ_JA_STIMMEN": 555
}
,
{
"GEMEINDE": "Flaach",
"BEZIRK": "Andelfingen",
"STIMMBETEILIGUNG": "   55.86",
"AZ_GÜLTIGE_STIMMZETTEL": 458,
"AZ_JA_STIMMEN": 202
}
,
{
"GEMEINDE": "Flurlingen",
"BEZIRK": "Andelfingen",
"STIMMBETEILIGUNG": "   56.56",
"AZ_GÜLTIGE_STIMMZETTEL": 516,
"AZ_JA_STIMMEN": 242
}
,
{
"GEMEINDE": "Henggart",
"BEZIRK": "Andelfingen",
"STIMMBETEILIGUNG": "   57.64",
"AZ_GÜLTIGE_STIMMZETTEL": 808,
"AZ_JA_STIMMEN": 400
}
,
{
"GEMEINDE": "Humlikon",
"BEZIRK": "Andelfingen",
"STIMMBETEILIGUNG": "   57.99",
"AZ_GÜLTIGE_STIMMZETTEL": 180,
"AZ_JA_STIMMEN": 84
}
,
{
"GEMEINDE": "Kleinandelfingen",
"BEZIRK": "Andelfingen",
"STIMMBETEILIGUNG": "   55.94",
"AZ_GÜLTIGE_STIMMZETTEL": 787,
"AZ_JA_STIMMEN": 416
}
,
{
"GEMEINDE": "Laufen-Uhwiesen",
"BEZIRK": "Andelfingen",
"STIMMBETEILIGUNG": "   54.65",
"AZ_GÜLTIGE_STIMMZETTEL": 583,
"AZ_JA_STIMMEN": 305
}
,
{
"GEMEINDE": "Marthalen",
"BEZIRK": "Andelfingen",
"STIMMBETEILIGUNG": "   56.30",
"AZ_GÜLTIGE_STIMMZETTEL": 758,
"AZ_JA_STIMMEN": 348
}
,
{
"GEMEINDE": "Oberstammheim",
"BEZIRK": "Andelfingen",
"STIMMBETEILIGUNG": "   57.63",
"AZ_GÜLTIGE_STIMMZETTEL": 433,
"AZ_JA_STIMMEN": 220
}
,
{
"GEMEINDE": "Ossingen",
"BEZIRK": "Andelfingen",
"STIMMBETEILIGUNG": "   56.26",
"AZ_GÜLTIGE_STIMMZETTEL": 551,
"AZ_JA_STIMMEN": 274
}
,
{
"GEMEINDE": "Rheinau",
"BEZIRK": "Andelfingen",
"STIMMBETEILIGUNG": "   57.81",
"AZ_GÜLTIGE_STIMMZETTEL": 473,
"AZ_JA_STIMMEN": 266
}
,
{
"GEMEINDE": "Thalheim a.d.Th.",
"BEZIRK": "Andelfingen",
"STIMMBETEILIGUNG": "   49.47",
"AZ_GÜLTIGE_STIMMZETTEL": 266,
"AZ_JA_STIMMEN": 121
}
,
{
"GEMEINDE": "Trüllikon",
"BEZIRK": "Andelfingen",
"STIMMBETEILIGUNG": "   50.91",
"AZ_GÜLTIGE_STIMMZETTEL": 387,
"AZ_JA_STIMMEN": 198
}
,
{
"GEMEINDE": "Truttikon",
"BEZIRK": "Andelfingen",
"STIMMBETEILIGUNG": "   67.07",
"AZ_GÜLTIGE_STIMMZETTEL": 216,
"AZ_JA_STIMMEN": 101
}
,
{
"GEMEINDE": "Unterstammheim",
"BEZIRK": "Andelfingen",
"STIMMBETEILIGUNG": "   60.10",
"AZ_GÜLTIGE_STIMMZETTEL": 365,
"AZ_JA_STIMMEN": 191
}
,
{
"GEMEINDE": "Volken",
"BEZIRK": "Andelfingen",
"STIMMBETEILIGUNG": "   57.28",
"AZ_GÜLTIGE_STIMMZETTEL": 115,
"AZ_JA_STIMMEN": 57
}
,
{
"GEMEINDE": "Waltalingen",
"BEZIRK": "Andelfingen",
"STIMMBETEILIGUNG": "   57.41",
"AZ_GÜLTIGE_STIMMZETTEL": 269,
"AZ_JA_STIMMEN": 135
}
,
{
"GEMEINDE": "Bachenbülach",
"BEZIRK": "Bülach",
"STIMMBETEILIGUNG": "   49.16",
"AZ_GÜLTIGE_STIMMZETTEL": 1106,
"AZ_JA_STIMMEN": 550
}
,
{
"GEMEINDE": "Bassersdorf",
"BEZIRK": "Bülach",
"STIMMBETEILIGUNG": "   46.80",
"AZ_GÜLTIGE_STIMMZETTEL": 3059,
"AZ_JA_STIMMEN": 1562
}
,
{
"GEMEINDE": "Bülach",
"BEZIRK": "Bülach",
"STIMMBETEILIGUNG": "   46.61",
"AZ_GÜLTIGE_STIMMZETTEL": 4736,
"AZ_JA_STIMMEN": 2567
}
,
{
"GEMEINDE": "Dietlikon",
"BEZIRK": "Bülach",
"STIMMBETEILIGUNG": "   54.66",
"AZ_GÜLTIGE_STIMMZETTEL": 2383,
"AZ_JA_STIMMEN": 1231
}
,
{
"GEMEINDE": "Eglisau",
"BEZIRK": "Bülach",
"STIMMBETEILIGUNG": "   68.14",
"AZ_GÜLTIGE_STIMMZETTEL": 1580,
"AZ_JA_STIMMEN": 797
}
,
{
"GEMEINDE": "Embrach",
"BEZIRK": "Bülach",
"STIMMBETEILIGUNG": "   46.18",
"AZ_GÜLTIGE_STIMMZETTEL": 2416,
"AZ_JA_STIMMEN": 1169
}
,
{
"GEMEINDE": "Freienstein-Teufen",
"BEZIRK": "Bülach",
"STIMMBETEILIGUNG": "   54.21",
"AZ_GÜLTIGE_STIMMZETTEL": 819,
"AZ_JA_STIMMEN": 432
}
,
{
"GEMEINDE": "Glattfelden",
"BEZIRK": "Bülach",
"STIMMBETEILIGUNG": "   46.78",
"AZ_GÜLTIGE_STIMMZETTEL": 1185,
"AZ_JA_STIMMEN": 612
}
,
{
"GEMEINDE": "Hochfelden",
"BEZIRK": "Bülach",
"STIMMBETEILIGUNG": "   52.28",
"AZ_GÜLTIGE_STIMMZETTEL": 630,
"AZ_JA_STIMMEN": 309
}
,
{
"GEMEINDE": "Höri",
"BEZIRK": "Bülach",
"STIMMBETEILIGUNG": "   43.86",
"AZ_GÜLTIGE_STIMMZETTEL": 579,
"AZ_JA_STIMMEN": 290
}
,
{
"GEMEINDE": "Hüntwangen",
"BEZIRK": "Bülach",
"STIMMBETEILIGUNG": "   53.61",
"AZ_GÜLTIGE_STIMMZETTEL": 362,
"AZ_JA_STIMMEN": 164
}
,
{
"GEMEINDE": "Kloten",
"BEZIRK": "Bülach",
"STIMMBETEILIGUNG": "   44.63",
"AZ_GÜLTIGE_STIMMZETTEL": 4534,
"AZ_JA_STIMMEN": 2293
}
,
{
"GEMEINDE": "Lufingen",
"BEZIRK": "Bülach",
"STIMMBETEILIGUNG": "   53.45",
"AZ_GÜLTIGE_STIMMZETTEL": 559,
"AZ_JA_STIMMEN": 233
}
,
{
"GEMEINDE": "Nürensdorf",
"BEZIRK": "Bülach",
"STIMMBETEILIGUNG": "   57.88",
"AZ_GÜLTIGE_STIMMZETTEL": 2025,
"AZ_JA_STIMMEN": 904
}
,
{
"GEMEINDE": "Oberembrach",
"BEZIRK": "Bülach",
"STIMMBETEILIGUNG": "   56.18",
"AZ_GÜLTIGE_STIMMZETTEL": 405,
"AZ_JA_STIMMEN": 166
}
,
{
"GEMEINDE": "Opfikon",
"BEZIRK": "Bülach",
"STIMMBETEILIGUNG": "   40.89",
"AZ_GÜLTIGE_STIMMZETTEL": 2902,
"AZ_JA_STIMMEN": 1444
}
,
{
"GEMEINDE": "Rafz",
"BEZIRK": "Bülach",
"STIMMBETEILIGUNG": "   54.58",
"AZ_GÜLTIGE_STIMMZETTEL": 1377,
"AZ_JA_STIMMEN": 749
}
,
{
"GEMEINDE": "Rorbas",
"BEZIRK": "Bülach",
"STIMMBETEILIGUNG": "   43.37",
"AZ_GÜLTIGE_STIMMZETTEL": 585,
"AZ_JA_STIMMEN": 298
}
,
{
"GEMEINDE": "Wallisellen",
"BEZIRK": "Bülach",
"STIMMBETEILIGUNG": "   51.73",
"AZ_GÜLTIGE_STIMMZETTEL": 3967,
"AZ_JA_STIMMEN": 2146
}
,
{
"GEMEINDE": "Wasterkingen",
"BEZIRK": "Bülach",
"STIMMBETEILIGUNG": "   59.12",
"AZ_GÜLTIGE_STIMMZETTEL": 237,
"AZ_JA_STIMMEN": 137
}
,
{
"GEMEINDE": "Wil",
"BEZIRK": "Bülach",
"STIMMBETEILIGUNG": "   61.92",
"AZ_GÜLTIGE_STIMMZETTEL": 563,
"AZ_JA_STIMMEN": 295
}
,
{
"GEMEINDE": "Winkel",
"BEZIRK": "Bülach",
"STIMMBETEILIGUNG": "   55.89",
"AZ_GÜLTIGE_STIMMZETTEL": 1523,
"AZ_JA_STIMMEN": 625
}
,
{
"GEMEINDE": "Bachs",
"BEZIRK": "Dielsdorf",
"STIMMBETEILIGUNG": "   48.61",
"AZ_GÜLTIGE_STIMMZETTEL": 208,
"AZ_JA_STIMMEN": 92
}
,
{
"GEMEINDE": "Boppelsen",
"BEZIRK": "Dielsdorf",
"STIMMBETEILIGUNG": "   57.72",
"AZ_GÜLTIGE_STIMMZETTEL": 488,
"AZ_JA_STIMMEN": 231
}
,
{
"GEMEINDE": "Buchs",
"BEZIRK": "Dielsdorf",
"STIMMBETEILIGUNG": "   43.53",
"AZ_GÜLTIGE_STIMMZETTEL": 1393,
"AZ_JA_STIMMEN": 665
}
,
{
"GEMEINDE": "Dällikon",
"BEZIRK": "Dielsdorf",
"STIMMBETEILIGUNG": "   43.97",
"AZ_GÜLTIGE_STIMMZETTEL": 930,
"AZ_JA_STIMMEN": 486
}
,
{
"GEMEINDE": "Dänikon",
"BEZIRK": "Dielsdorf",
"STIMMBETEILIGUNG": "   48.71",
"AZ_GÜLTIGE_STIMMZETTEL": 511,
"AZ_JA_STIMMEN": 245
}
,
{
"GEMEINDE": "Dielsdorf",
"BEZIRK": "Dielsdorf",
"STIMMBETEILIGUNG": "   44.03",
"AZ_GÜLTIGE_STIMMZETTEL": 1428,
"AZ_JA_STIMMEN": 715
}
,
{
"GEMEINDE": "Hüttikon",
"BEZIRK": "Dielsdorf",
"STIMMBETEILIGUNG": "   47.96",
"AZ_GÜLTIGE_STIMMZETTEL": 218,
"AZ_JA_STIMMEN": 103
}
,
{
"GEMEINDE": "Neerach",
"BEZIRK": "Dielsdorf",
"STIMMBETEILIGUNG": "   52.14",
"AZ_GÜLTIGE_STIMMZETTEL": 1111,
"AZ_JA_STIMMEN": 445
}
,
{
"GEMEINDE": "Niederglatt",
"BEZIRK": "Dielsdorf",
"STIMMBETEILIGUNG": "   41.22",
"AZ_GÜLTIGE_STIMMZETTEL": 1114,
"AZ_JA_STIMMEN": 558
}
,
{
"GEMEINDE": "Niederhasli",
"BEZIRK": "Dielsdorf",
"STIMMBETEILIGUNG": "   48.39",
"AZ_GÜLTIGE_STIMMZETTEL": 2357,
"AZ_JA_STIMMEN": 1240
}
,
{
"GEMEINDE": "Niederweningen",
"BEZIRK": "Dielsdorf",
"STIMMBETEILIGUNG": "   52.22",
"AZ_GÜLTIGE_STIMMZETTEL": 880,
"AZ_JA_STIMMEN": 419
}
,
{
"GEMEINDE": "Oberglatt",
"BEZIRK": "Dielsdorf",
"STIMMBETEILIGUNG": "   37.97",
"AZ_GÜLTIGE_STIMMZETTEL": 1081,
"AZ_JA_STIMMEN": 579
}
,
{
"GEMEINDE": "Oberweningen",
"BEZIRK": "Dielsdorf",
"STIMMBETEILIGUNG": "   48.02",
"AZ_GÜLTIGE_STIMMZETTEL": 503,
"AZ_JA_STIMMEN": 265
}
,
{
"GEMEINDE": "Otelfingen",
"BEZIRK": "Dielsdorf",
"STIMMBETEILIGUNG": "   50.76",
"AZ_GÜLTIGE_STIMMZETTEL": 762,
"AZ_JA_STIMMEN": 409
}
,
{
"GEMEINDE": "Regensberg",
"BEZIRK": "Dielsdorf",
"STIMMBETEILIGUNG": "   58.25",
"AZ_GÜLTIGE_STIMMZETTEL": 179,
"AZ_JA_STIMMEN": 81
}
,
{
"GEMEINDE": "Regensdorf",
"BEZIRK": "Dielsdorf",
"STIMMBETEILIGUNG": "   43.99",
"AZ_GÜLTIGE_STIMMZETTEL": 3797,
"AZ_JA_STIMMEN": 1932
}
,
{
"GEMEINDE": "Rümlang",
"BEZIRK": "Dielsdorf",
"STIMMBETEILIGUNG": "   45.25",
"AZ_GÜLTIGE_STIMMZETTEL": 1697,
"AZ_JA_STIMMEN": 956
}
,
{
"GEMEINDE": "Schleinikon",
"BEZIRK": "Dielsdorf",
"STIMMBETEILIGUNG": "   50.40",
"AZ_GÜLTIGE_STIMMZETTEL": 244,
"AZ_JA_STIMMEN": 131
}
,
{
"GEMEINDE": "Schöfflisdorf",
"BEZIRK": "Dielsdorf",
"STIMMBETEILIGUNG": "   56.19",
"AZ_GÜLTIGE_STIMMZETTEL": 491,
"AZ_JA_STIMMEN": 228
}
,
{
"GEMEINDE": "Stadel",
"BEZIRK": "Dielsdorf",
"STIMMBETEILIGUNG": "   45.76",
"AZ_GÜLTIGE_STIMMZETTEL": 614,
"AZ_JA_STIMMEN": 302
}
,
{
"GEMEINDE": "Steinmaur",
"BEZIRK": "Dielsdorf",
"STIMMBETEILIGUNG": "   48.47",
"AZ_GÜLTIGE_STIMMZETTEL": 992,
"AZ_JA_STIMMEN": 434
}
,
{
"GEMEINDE": "Weiach",
"BEZIRK": "Dielsdorf",
"STIMMBETEILIGUNG": "   46.91",
"AZ_GÜLTIGE_STIMMZETTEL": 331,
"AZ_JA_STIMMEN": 179
}
,
{
"GEMEINDE": "Aesch",
"BEZIRK": "Dietikon",
"STIMMBETEILIGUNG": "   62.09",
"AZ_GÜLTIGE_STIMMZETTEL": 437,
"AZ_JA_STIMMEN": 174
}
,
{
"GEMEINDE": "Birmensdorf",
"BEZIRK": "Dietikon",
"STIMMBETEILIGUNG": "   53.66",
"AZ_GÜLTIGE_STIMMZETTEL": 2006,
"AZ_JA_STIMMEN": 929
}
,
{
"GEMEINDE": "Dietikon",
"BEZIRK": "Dietikon",
"STIMMBETEILIGUNG": "   42.22",
"AZ_GÜLTIGE_STIMMZETTEL": 4707,
"AZ_JA_STIMMEN": 2525
}
,
{
"GEMEINDE": "Geroldswil",
"BEZIRK": "Dietikon",
"STIMMBETEILIGUNG": "   46.34",
"AZ_GÜLTIGE_STIMMZETTEL": 1360,
"AZ_JA_STIMMEN": 619
}
,
{
"GEMEINDE": "Oberengstringen",
"BEZIRK": "Dietikon",
"STIMMBETEILIGUNG": "   48.65",
"AZ_GÜLTIGE_STIMMZETTEL": 1823,
"AZ_JA_STIMMEN": 922
}
,
{
"GEMEINDE": "Oetwil a.d.L",
"BEZIRK": "Dietikon",
"STIMMBETEILIGUNG": "   52.21",
"AZ_GÜLTIGE_STIMMZETTEL": 832,
"AZ_JA_STIMMEN": 343
}
,
{
"GEMEINDE": "Schlieren",
"BEZIRK": "Dietikon",
"STIMMBETEILIGUNG": "   42.63",
"AZ_GÜLTIGE_STIMMZETTEL": 2804,
"AZ_JA_STIMMEN": 1524
}
,
{
"GEMEINDE": "Uitikon",
"BEZIRK": "Dietikon",
"STIMMBETEILIGUNG": "   65.06",
"AZ_GÜLTIGE_STIMMZETTEL": 1753,
"AZ_JA_STIMMEN": 637
}
,
{
"GEMEINDE": "Unterengstringen",
"BEZIRK": "Dietikon",
"STIMMBETEILIGUNG": "   55.16",
"AZ_GÜLTIGE_STIMMZETTEL": 1128,
"AZ_JA_STIMMEN": 486
}
,
{
"GEMEINDE": "Urdorf",
"BEZIRK": "Dietikon",
"STIMMBETEILIGUNG": "   49.38",
"AZ_GÜLTIGE_STIMMZETTEL": 2879,
"AZ_JA_STIMMEN": 1485
}
,
{
"GEMEINDE": "Weiningen",
"BEZIRK": "Dietikon",
"STIMMBETEILIGUNG": "   47.66",
"AZ_GÜLTIGE_STIMMZETTEL": 1175,
"AZ_JA_STIMMEN": 513
}
,
{
"GEMEINDE": "Bäretswil",
"BEZIRK": "Hinwil",
"STIMMBETEILIGUNG": "   50.36",
"AZ_GÜLTIGE_STIMMZETTEL": 1582,
"AZ_JA_STIMMEN": 828
}
,
{
"GEMEINDE": "Bubikon",
"BEZIRK": "Hinwil",
"STIMMBETEILIGUNG": "   52.78",
"AZ_GÜLTIGE_STIMMZETTEL": 2308,
"AZ_JA_STIMMEN": 1215
}
,
{
"GEMEINDE": "Dürnten",
"BEZIRK": "Hinwil",
"STIMMBETEILIGUNG": "   49.48",
"AZ_GÜLTIGE_STIMMZETTEL": 2034,
"AZ_JA_STIMMEN": 1045
}
,
{
"GEMEINDE": "Fischenthal",
"BEZIRK": "Hinwil",
"STIMMBETEILIGUNG": "   50.63",
"AZ_GÜLTIGE_STIMMZETTEL": 749,
"AZ_JA_STIMMEN": 422
}
,
{
"GEMEINDE": "Gossau",
"BEZIRK": "Hinwil",
"STIMMBETEILIGUNG": "   49.72",
"AZ_GÜLTIGE_STIMMZETTEL": 3179,
"AZ_JA_STIMMEN": 1664
}
,
{
"GEMEINDE": "Grüningen",
"BEZIRK": "Hinwil",
"STIMMBETEILIGUNG": "   55.86",
"AZ_GÜLTIGE_STIMMZETTEL": 1141,
"AZ_JA_STIMMEN": 580
}
,
{
"GEMEINDE": "Hinwil",
"BEZIRK": "Hinwil",
"STIMMBETEILIGUNG": "   50.15",
"AZ_GÜLTIGE_STIMMZETTEL": 3370,
"AZ_JA_STIMMEN": 1824
}
,
{
"GEMEINDE": "Rüti",
"BEZIRK": "Hinwil",
"STIMMBETEILIGUNG": "   46.63",
"AZ_GÜLTIGE_STIMMZETTEL": 3389,
"AZ_JA_STIMMEN": 1879
}
,
{
"GEMEINDE": "Seegräben",
"BEZIRK": "Hinwil",
"STIMMBETEILIGUNG": "   54.24",
"AZ_GÜLTIGE_STIMMZETTEL": 459,
"AZ_JA_STIMMEN": 240
}
,
{
"GEMEINDE": "Wald",
"BEZIRK": "Hinwil",
"STIMMBETEILIGUNG": "   48.57",
"AZ_GÜLTIGE_STIMMZETTEL": 2615,
"AZ_JA_STIMMEN": 1423
}
,
{
"GEMEINDE": "Wetzikon",
"BEZIRK": "Hinwil",
"STIMMBETEILIGUNG": "   45.19",
"AZ_GÜLTIGE_STIMMZETTEL": 5920,
"AZ_JA_STIMMEN": 3274
}
,
{
"GEMEINDE": "Adliswil",
"BEZIRK": "Horgen",
"STIMMBETEILIGUNG": "   50.63",
"AZ_GÜLTIGE_STIMMZETTEL": 4782,
"AZ_JA_STIMMEN": 2448
}
,
{
"GEMEINDE": "Hirzel",
"BEZIRK": "Horgen",
"STIMMBETEILIGUNG": "   50.99",
"AZ_GÜLTIGE_STIMMZETTEL": 711,
"AZ_JA_STIMMEN": 338
}
,
{
"GEMEINDE": "Horgen",
"BEZIRK": "Horgen",
"STIMMBETEILIGUNG": "   51.66",
"AZ_GÜLTIGE_STIMMZETTEL": 5518,
"AZ_JA_STIMMEN": 2909
}
,
{
"GEMEINDE": "Hütten",
"BEZIRK": "Horgen",
"STIMMBETEILIGUNG": "   52.22",
"AZ_GÜLTIGE_STIMMZETTEL": 326,
"AZ_JA_STIMMEN": 137
}
,
{
"GEMEINDE": "Kilchberg",
"BEZIRK": "Horgen",
"STIMMBETEILIGUNG": "   60.38",
"AZ_GÜLTIGE_STIMMZETTEL": 2805,
"AZ_JA_STIMMEN": 1158
}
,
{
"GEMEINDE": "Langnau a.A.",
"BEZIRK": "Horgen",
"STIMMBETEILIGUNG": "   52.16",
"AZ_GÜLTIGE_STIMMZETTEL": 2300,
"AZ_JA_STIMMEN": 1141
}
,
{
"GEMEINDE": "Oberrieden",
"BEZIRK": "Horgen",
"STIMMBETEILIGUNG": "   60.63",
"AZ_GÜLTIGE_STIMMZETTEL": 2044,
"AZ_JA_STIMMEN": 927
}
,
{
"GEMEINDE": "Richterswil",
"BEZIRK": "Horgen",
"STIMMBETEILIGUNG": "   52.85",
"AZ_GÜLTIGE_STIMMZETTEL": 3959,
"AZ_JA_STIMMEN": 2050
}
,
{
"GEMEINDE": "Rüschlikon",
"BEZIRK": "Horgen",
"STIMMBETEILIGUNG": "   57.62",
"AZ_GÜLTIGE_STIMMZETTEL": 1833,
"AZ_JA_STIMMEN": 802
}
,
{
"GEMEINDE": "Schönenberg",
"BEZIRK": "Horgen",
"STIMMBETEILIGUNG": "   55.52",
"AZ_GÜLTIGE_STIMMZETTEL": 757,
"AZ_JA_STIMMEN": 361
}
,
{
"GEMEINDE": "Thalwil",
"BEZIRK": "Horgen",
"STIMMBETEILIGUNG": "   54.11",
"AZ_GÜLTIGE_STIMMZETTEL": 5685,
"AZ_JA_STIMMEN": 2866
}
,
{
"GEMEINDE": "Wädenswil",
"BEZIRK": "Horgen",
"STIMMBETEILIGUNG": "   53.16",
"AZ_GÜLTIGE_STIMMZETTEL": 6693,
"AZ_JA_STIMMEN": 3504
}
,
{
"GEMEINDE": "Erlenbach",
"BEZIRK": "Meilen",
"STIMMBETEILIGUNG": "   59.34",
"AZ_GÜLTIGE_STIMMZETTEL": 1939,
"AZ_JA_STIMMEN": 822
}
,
{
"GEMEINDE": "Herrliberg",
"BEZIRK": "Meilen",
"STIMMBETEILIGUNG": "   63.10",
"AZ_GÜLTIGE_STIMMZETTEL": 2475,
"AZ_JA_STIMMEN": 1032
}
,
{
"GEMEINDE": "Hombrechtikon",
"BEZIRK": "Meilen",
"STIMMBETEILIGUNG": "   49.90",
"AZ_GÜLTIGE_STIMMZETTEL": 2533,
"AZ_JA_STIMMEN": 1402
}
,
{
"GEMEINDE": "Küsnacht",
"BEZIRK": "Meilen",
"STIMMBETEILIGUNG": "   56.92",
"AZ_GÜLTIGE_STIMMZETTEL": 4814,
"AZ_JA_STIMMEN": 2093
}
,
{
"GEMEINDE": "Männedorf",
"BEZIRK": "Meilen",
"STIMMBETEILIGUNG": "   57.12",
"AZ_GÜLTIGE_STIMMZETTEL": 3659,
"AZ_JA_STIMMEN": 1882
}
,
{
"GEMEINDE": "Meilen",
"BEZIRK": "Meilen",
"STIMMBETEILIGUNG": "   60.23",
"AZ_GÜLTIGE_STIMMZETTEL": 4809,
"AZ_JA_STIMMEN": 2394
}
,
{
"GEMEINDE": "Oetwil a.S.",
"BEZIRK": "Meilen",
"STIMMBETEILIGUNG": "   43.03",
"AZ_GÜLTIGE_STIMMZETTEL": 1072,
"AZ_JA_STIMMEN": 563
}
,
{
"GEMEINDE": "Stäfa",
"BEZIRK": "Meilen",
"STIMMBETEILIGUNG": "   57.25",
"AZ_GÜLTIGE_STIMMZETTEL": 5171,
"AZ_JA_STIMMEN": 2407
}
,
{
"GEMEINDE": "Uetikon a.S.",
"BEZIRK": "Meilen",
"STIMMBETEILIGUNG": "   54.71",
"AZ_GÜLTIGE_STIMMZETTEL": 1961,
"AZ_JA_STIMMEN": 1025
}
,
{
"GEMEINDE": "Zollikon",
"BEZIRK": "Meilen",
"STIMMBETEILIGUNG": "   59.39",
"AZ_GÜLTIGE_STIMMZETTEL": 4761,
"AZ_JA_STIMMEN": 2031
}
,
{
"GEMEINDE": "Zumikon",
"BEZIRK": "Meilen",
"STIMMBETEILIGUNG": "   62.08",
"AZ_GÜLTIGE_STIMMZETTEL": 1980,
"AZ_JA_STIMMEN": 791
}
,
{
"GEMEINDE": "Bauma",
"BEZIRK": "Pfäffikon",
"STIMMBETEILIGUNG": "   57.53",
"AZ_GÜLTIGE_STIMMZETTEL": 1681,
"AZ_JA_STIMMEN": 897
}
,
{
"GEMEINDE": "Fehraltorf",
"BEZIRK": "Pfäffikon",
"STIMMBETEILIGUNG": "   51.70",
"AZ_GÜLTIGE_STIMMZETTEL": 1799,
"AZ_JA_STIMMEN": 920
}
,
{
"GEMEINDE": "Hittnau",
"BEZIRK": "Pfäffikon",
"STIMMBETEILIGUNG": "   53.54",
"AZ_GÜLTIGE_STIMMZETTEL": 1246,
"AZ_JA_STIMMEN": 661
}
,
{
"GEMEINDE": "Illnau-Effretikon",
"BEZIRK": "Pfäffikon",
"STIMMBETEILIGUNG": "   50.70",
"AZ_GÜLTIGE_STIMMZETTEL": 5079,
"AZ_JA_STIMMEN": 2858
}
,
{
"GEMEINDE": "Lindau",
"BEZIRK": "Pfäffikon",
"STIMMBETEILIGUNG": "   53.26",
"AZ_GÜLTIGE_STIMMZETTEL": 1578,
"AZ_JA_STIMMEN": 749
}
,
{
"GEMEINDE": "Pfäffikon",
"BEZIRK": "Pfäffikon",
"STIMMBETEILIGUNG": "   52.76",
"AZ_GÜLTIGE_STIMMZETTEL": 3565,
"AZ_JA_STIMMEN": 1943
}
,
{
"GEMEINDE": "Russikon",
"BEZIRK": "Pfäffikon",
"STIMMBETEILIGUNG": "   56.91",
"AZ_GÜLTIGE_STIMMZETTEL": 1589,
"AZ_JA_STIMMEN": 741
}
,
{
"GEMEINDE": "Weisslingen",
"BEZIRK": "Pfäffikon",
"STIMMBETEILIGUNG": "   55.29",
"AZ_GÜLTIGE_STIMMZETTEL": 1226,
"AZ_JA_STIMMEN": 562
}
,
{
"GEMEINDE": "Wila",
"BEZIRK": "Pfäffikon",
"STIMMBETEILIGUNG": "   50.37",
"AZ_GÜLTIGE_STIMMZETTEL": 661,
"AZ_JA_STIMMEN": 367
}
,
{
"GEMEINDE": "Wildberg",
"BEZIRK": "Pfäffikon",
"STIMMBETEILIGUNG": "   59.97",
"AZ_GÜLTIGE_STIMMZETTEL": 409,
"AZ_JA_STIMMEN": 178
}
,
{
"GEMEINDE": "Dübendorf",
"BEZIRK": "Uster",
"STIMMBETEILIGUNG": "   46.17",
"AZ_GÜLTIGE_STIMMZETTEL": 6335,
"AZ_JA_STIMMEN": 3378
}
,
{
"GEMEINDE": "Egg",
"BEZIRK": "Uster",
"STIMMBETEILIGUNG": "   55.55",
"AZ_GÜLTIGE_STIMMZETTEL": 2832,
"AZ_JA_STIMMEN": 1391
}
,
{
"GEMEINDE": "Fällanden",
"BEZIRK": "Uster",
"STIMMBETEILIGUNG": "   49.87",
"AZ_GÜLTIGE_STIMMZETTEL": 2453,
"AZ_JA_STIMMEN": 1153
}
,
{
"GEMEINDE": "Greifensee",
"BEZIRK": "Uster",
"STIMMBETEILIGUNG": "   54.38",
"AZ_GÜLTIGE_STIMMZETTEL": 1760,
"AZ_JA_STIMMEN": 918
}
,
{
"GEMEINDE": "Maur",
"BEZIRK": "Uster",
"STIMMBETEILIGUNG": "   57.00",
"AZ_GÜLTIGE_STIMMZETTEL": 3434,
"AZ_JA_STIMMEN": 1511
}
,
{
"GEMEINDE": "Mönchaltorf",
"BEZIRK": "Uster",
"STIMMBETEILIGUNG": "   54.80",
"AZ_GÜLTIGE_STIMMZETTEL": 1301,
"AZ_JA_STIMMEN": 729
}
,
{
"GEMEINDE": "Schwerzenbach",
"BEZIRK": "Uster",
"STIMMBETEILIGUNG": "   48.61",
"AZ_GÜLTIGE_STIMMZETTEL": 1356,
"AZ_JA_STIMMEN": 697
}
,
{
"GEMEINDE": "Uster",
"BEZIRK": "Uster",
"STIMMBETEILIGUNG": "   55.35",
"AZ_GÜLTIGE_STIMMZETTEL": 10579,
"AZ_JA_STIMMEN": 5888
}
,
{
"GEMEINDE": "Volketswil",
"BEZIRK": "Uster",
"STIMMBETEILIGUNG": "   45.17",
"AZ_GÜLTIGE_STIMMZETTEL": 4503,
"AZ_JA_STIMMEN": 2156
}
,
{
"GEMEINDE": "Wangen-Brüttisellen",
"BEZIRK": "Uster",
"STIMMBETEILIGUNG": "   45.13",
"AZ_GÜLTIGE_STIMMZETTEL": 1914,
"AZ_JA_STIMMEN": 962
}
,
{
"GEMEINDE": "Altikon",
"BEZIRK": "Winterthur",
"STIMMBETEILIGUNG": "   50.96",
"AZ_GÜLTIGE_STIMMZETTEL": 238,
"AZ_JA_STIMMEN": 118
}
,
{
"GEMEINDE": "Brütten",
"BEZIRK": "Winterthur",
"STIMMBETEILIGUNG": "   60.61",
"AZ_GÜLTIGE_STIMMZETTEL": 828,
"AZ_JA_STIMMEN": 388
}
,
{
"GEMEINDE": "Dägerlen",
"BEZIRK": "Winterthur",
"STIMMBETEILIGUNG": "   52.67",
"AZ_GÜLTIGE_STIMMZETTEL": 350,
"AZ_JA_STIMMEN": 190
}
,
{
"GEMEINDE": "Dättlikon",
"BEZIRK": "Winterthur",
"STIMMBETEILIGUNG": "   53.55",
"AZ_GÜLTIGE_STIMMZETTEL": 249,
"AZ_JA_STIMMEN": 124
}
,
{
"GEMEINDE": "Dinhard",
"BEZIRK": "Winterthur",
"STIMMBETEILIGUNG": "   56.58",
"AZ_GÜLTIGE_STIMMZETTEL": 580,
"AZ_JA_STIMMEN": 319
}
,
{
"GEMEINDE": "Elgg",
"BEZIRK": "Winterthur",
"STIMMBETEILIGUNG": "   53.76",
"AZ_GÜLTIGE_STIMMZETTEL": 1367,
"AZ_JA_STIMMEN": 740
}
,
{
"GEMEINDE": "Ellikon a.d.Th.",
"BEZIRK": "Winterthur",
"STIMMBETEILIGUNG": "   49.49",
"AZ_GÜLTIGE_STIMMZETTEL": 289,
"AZ_JA_STIMMEN": 147
}
,
{
"GEMEINDE": "Elsau",
"BEZIRK": "Winterthur",
"STIMMBETEILIGUNG": "   52.31",
"AZ_GÜLTIGE_STIMMZETTEL": 1179,
"AZ_JA_STIMMEN": 582
}
,
{
"GEMEINDE": "Hagenbuch",
"BEZIRK": "Winterthur",
"STIMMBETEILIGUNG": "   47.61",
"AZ_GÜLTIGE_STIMMZETTEL": 373,
"AZ_JA_STIMMEN": 176
}
,
{
"GEMEINDE": "Hettlingen",
"BEZIRK": "Winterthur",
"STIMMBETEILIGUNG": "   55.99",
"AZ_GÜLTIGE_STIMMZETTEL": 1084,
"AZ_JA_STIMMEN": 534
}
,
{
"GEMEINDE": "Hofstetten",
"BEZIRK": "Winterthur",
"STIMMBETEILIGUNG": "   50.99",
"AZ_GÜLTIGE_STIMMZETTEL": 148,
"AZ_JA_STIMMEN": 68
}
,
{
"GEMEINDE": "Neftenbach",
"BEZIRK": "Winterthur",
"STIMMBETEILIGUNG": "   49.68",
"AZ_GÜLTIGE_STIMMZETTEL": 1682,
"AZ_JA_STIMMEN": 824
}
,
{
"GEMEINDE": "Pfungen",
"BEZIRK": "Winterthur",
"STIMMBETEILIGUNG": "   49.08",
"AZ_GÜLTIGE_STIMMZETTEL": 790,
"AZ_JA_STIMMEN": 463
}
,
{
"GEMEINDE": "Rickenbach",
"BEZIRK": "Winterthur",
"STIMMBETEILIGUNG": "   53.55",
"AZ_GÜLTIGE_STIMMZETTEL": 928,
"AZ_JA_STIMMEN": 445
}
,
{
"GEMEINDE": "Schlatt",
"BEZIRK": "Winterthur",
"STIMMBETEILIGUNG": "   51.67",
"AZ_GÜLTIGE_STIMMZETTEL": 255,
"AZ_JA_STIMMEN": 145
}
,
{
"GEMEINDE": "Seuzach",
"BEZIRK": "Winterthur",
"STIMMBETEILIGUNG": "   53.61",
"AZ_GÜLTIGE_STIMMZETTEL": 2603,
"AZ_JA_STIMMEN": 1292
}
,
{
"GEMEINDE": "Turbenthal",
"BEZIRK": "Winterthur",
"STIMMBETEILIGUNG": "   43.75",
"AZ_GÜLTIGE_STIMMZETTEL": 1167,
"AZ_JA_STIMMEN": 709
}
,
{
"GEMEINDE": "Wiesendangen",
"BEZIRK": "Winterthur",
"STIMMBETEILIGUNG": "   55.34",
"AZ_GÜLTIGE_STIMMZETTEL": 2217,
"AZ_JA_STIMMEN": 1066
}
,
{
"GEMEINDE": "Winterthur",
"BEZIRK": "Winterthur",
"STIMMBETEILIGUNG": "   48.18",
"AZ_GÜLTIGE_STIMMZETTEL": 28956,
"AZ_JA_STIMMEN": 16909
}
,
{
"GEMEINDE": "Zell",
"BEZIRK": "Winterthur",
"STIMMBETEILIGUNG": "   44.94",
"AZ_GÜLTIGE_STIMMZETTEL": 1500,
"AZ_JA_STIMMEN": 894
}
,
{
"GEMEINDE": "Zürich",
"BEZIRK": "Zürich",
"STIMMBETEILIGUNG": "   48.52",
"AZ_GÜLTIGE_STIMMZETTEL": 101177,
"AZ_JA_STIMMEN": 58673
}
]
